Workbook

Sheet Hensoldt AG
B2: Hensoldt AG Equity Research Report
B5: Table of Contents:
B7: 1. Inputs | H7: Implied Share Price 1 | J7: ='DCF Valuation '!E44 -> 61.208704 | K7: €/share | L7: (Using Terminal Value)
B9: 2. Income Statement | H9: Implied Share Price 2 | J9: ='DCF Valuation '!K44 -> 48.726513 | K9: €/share | L9: (Using Exit Multiple)
B11: 3. Balance Sheet
H12: Current Price | J12: 85.4 | K12: €/share
B13: 4. Cash Flow Statement
H14: Upside Potential 1: | J14: =(J7-J12)/J7 -> -0.39522641
B15: Forecast Sheets:
H16: Upside Potential 2: | J16: =(J9-J12)/J9 -> -0.75263926
B17: 5. Revenue/Expense Forecast
B19: 6. Fixed Asset Forecast
H20: Colour Code
B21: 7. Working Capital / Other Assets | H21: Green: Links to another sheet
H22: Purple: Links to same sheet
B23: 8. Debt & Cash Forecast | H23: Black: Calculations
H24: Red: Discretionary Inputs
B25: Output: | H25: Blue: hard-coded Inputs
B27: 9. DCF Modelling
B29: 10. Competitors KPI's

Sheet Inputs
B1: =_xlfn.CONCAT(C7, " - ", "Inputs -", " In", " ", C9, " ", C10) -> HAG - Inputs - In Euro millions
A4: Company related inputs
E5: Scenarios | H5: Inputs/Assumptions to be altered | K5: Revenue & Expenses: | P5: Fixed Asset Forecast: | T5: Working Capital: | Y5: Debt & Cash: | AC5: Version:
B6: Company Name | C6: Hensoldt AG | E6: 1 is the most pessimistic assumption
B7: Company short Name | C7: HAG | E7: 2 is a realistic asumption | K7: Revenue Conversion Rate | N7: 3 | P7: Capex | R7: 3 | T7: Inventories | W7: 3 | Y7: Debt Policy | AA7: 1
B8: Latest financial year end | C8: 45657 | E8: 3 is the optimistic forecast | K8: Revenue Growth Rate | N8: 3 | P8: D&A | R8: 3 | Y8: Dividend Policy | AA8: 1 | AB8: <- | AC8: 2
B9: Currency | C9: Euro | E9: 4 is - if available - companies own guidance | K9: Book to Bill Ratio | N9: 3 | P9: Disposals | R9: 3 | T9: Trade Recievables | W9: 3 | Y9: Intrest Income Scenario | AA9: 2
B10: Units | C10: millions | K10: Cost of Sales | N10: 4 | T10: Contract Assets | W10: 3 | Y10: Intrest Expense Scenario | AA10: 2
K11: SG&A | N11: 3 | T11: Trade Payable | W11: 3 | Y11: Main Intrest Rate | AA11: 4
K12: R&D | N12: 3 | T12: Contract Liabilites | W12: 3
B13: Implied Share Price 1 | C13: ='DCF Valuation '!E44 -> 61.208704 | D13: €/share | E13: (Using Terminal Value) | K13: Other Income | N13: 3 | Y13: Target Levrage ratio | AA13: 2
T14: Other current assets | W14: 3 | Y14: Deffered Tax Liabilities | AA14: 1
B15: Implied Share Price 2 | C15: ='DCF Valuation '!K44 -> 48.726513 | D15: €/share | E15: (Using Exit Multiple) | T15: Other Current Liabilities | W15: 3 | Y15: Provisions % of Revenue | AA15: 0.3
T16: Other Non-current Liabiltiy | W16: 2 | Y16: Intrest rate Spread (Leases) | AA16: 0.0283
Y17: Intrest rate Spead (Debt) | AA17: 0.0175
Y18: Minimum Cash reserce | AA18: 0.3

Sheet IS Neu
A1: =_xlfn.CONCAT(Inputs!C7, " - ", "Income Statement", " - ", "in ", Inputs!C9, " ", Inputs!C10) -> HAG - Income Statement - in Euro millions
B4: Financial year end | D4: =EDATE(Inputs!$C$8, D5*12) -> 43830 | E4: =EDATE(Inputs!$C$8, E5*12) -> 44196 | F4: =EDATE(Inputs!$C$8, F5*12) -> 44561 | G4: =EDATE(Inputs!$C$8, G5*12) -> 44926 | H4: =EDATE(Inputs!$C$8, H5*12) -> 45291 | I4: =EDATE(Inputs!$C$8, I5*12) -> 45657 | J4: =EDATE(Inputs!$C$8, J5*12) -> 46022 | K4: =EDATE(Inputs!$C$8, K5*12) -> 46387 | ... N4: =EDATE(Inputs!$C$8, N5*12) -> 47483 | P4: Assumptions & Relevant Data Points
B5: Time-line counter | D5: -5 | E5: -4 | F5: -3 | G5: -2 | H5: -1 | I5: 0 | J5: 1 | K5: 2 | L5: 3 | M5: 4 | N5: 5 | P5: Tax:
B6: Currency and units | D6: =_xlfn.CONCAT(Inputs!$C$9, " ", Inputs!$C$10) -> Euro millions | E6: =_xlfn.CONCAT(Inputs!$C$9, " ", Inputs!$C$10) -> Euro millions | F6: =_xlfn.CONCAT(Inputs!$C$9, " ", Inputs!$C$10) -> Euro millions | G6: =_xlfn.CONCAT(Inputs!$C$9, " ", Inputs!$C$10) -> Euro millions | H6: =_xlfn.CONCAT(Inputs!$C$9, " ", Inputs!$C$10) -> Euro millions | I6: =_xlfn.CONCAT(Inputs!$C$9, " ", Inputs!$C$10) -> Euro millions | J6: =_xlfn.CONCAT(Inputs!$C$9, " ", Inputs!$C$10) -> Euro millions | K6: =_xlfn.CONCAT(Inputs!$C$9, " ", Inputs!$C$10) -> Euro millions | ... N6: =_xlfn.CONCAT(Inputs!$C$9, " ", Inputs!$C$10) -> Euro millions | P6: Tax Rate as shown in Annual report is on average 28,3% in Germany,
B7: Time-Stamp | D7: =IF(D5<=0, "Historical", "Forecasted") -> Historical | E7: =IF(E5<=0, "Historical", "Forecasted") -> Historical | F7: =IF(F5<=0, "Historical", "Forecasted") -> Historical | G7: =IF(G5<=0, "Historical", "Forecasted") -> Historical | H7: =IF(H5<=0, "Historical", "Forecasted") -> Historical | I7: =IF(I5<=0, "Historical", "Forecasted") -> Historical | J7: =IF(J5<=0, "Historical", "Forecasted") -> Forecasted | K7: =IF(K5<=0, "Historical", "Forecasted") -> Forecasted | ... N7: =IF(N5<=0, "Historical", "Forecasted") -> Forecasted | P7: used here to forecast the income tax burden with deferred taxed being used in 2024 to reduce the tax burden
P8: Subsidiaries in foreign countries are taxed individually, making overall taxation difficult to forecast
B9: Standardised Income Statement
P10: Other Non-Op. Income:
B11: Top Line & Gross Profit | P11: Other Non-Operating Income kept at 0 due to small impact/discretionary nature
B12: Revenue | D12: =SUMIF($J$40:$J$61,$B$12,D40:D61) -> 1114.2 | E12: =SUMIF($J$40:$J$61,$B$12,E40:E61) -> 1206.9 | F12: =SUMIF($J$40:$J$61,$B$12,F40:F61) -> 1474 | G12: =SUMIF($J$40:$J$61,$B$12,G40:G61) -> 1707 | H12: =SUMIF($J$40:$J$61,$B$12,H40:H61) -> 1847 | I12: =SUMIF($J$40:$J$61,$B$12,I40:I61) -> 2240 | J12: ='Revenue & Expenses (updated)'!M22 -> 2800 | K12: ='Revenue & Expenses (updated)'!N22 -> 2930.004 | L12: ='Revenue & Expenses (updated)'!O22 -> 3662.0577 | M12: ='Revenue & Expenses (updated)'!P22 -> 4236.7788 | N12: ='Revenue & Expenses (updated)'!Q22 -> 5090.2078
B13: Cost of Sales (COGS) | D13: =SUMIF($J$40:$J$61,$B$13,D40:D61) -> -859.3 | E13: =SUMIF($J$40:$J$61,$B$13,E40:E61) -> -936.1 | F13: =SUMIF($J$40:$J$61,$B$13,F40:F61) -> -1144 | G13: =SUMIF($J$40:$J$61,$B$13,G40:G61) -> -1314 | H13: =SUMIF($J$40:$J$61,$B$13,H40:H61) -> -1427 | I13: =SUMIF($J$40:$J$61,$B$13,I40:I61) -> -1732 | J13: ='Revenue & Expenses (updated)'!M45*-1 -> -1960 | K13: ='Revenue & Expenses (updated)'!N45*-1 -> -2021.7028 | L13: ='Revenue & Expenses (updated)'!O45*-1 -> -2490.1992 | M13: ='Revenue & Expenses (updated)'!P45*-1 -> -2881.0096 | N13: ='Revenue & Expenses (updated)'!Q45*-1 -> -3461.3413 | P13: Other Financial Net
B14: Gross Profit | D14: =SUM(D12:D13) -> 254.9 | E14: =SUM(E12:E13) -> 270.8 | F14: =SUM(F12:F13) -> 330 | G14: =SUM(G12:G13) -> 393 | H14: =SUM(H12:H13) -> 420 | I14: =SUM(I12:I13) -> 508 | J14: =SUM(J12:J13) -> 840 | K14: =SUM(K12:K13) -> 908.30124 | ... N14: =SUM(N12:N13) -> 1628.8665 | P14: Also kept at 0, since those are miscallanious items which dont have a large impact but are difficult to forecast
B15: SG&A | D15: =SUMIF($J$40:$J$61,$B$15,D40:D61) -> -161.1 | E15: =SUMIF($J$40:$J$61,$B$15,E40:E61) -> -177.4 | F15: =SUMIF($J$40:$J$61,$B$15,F40:F61) -> -182 | G15: =SUMIF($J$40:$J$61,$B$15,G40:G61) -> -199 | H15: =SUMIF($J$40:$J$61,$B$15,H40:H61) -> -229 | I15: =SUMIF($J$40:$J$61,$B$15,I40:I61) -> -290 | J15: ='Revenue & Expenses (updated)'!M47*-1 -> -252 | K15: ='Revenue & Expenses (updated)'!N47*-1 -> -263.70036 | L15: ='Revenue & Expenses (updated)'!O47*-1 -> -329.58519 | M15: ='Revenue & Expenses (updated)'!P47*-1 -> -381.31009 | N15: ='Revenue & Expenses (updated)'!Q47*-1 -> -458.1187
B16: R&D | D16: =SUMIF($J$40:$J$61,$B$16,D40:D61) -> -31 | E16: =SUMIF($J$40:$J$61,$B$16,E40:E61) -> -25.1 | F16: =SUMIF($J$40:$J$61,$B$16,F40:F61) -> -31 | G16: =SUMIF($J$40:$J$61,$B$16,G40:G61) -> -36 | H16: =SUMIF($J$40:$J$61,$B$16,H40:H61) -> -30 | I16: =SUMIF($J$40:$J$61,$B$16,I40:I61) -> -32 | J16: ='Revenue & Expenses (updated)'!M49*-1 -> -112 | K16: ='Revenue & Expenses (updated)'!N49*-1 -> -117.20016 | L16: ='Revenue & Expenses (updated)'!O49*-1 -> -146.48231 | M16: ='Revenue & Expenses (updated)'!P49*-1 -> -169.47115 | N16: ='Revenue & Expenses (updated)'!Q49*-1 -> -203.60831
B17: Other Operating Income/(Expense) Net | D17: =SUMIF($J$40:$J$61,$B$17,D40:D61) -> -0.7 | E17: =SUMIF($J$40:$J$61,$B$17,E40:E61) -> 0.2 | F17: =SUMIF($J$40:$J$61,$B$17,F40:F61) -> 9 | G17: =SUMIF($J$40:$J$61,$B$17,G40:G61) -> 8 | H17: =SUMIF($J$40:$J$61,$B$17,H40:H61) -> 6 | I17: =SUMIF($J$40:$J$61,$B$17,I40:I61) -> -2 | J17: 0 | K17: 0 | L17: 0 | M17: 0 | N17: 0
B18: EBIT | D18: =SUM(D14:D17) -> 62.1 | E18: =SUM(E14:E17) -> 68.5 | F18: =SUM(F14:F17) -> 126 | G18: =SUM(G14:G17) -> 166 | H18: =SUM(H14:H17) -> 167 | I18: =SUM(I14:I17) -> 184 | J18: =SUM(J14:J17) -> 476 | K18: =SUM(K14:K17) -> 527.40072 | ... N18: =SUM(N14:N17) -> 967.13948
B19: Interest Expense | D19: =SUMIF($J$40:$J$61,$B$19,D40:D61) -> -83.5 | E19: =SUMIF($J$40:$J$61,$B$19,E40:E61) -> -137.7 | F19: =SUMIF($J$40:$J$61,$B$19,F40:F61) -> -42 | G19: =SUMIF($J$40:$J$61,$B$19,G40:G61) -> -44 | H19: =SUMIF($J$40:$J$61,$B$19,H40:H61) -> -82 | I19: =SUMIF($J$40:$J$61,$B$19,I40:I61) -> -100 | J19: ='Debt & Cash'!K44 -> -60.20552 | K19: ='Debt & Cash'!L44 -> -76.780831 | L19: ='Debt & Cash'!M44 -> -79.521158 | M19: ='Debt & Cash'!N44 -> -66.743713 | N19: ='Debt & Cash'!O44 -> -72.503619
B20: Interest Income | D20: =SUMIF($J$40:$J$61,$B$20,D40:D61) -> 58.9 | E20: =SUMIF($J$40:$J$61,$B$20,E40:E61) -> 4 | F20: =SUMIF($J$40:$J$61,$B$20,F40:F61) -> 4 | G20: =SUMIF($J$40:$J$61,$B$20,G40:G61) -> 9 | H20: =SUMIF($J$40:$J$61,$B$20,H40:H61) -> 18 | I20: =SUMIF($J$40:$J$61,$B$20,I40:I61) -> 31 | J20: ='Debt & Cash'!K51 -> 29.66 | K20: ='Debt & Cash'!L51 -> 31.383815 | L20: ='Debt & Cash'!M51 -> 32.048631 | M20: ='Debt & Cash'!N51 -> 37.291034 | N20: ='Debt & Cash'!O51 -> 42.379228
B21: Other Fin Net | D21: =SUMIF($J$40:$J$61,$B$21,D40:D61) -> -1.9 | E21: =SUMIF($J$40:$J$61,$B$21,E40:E61) -> -10 | F21: =SUMIF($J$40:$J$61,$B$21,F40:F61) -> -3 | G21: =SUMIF($J$40:$J$61,$B$21,G40:G61) -> -1 | H21: =SUMIF($J$40:$J$61,$B$21,H40:H61) -> -7 | I21: =SUMIF($J$40:$J$61,$B$21,I40:I61) -> 1 | J21: 0 | K21: 0 | L21: 0 | M21: 0 | N21: 0
B22: EBT | D22: =SUM(D18:D21) -> 35.6 | E22: =SUM(E18:E21) -> -75.2 | F22: =SUM(F18:F21) -> 85 | G22: =SUM(G18:G21) -> 130 | H22: =SUM(H18:H21) -> 96 | I22: =SUM(I18:I21) -> 116 | J22: =SUM(J18:J21) -> 445.45448 | K22: =SUM(K18:K21) -> 482.0037 | ... N22: =SUM(N18:N21) -> 937.01509
B23: Income Taxes | C23: 0.283 | D23: =SUMIF($J$40:$J$61,$B$23,D40:D61) -> -27.4 | E23: =SUMIF($J$40:$J$61,$B$23,E40:E61) -> 10.7 | F23: =SUMIF($J$40:$J$61,$B$23,F40:F61) -> -22 | G23: =SUMIF($J$40:$J$61,$B$23,G40:G61) -> -49 | H23: =SUMIF($J$40:$J$61,$B$23,H40:H61) -> -36 | I23: =SUMIF($J$40:$J$61,$B$23,I40:I61) -> -12 | J23: =J22*$C$23*-1 -> -126.06362 | K23: =K22*$C$23*-1 -> -136.40705 | L23: =L22*$C$23*-1 -> -183.47412 | M23: =M22*$C$23*-1 -> -219.47649 | N23: =N22*$C$23*-1 -> -265.17527
B24: Net Income | D24: =SUM(D22:D23) -> 8.2 | E24: =SUM(E22:E23) -> -64.5 | F24: =SUM(F22:F23) -> 63 | G24: =SUM(G22:G23) -> 81 | H24: =SUM(H22:H23) -> 60 | I24: =SUM(I22:I23) -> 104 | J24: =J22+J23 -> 319.39086 | K24: =K22+K23 -> 345.59666 | L24: =L22+L23 -> 464.84432 | M24: =M22+M23 -> 556.05881 | N24: =N22+N23 -> 671.83982
B25: Attributable to Owners | D25: =SUMIF($J$40:$J$61,$B$25,D40:D61) -> 5.9 | E25: =SUMIF($J$40:$J$61,$B$25,E40:E61) -> -65.2 | F25: =SUMIF($J$40:$J$61,$B$25,F40:F61) -> 63 | G25: =SUMIF($J$40:$J$61,$B$25,G40:G61) -> 78 | H25: =SUMIF($J$40:$J$61,$B$25,H40:H61) -> 56 | I25: =SUMIF($J$40:$J$61,$B$25,I40:I61) -> 108 | J25: =J24-2 -> 317.39086 | K25: =K24-2 -> 343.59666 | L25: =L24-2 -> 462.84432 | M25: =M24-2 -> 554.05881 | N25: =N24-2 -> 669.83982 | P25: Non-Controlling Interest:
B26: Attributable to NCI | D26: =SUMIF($J$40:$J$61,$B$26,D40:D61) -> 2.3 | E26: =SUMIF($J$40:$J$61,$B$26,E40:E61) -> 0.7 | F26: =SUMIF($J$40:$J$61,$B$26,F40:F61) -> 0 | G26: =SUMIF($J$40:$J$61,$B$26,G40:G61) -> 2 | H26: =SUMIF($J$40:$J$61,$B$26,H40:H61) -> 2 | I26: =SUMIF($J$40:$J$61,$B$26,I40:I61) -> -2 | J26: 2 | K26: 2 | L26: 2 | M26: 2 | N26: 2 | P26: 30% SA; 6,7% US; 15% FR; 9,4% DE are non-controlling interest in Subsidiaries
B27: Per Share | D27: =D28 -> 0.07 | E27: =E28 -> -0.75 | F27: =F28 -> 0.6 | G27: =G28 -> 0.75 | H27: =H28 -> 0.53 | I27: =I28 -> 0.93 | J27: =J24/$C$28 -> 2.7533695 | K27: =K24/$C$28 -> 2.9792815 | L27: =L24/$C$28 -> 4.0072786 | M27: =M24/$C$28 -> 4.7936104 | N27: =N24/$C$28 -> 5.7917226 | P27: since the Holding company is 25% owned by Leonardo, 25% German Government and 50% Float, 2 mn as an average of the past years is assumed
B28: Earnings Per Share (EPS) Number of Shares: | C28: 116 | D28: =D61 -> 0.07 | E28: =E61 -> -0.75 | F28: =F61 -> 0.6 | G28: =G61 -> 0.75 | H28: =H61 -> 0.53 | I28: =I61 -> 0.93
P29: EBITDA:
B30: EBITDA | D30: =SUM(D18, D31) -> 191.7 | E30: =SUM(E18, E31) -> 189.3 | F30: =SUM(F18, F31) -> 252 | G30: =SUM(G18, G31) -> 269 | H30: =SUM(H18, H31) -> 284 | I30: =SUM(I18, I31) -> 346 | J30: =SUM(J18, J31) -> 739.0373 | K30: =SUM(K18, K31) -> 798.39069 | ... N30: =SUM(N18, N31) -> 1286.7258 | P30: For final calculation, the calculated EBIT needs to be adjusted by the D&A.
B31: D&A | D31: ='CF Neu '!G53 -> 129.6 | E31: ='CF Neu '!H53 -> 120.8 | F31: ='CF Neu '!I53 -> 126 | G31: ='CF Neu '!J53 -> 103 | H31: ='CF Neu '!K53 -> 117 | I31: ='CF Neu '!L53 -> 162 | J31: ='FA-Forecast (updated)'!M84 -> 263.0373 | K31: ='FA-Forecast (updated)'!N84 -> 270.98997 | L31: ='FA-Forecast (updated)'!O84 -> 279.6455 | M31: ='FA-Forecast (updated)'!P84 -> 296.85834 | N31: ='FA-Forecast (updated)'!Q84 -> 319.58634
B33: Margin (EBITDA) | D33: =D30/D12 -> 0.1720517 | E33: =E30/E12 -> 0.15684812 | F33: =F30/F12 -> 0.17096336 | G33: =G30/G12 -> 0.15758641 | H33: =H30/H12 -> 0.15376286 | I33: =I30/I12 -> 0.15446429 | J33: =J30/J12 -> 0.26394189 | K33: =K30/K12 -> 0.27248792 | ... N33: =N30/N12 -> 0.25278454
B36: Cash | D36: ='BS Neu'!D26 -> 137.4 | E36: ='BS Neu'!E26 -> 645.5 | F36: ='BS Neu'!F26 -> 529 | G36: ='BS Neu'!G26 -> 460 | H36: ='BS Neu'!H26 -> 802 | I36: ='BS Neu'!I26 -> 733 | J36: ='BS Neu'!J26 -> 936.21801 | K36: ='BS Neu'!K26 -> 1136.5754 | ... N36: ='BS Neu'!N26 -> 2223.6018
B37: Cash Safety lvl | D37: =D36/D12 -> 0.12331718 | E37: =E36/E12 -> 0.53484133 | F37: =F36/F12 -> 0.35888738 | G37: =G36/G12 -> 0.26947862 | H37: =H36/H12 -> 0.43421765 | I37: =I36/I12 -> 0.32723214 | J37: =J36/J12 -> 0.33436357 | K37: =K36/K12 -> 0.38790916 | ... N37: =N36/N12 -> 0.43683911
B39: Year | D39: 2019 | E39: 2020 | F39: 2021 | G39: 2022 | H39: 2023 | I39: 2024
B40: Revenue | D40: 1114.2 | E40: 1206.9 | F40: 1474 | G40: 1707 | H40: 1847 | I40: 2240 | J40: Revenue
B41: Cost of sales | D41: -859.3 | E41: -936.1 | F41: -1144 | G41: -1314 | H41: -1427 | I41: -1732 | J41: Cost of Sales (COGS)
B42: Gross profit | D42: 254.9 | E42: 270.8 | F42: 330 | G42: 393 | H42: 420 | I42: 508 | J42: Gross Profit
B43: Selling and distribution expenses | D43: -84.8 | E43: -90.2 | F43: -99 | G43: -107 | H43: -111 | I43: -128 | J43: SG&A
B44: General administrative expenses | D44: -76.3 | E44: -87.2 | F44: -83 | G44: -92 | H44: -118 | I44: -162 | J44: SG&A
B45: Research and development costs | D45: -31 | E45: -25.1 | F45: -31 | G45: -36 | H45: -30 | I45: -32 | J45: R&D
B46: Other operating income | D46: 25.3 | E46: 18.9 | F46: 29 | G46: 21 | H46: 22 | I46: 22 | J46: Other Operating Income/(Expense) Net
B47: Other operating expenses | D47: -24.8 | E47: -16.1 | F47: -18 | G47: -21 | H47: -21 | I47: -24 | J47: Other Operating Income/(Expense) Net
B48: Share of profit / loss from investments accounted for using the equity method | D48: -1.2 | E48: -2.6 | F48: -2 | G48: 0 | H48: 0 | I48: 3 | J48: Other Operating Income/(Expense) Net
B49: Other income / expense from investments | D49: 0 | E49: 0 | F49: 0 | G49: 8 | H49: 5 | I49: -3 | J49: Other Operating Income/(Expense) Net
B50: Earnings before financial result and income taxes (EBIT) | D50: 62.1 | E50: 68.5 | F50: 126 | G50: 166 | H50: 166 | I50: 185 | J50: EBIT
B51: Interest income | D51: 58.9 | E51: 4 | F51: 4 | G51: 9 | H51: 18 | I51: 31 | J51: Interest Income
... B53: Other finance income / cost | D53: -1.9 | E53: -10 | F53: -3 | G53: -1 | H53: -7 | I53: 1 | J53: Other Fin Net
B54: Finance result | D54: -26.5 | E54: -143.7 | F54: -41 | G54: -37 | H54: -72 | I54: -68
B55: Earnings before income taxes (EBT) | D55: 35.6 | E55: -75.2 | F55: 85 | G55: 130 | H55: 94 | I55: 117 | J55: EBT
B56: Income taxes | D56: -27.4 | E56: 10.7 | F56: -22 | G56: -49 | H56: -36 | I56: -12 | J56: Income Taxes
B57: Group profit / loss | D57: 8.2 | E57: -64.5 | F57: 63 | G57: 80 | H57: 58 | I57: 106 | J57: EBT
B58: thereof attributable to the owners of HENSOLDT AG | D58: 5.9 | E58: -65.2 | F58: 63 | G58: 78 | H58: 56 | I58: 108 | J58: Attributable to Owners
B59: thereof attributable to non-controlling interests | D59: 2.3 | E59: 0.7 | F59: 0 | G59: 2 | H59: 2 | I59: -2 | J59: Attributable to NCI
B60: Earnings per share
B61: Basic and diluted earnings per share (EUR) | D61: 0.07 | E61: -0.75 | F61: 0.6 | G61: 0.75 | H61: 0.53 | I61: 0.93 | J61: Earnings Per Share (EPS)

Sheet BS Neu
A1: =_xlfn.CONCAT(Inputs!C7, " - ", "Balance Sheet", " - ", "in ", Inputs!C9, " ", Inputs!C10) -> HAG - Balance Sheet - in Euro millions
B4: Financial year end | D4: =EDATE(Inputs!$C$8, D5*12) -> 43830 | E4: =EDATE(Inputs!$C$8, E5*12) -> 44196 | F4: =EDATE(Inputs!$C$8, F5*12) -> 44561 | G4: =EDATE(Inputs!$C$8, G5*12) -> 44926 | H4: =EDATE(Inputs!$C$8, H5*12) -> 45291 | I4: =EDATE(Inputs!$C$8, I5*12) -> 45657 | J4: =EDATE(Inputs!$C$8, J5*12) -> 46022 | K4: =EDATE(Inputs!$C$8, K5*12) -> 46387 | ... N4: =EDATE(Inputs!$C$8, N5*12) -> 47483
B5: Time-line counter | D5: -5 | E5: -4 | F5: -3 | G5: -2 | H5: -1 | I5: 0 | J5: 1 | K5: 2 | L5: 3 | M5: 4 | N5: 5
B6: Currency and units | D6: =_xlfn.CONCAT(Inputs!$C$9, " ", Inputs!$C$10) -> Euro millions | E6: =_xlfn.CONCAT(Inputs!$C$9, " ", Inputs!$C$10) -> Euro millions | F6: =_xlfn.CONCAT(Inputs!$C$9, " ", Inputs!$C$10) -> Euro millions | G6: =_xlfn.CONCAT(Inputs!$C$9, " ", Inputs!$C$10) -> Euro millions | H6: =_xlfn.CONCAT(Inputs!$C$9, " ", Inputs!$C$10) -> Euro millions | I6: =_xlfn.CONCAT(Inputs!$C$9, " ", Inputs!$C$10) -> Euro millions | J6: =_xlfn.CONCAT(Inputs!$C$9, " ", Inputs!$C$10) -> Euro millions | K6: =_xlfn.CONCAT(Inputs!$C$9, " ", Inputs!$C$10) -> Euro millions | ... N6: =_xlfn.CONCAT(Inputs!$C$9, " ", Inputs!$C$10) -> Euro millions
B7: Time-Stamp | D7: =IF(D5<=0, "Historical", "Forecasted") -> Historical | E7: =IF(E5<=0, "Historical", "Forecasted") -> Historical | F7: =IF(F5<=0, "Historical", "Forecasted") -> Historical | G7: =IF(G5<=0, "Historical", "Forecasted") -> Historical | H7: =IF(H5<=0, "Historical", "Forecasted") -> Historical | I7: =IF(I5<=0, "Historical", "Forecasted") -> Historical | J7: =IF(J5<=0, "Historical", "Forecasted") -> Forecasted | K7: =IF(K5<=0, "Historical", "Forecasted") -> Forecasted | ... N7: =IF(N5<=0, "Historical", "Forecasted") -> Forecasted
B10: Standardised Balance sheet
B12: Assets
B13: Non-Current Assets
A14: x | B14: Goodwill & Intangibles | D14: =SUMIF($J$66:$J$111, $B$14,D66:D111) -> 1040.5 | E14: =SUMIF($J$66:$J$111, $B$14,E66:E111) -> 1023.4 | F14: =SUMIF($J$66:$J$111, $B$14,F66:F111) -> 1043 | G14: =SUMIF($J$66:$J$111, $B$14,G66:G111) -> 1042 | H14: =SUMIF($J$66:$J$111, $B$14,H66:H111) -> 1057 | I14: =SUMIF($J$66:$J$111, $B$14,I66:I111) -> 1782 | J14: ='FA-Forecast (updated)'!M41 -> 1766.6493 | K14: ='FA-Forecast (updated)'!N41 -> 1746.7553 | L14: ='FA-Forecast (updated)'!O41 -> 1756.9797 | M14: ='FA-Forecast (updated)'!P41 -> 1784.8072 | N14: ='FA-Forecast (updated)'!Q41 -> 1840.4171
A15: x | B15: Property, Plant & Equipment (incl. RoU) | D15: =SUMIF($J$66:$J$111, $B$15, D66:D111) -> 247.8 | E15: =SUMIF($J$66:$J$111, $B$15, E66:E111) -> 246.6 | F15: =SUMIF($J$66:$J$111, $B$15, F66:F111) -> 249 | G15: =SUMIF($J$66:$J$111, $B$15, G66:G111) -> 261 | H15: =SUMIF($J$66:$J$111, $B$15, H66:H111) -> 329 | I15: =SUMIF($J$66:$J$111, $B$15, I66:I111) -> 451 | J15: ='FA-Forecast (updated)'!M51 -> 624.16865 | K15: ='FA-Forecast (updated)'!N51 -> 722.74923 | L15: ='FA-Forecast (updated)'!O51 -> 869.00526 | M15: ='FA-Forecast (updated)'!P51 -> 1047.7959 | N15: ='FA-Forecast (updated)'!Q51 -> 1276.6266
B16: Investments & Other Fin Assets (NC) | D16: =SUMIF($J$66:$J$111, $B$16, D66:D111) -> 69.1 | E16: =SUMIF($J$66:$J$111, $B$16, E66:E111) -> 12.3 | F16: =SUMIF($J$66:$J$111, $B$16, F66:F111) -> 22 | G16: =SUMIF($J$66:$J$111, $B$16, G66:G111) -> 24 | H16: =SUMIF($J$66:$J$111, $B$16, H66:H111) -> 26 | I16: =SUMIF($J$66:$J$111, $B$16, I66:I111) -> 35 | J16: =I16 -> 35 | K16: =J16 -> 35 | L16: =K16 -> 35 | M16: =L16 -> 35 | N16: =M16 -> 35 | O16: (Kept constant, since there is no clear indication if the company intends to increase/decrease this)
B17: Other Non-Current Assets | D17: =SUMIF($J$66:$J$111, $B$17, D66:D111) -> 4.9 | E17: =SUMIF($J$66:$J$111, $B$17, E66:E111) -> 4.8 | F17: =SUMIF($J$66:$J$111, $B$17, F66:F111) -> 3 | G17: =SUMIF($J$66:$J$111, $B$17, G66:G111) -> 2 | H17: =SUMIF($J$66:$J$111, $B$17, H66:H111) -> 3 | I17: =SUMIF($J$66:$J$111, $B$17, I66:I111) -> 20 | J17: ='BS Neu'!I17 -> 20 | K17: ='BS Neu'!J17 -> 20 | L17: ='BS Neu'!K17 -> 20 | M17: ='BS Neu'!L17 -> 20 | N17: ='BS Neu'!M17 -> 20
B18: Deferred Tax Assets | D18: =SUMIF($J$66:$J$111, $B$18, D66:D111) -> 30.4 | E18: =SUMIF($J$66:$J$111, $B$18, E66:E111) -> 26.3 | F18: =SUMIF($J$66:$J$111, $B$18, F66:F111) -> 11 | G18: =SUMIF($J$66:$J$111, $B$18, G66:G111) -> 6 | H18: =SUMIF($J$66:$J$111, $B$18, H66:H111) -> 9 | I18: =SUMIF($J$66:$J$111, $B$18, I66:I111) -> 1 | J18: 0 | K18: 0 | L18: 0 | M18: 0 | N18: 0
B19: Total Non-Current Assets | D19: =SUM(D14:D18) -> 1392.7 | E19: =SUM(E14:E18) -> 1313.4 | F19: =SUM(F14:F18) -> 1328 | G19: =SUM(G14:G18) -> 1335 | H19: =SUM(H14:H18) -> 1424 | I19: =SUM(I14:I18) -> 2289 | J19: =SUM(J13:J18) -> 2445.8179 | K19: =SUM(K13:K18) -> 2524.5045 | L19: =SUM(L13:L18) -> 2680.9849 | M19: =SUM(M13:M18) -> 2887.6031 | N19: =SUM(N13:N18) -> 3172.0437
B21: Current Assets
A22: x | B22: Inventories | D22: =SUMIF($J$66:$J$111, $B$22,D66:D111) -> 411.1 | E22: =SUMIF($J$66:$J$111, $B$22,E66:E111) -> 403.7 | F22: =SUMIF($J$66:$J$111, $B$22,F66:F111) -> 444 | G22: =SUMIF($J$66:$J$111, $B$22,G66:G111) -> 516 | H22: =SUMIF($J$66:$J$111, $B$22,H66:H111) -> 625 | I22: =SUMIF($J$66:$J$111, $B$22,I66:I111) -> 719 | J22: ='WC & other Assets (updated) '!M16 -> 751.78082 | K22: ='WC & other Assets (updated) '!N16 -> 775.44763 | L22: ='WC & other Assets (updated) '!O16 -> 955.14491 | M22: ='WC & other Assets (updated) '!P16 -> 1105.0448 | N22: ='WC & other Assets (updated) '!Q16 -> 1327.6378
A23: x | B23: Trade Receivables | D23: =SUMIF($J$66:$J$111, $B$23,D66:D111) -> 290.8 | E23: =SUMIF($J$66:$J$111, $B$23,E66:E111) -> 282 | F23: =SUMIF($J$66:$J$111, $B$23,F66:F111) -> 309 | G23: =SUMIF($J$66:$J$111, $B$23,G66:G111) -> 323 | H23: =SUMIF($J$66:$J$111, $B$23,H66:H111) -> 382 | I23: =SUMIF($J$66:$J$111, $B$23,I66:I111) -> 426 | J23: ='WC & other Assets (updated) '!M25 -> 421.91781 | K23: ='WC & other Assets (updated) '!N25 -> 441.50745 | L23: ='WC & other Assets (updated) '!O25 -> 551.81691 | M23: ='WC & other Assets (updated) '!P25 -> 638.41873 | N23: ='WC & other Assets (updated) '!Q25 -> 767.01761
B24: Contract Assets | D24: =SUMIF($J$66:$J$111, $B$24,D66:D111) -> 165.9 | E24: =SUMIF($J$66:$J$111, $B$24,E66:E111) -> 204.4 | F24: =SUMIF($J$66:$J$111, $B$24,F66:F111) -> 170 | G24: =SUMIF($J$66:$J$111, $B$24,G66:G111) -> 182 | H24: =SUMIF($J$66:$J$111, $B$24,H66:H111) -> 196 | I24: =SUMIF($J$66:$J$111, $B$24,I66:I111) -> 385 | J24: ='WC & other Assets (updated) '!M23 -> 308 | K24: ='WC & other Assets (updated) '!N23 -> 322.30044 | L24: ='WC & other Assets (updated) '!O23 -> 402.82635 | M24: ='WC & other Assets (updated) '!P23 -> 466.04567 | N24: ='WC & other Assets (updated) '!Q23 -> 559.92286
B25: Other Current Assets | D25: =SUMIF($J$66:$J$111, $B$25,D66:D111) -> 58.1 | E25: =SUMIF($J$66:$J$111, $B$25,E66:E111) -> 98.6 | F25: =SUMIF($J$66:$J$111, $B$25,F66:F111) -> 177 | G25: =SUMIF($J$66:$J$111, $B$25,G66:G111) -> 163 | H25: =SUMIF($J$66:$J$111, $B$25,H66:H111) -> 150 | I25: =SUMIF($J$66:$J$111, $B$25,I66:I111) -> 143 | J25: ='Debt & Cash'!K107+'WC & other Assets (updated) '!M70 -> 301.38087 | K25: ='Debt & Cash'!L107+'WC & other Assets (updated) '!N70 -> 315.37399 | L25: ='Debt & Cash'!M107+'WC & other Assets (updated) '!O70 -> 394.16934 | M25: ='Debt & Cash'!N107+'WC & other Assets (updated) '!P70 -> 456.03004 | N25: ='Debt & Cash'!O107+'WC & other Assets (updated) '!Q70 -> 547.88974
B26: Cash & Cash Equivalents | D26: =SUMIF($J$66:$J$111, $B$26,D66:D111) -> 137.4 | E26: =SUMIF($J$66:$J$111, $B$26,E66:E111) -> 645.5 | F26: =SUMIF($J$66:$J$111, $B$26,F66:F111) -> 529 | G26: =SUMIF($J$66:$J$111, $B$26,G66:G111) -> 460 | H26: =SUMIF($J$66:$J$111, $B$26,H66:H111) -> 802 | I26: =SUMIF($J$66:$J$111, $B$26,I66:I111) -> 733 | J26: =I26+'CF Neu '!M38 -> 936.21801 | K26: =J26+'CF Neu '!N38 -> 1136.5754 | L26: =K26+'CF Neu '!O38 -> 1486.0689 | M26: =L26+'CF Neu '!P38 -> 1825.2819 | N26: =M26+'CF Neu '!Q38 -> 2223.6018 | O26: (THIS IS A PLUG, which will be balanced through the other items. Not forecasted as a %)
B27: Total Current Assets | D27: =SUM(D22:D26) -> 1063.3 | E27: =SUM(E22:E26) -> 1634.2 | F27: =SUM(F22:F26) -> 1629 | G27: =SUM(G22:G26) -> 1644 | H27: =SUM(H22:H26) -> 2155 | I27: =SUM(I22:I26) -> 2406 | J27: =SUM(J22:J26) -> 2719.2975 | K27: =SUM(K22:K26) -> 2991.2049 | ... N27: =SUM(N22:N26) -> 5426.0698 | O27: (Cash is not forecasted but a result of the Cash-Flow Statement Result)
B29: Total Assets | D29: =SUM(D27,D19) -> 2456 | E29: =SUM(E27,E19) -> 2947.6 | F29: =SUM(F27,F19) -> 2957 | G29: =SUM(G27,G19) -> 2979 | H29: =SUM(H27,H19) -> 3579 | I29: =SUM(I27,I19) -> 4695 | J29: =SUM(J27,J19) -> 5165.1154 | K29: =SUM(K27,K19) -> 5515.7094 | ... N29: =SUM(N27,N19) -> 8598.1135
B31: Equity & Liab.
B32: Equity
A33: x | B33: Share Capital | D33: =SUMIF($J$66:$J$112, $B$33, D66:D112) -> 10 | E33: =SUMIF($J$66:$J$112, $B$33, E66:E112) -> 105 | F33: =SUMIF($J$66:$J$112, $B$33, F66:F112) -> 105 | G33: =SUMIF($J$66:$J$112, $B$33, G66:G112) -> 105 | H33: =SUMIF($J$66:$J$112, $B$33, H66:H112) -> 116 | I33: =SUMIF($J$66:$J$112, $B$33, I66:I112) -> 116 | J33: 116 | K33: 116 | L33: 116 | M33: 116 | N33: 116 | O33: (Kept Constant (no capital markets financing -> strong financial position)
B34: Other Reserves (incl. Capital Reserve) | D34: =SUMIF($J$66:$J$112,$B$34, D66:D112) -> 346.9 | E34: =SUMIF($J$66:$J$112,$B$34, E66:E112) -> 510.5 | F34: =SUMIF($J$66:$J$112,$B$34, F66:F112) -> 472 | G34: =SUMIF($J$66:$J$112,$B$34, G66:G112) -> 554 | H34: =SUMIF($J$66:$J$112,$B$34, H66:H112) -> 645 | I34: 508 | J34: 508 | K34: 508 | L34: 508 | M34: 508 | N34: 508 | O34: (Kept constant, since there is no indication/legal guidline forcing the company to keep more of it's excess cash in reserves)
B35: Retained Earnings | D35: =SUMIF($J$66:$J$112,$B$35,D66:D112) -> -215.8 | E35: =SUMIF($J$66:$J$112,$B$35,E66:E112) -> -281.6 | F35: =SUMIF($J$66:$J$112,$B$35,F66:F112) -> -171 | G35: =SUMIF($J$66:$J$112,$B$35,G66:G112) -> -55 | H35: =SUMIF($J$66:$J$112,$B$35,H66:H112) -> 62 | I35: 245 | J35: =I35+'IS Neu'!J24+'CF Neu '!M32 -> 427.05279 | K35: =J35+'IS Neu'!K24+'CF Neu '!N32 -> 617.13095 | L35: =K35+'IS Neu'!L24+'CF Neu '!O32 -> 863.49844 | M35: =L35+'IS Neu'!M24+'CF Neu '!P32 -> 1147.0884 | N35: =M35+'IS Neu'!N24+'CF Neu '!Q32 -> 1476.2899
B36: Equity Attributable to Shareholders | D36: =SUMIF($J$66:J$112,$B$36, D66:D112) -> 141.2 | E36: =SUMIF($J$66:K$112,$B$36, E66:E112) -> 333.9 | F36: =SUMIF($J$66:L$112,$B$36, F66:F112) -> 406 | G36: =SUMIF($J$66:M$112,$B$36, G66:G112) -> 604 | H36: =SUMIF($J$66:N$112,$B$36, H66:H112) -> 822 | I36: =SUM(I33:I35) -> 869 | J36: =SUM(J33:J35) -> 1051.0528 | K36: =SUM(K33:K35) -> 1241.131 | L36: =SUM(L33:L35) -> 1487.4984 | M36: =SUM(M33:M35) -> 1771.0884 | N36: =SUM(N33:N35) -> 2100.2899
B37: Non-Controlling Interests | D37: =SUMIF($J$66:J$112,$B$37, D66:D112) -> 13.6 | E37: =SUMIF($J$66:K$112,$B$37, E66:E112) -> 12.9 | F37: =SUMIF($J$66:L$112,$B$37, F66:F112) -> 11 | G37: =SUMIF($J$66:M$112,$B$37, G66:G112) -> 13 | H37: =SUMIF($J$66:N$112,$B$37, H66:H112) -> 16 | I37: =SUMIF($J$66:O$112,$B$37, I66:I112) -> 14 | J37: =I37 -> 14 | K37: =J37 -> 14 | L37: =K37 -> 14 | M37: =L37 -> 14 | N37: =M37 -> 14 | O37: (Kept constant, because share of other investors in subsidiaries is not likely to change. SA, FR, DE subsidiaries with other shareholders)
B38: Total Equity | D38: =SUM(D36,D37) -> 154.8 | E38: =SUM(E36,E37) -> 346.8 | F38: =SUM(F36,F37) -> 417 | G38: =SUM(G36,G37) -> 617 | H38: =SUM(H36,H37) -> 838 | I38: =SUM(I36,I37) -> 883 | J38: =SUM(J36:J37) -> 1065.0528 | K38: =SUM(K36:K37) -> 1255.131 | L38: =SUM(L36:L37) -> 1501.4984 | M38: =SUM(M36:M37) -> 1785.0884 | N38: =SUM(N36:N37) -> 2114.2899
B40: Liabilities
B41: Non-Current Liabilities
B42: Non-Current Debt (Financing & Lease) | D42: =SUMIF($J$66:J$112,$B$42, D66:D112) -> 1035.2 | E42: =SUMIF($J$66:K$112,$B$42, E66:E112) -> 741.6 | F42: =SUMIF($J$66:L$112,$B$42, F66:F112) -> 761 | G42: =SUMIF($J$66:M$112,$B$42, G66:G112) -> 759 | H42: =SUMIF($J$66:N$112,$B$42, H66:H112) -> 812 | I42: =SUMIF($J$66:O$112,$B$42, I66:I112) -> 1328 | J42: ='Debt & Cash'!K61 -> 1326.6636 | K42: ='Debt & Cash'!L61 -> 1383.0844 | L42: ='Debt & Cash'!M61 -> 1466.4356 | M42: ='Debt & Cash'!N61 -> 1566.8764 | N42: ='Debt & Cash'!O61 -> 1694.8995
B43: Non-Current Provisions | D43: =SUMIF($J$66:J$112,$B$43, D66:D112) -> 413.6 | E43: =SUMIF($J$66:K$112,$B$43, E66:E112) -> 482.6 | F43: =SUMIF($J$66:L$112,$B$43, F66:F112) -> 497 | G43: =SUMIF($J$66:M$112,$B$43, G66:G112) -> 282 | H43: =SUMIF($J$66:N$112,$B$43, H66:H112) -> 357 | I43: =SUMIF($J$66:O$112,$B$43, I66:I112) -> 418 | J43: ='Debt & Cash'!K137 -> 588 | K43: ='Debt & Cash'!L137 -> 615.30084 | L43: ='Debt & Cash'!M137 -> 769.03212 | M43: ='Debt & Cash'!N137 -> 889.72355 | N43: ='Debt & Cash'!O137 -> 1068.9436
B44: Other Non-Current Liabilities | D44: =SUMIF($J$66:J$112,$B$44, D66:D112) -> 24.2 | E44: =SUMIF($J$66:K$112,$B$44, E66:E112) -> 25.1 | F44: =SUMIF($J$66:L$112,$B$44, F66:F112) -> 22 | G44: =SUMIF($J$66:M$112,$B$44, G66:G112) -> 25 | H44: =SUMIF($J$66:N$112,$B$44, H66:H112) -> 24 | I44: =SUMIF($J$66:O$112,$B$44, I66:I112) -> 59 | J44: ='WC & other Assets (updated) '!M83 -> 45.673907 | K44: ='WC & other Assets (updated) '!N83 -> 49.994134 | L44: ='WC & other Assets (updated) '!O83 -> 68.145468 | M44: ='WC & other Assets (updated) '!P83 -> 72.406694 | N44: ='WC & other Assets (updated) '!Q83 -> 89.102537
B45: Deferred Tax Liabilities | D45: =SUMIF($J$66:J$112,$B$45, D66:D112) -> 44.9 | E45: =SUMIF($J$66:K$112,$B$45, E66:E112) -> 15.3 | F45: =SUMIF($J$66:L$112,$B$45, F66:F112) -> 15 | G45: =SUMIF($J$66:M$112,$B$45, G66:G112) -> 113 | H45: =SUMIF($J$66:N$112,$B$45, H66:H112) -> 118 | I45: =SUMIF($J$66:O$112,$B$45, I66:I112) -> 156 | J45: ='Debt & Cash'!K112 -> 182.95527 | K45: ='Debt & Cash'!L112 -> 188.84128 | L45: ='Debt & Cash'!M112 -> 200.54653 | M45: ='Debt & Cash'!N112 -> 216.00226 | N45: ='Debt & Cash'!O112 -> 237.27936 | O45: (from debt and cash scheduel, assumption is, that the historical average of total-non current assets for net deffered tax is held steady)
B46: Total Non-Current Liabilities | D46: =SUM(D42:D45) -> 1517.9 | E46: =SUM(E42:E45) -> 1264.6 | F46: =SUM(F42:F45) -> 1295 | G46: =SUM(G42:G45) -> 1179 | H46: =SUM(H42:H45) -> 1311 | I46: =SUM(I42:I45) -> 1961 | J46: =SUM(J42:J45) -> 2143.2928 | K46: =SUM(K42:K45) -> 2237.2206 | ... N46: =SUM(N42:N45) -> 3090.225
B48: Current Liabilities
B49: Current Debt (Financing & Lease) | D49: =SUMIF($J$66:$J$112,$B$49,D66:D112) -> 44.8 | E49: =SUMIF($J$66:$J$112,$B$49,E66:E112) -> 474.8 | F49: =SUMIF($J$66:$J$112,$B$49,F66:F112) -> 192 | G49: =SUMIF($J$66:$J$112,$B$49,G66:G112) -> 34 | H49: =SUMIF($J$66:$J$112,$B$49,H66:H112) -> 50 | I49: =SUMIF($J$66:$J$112,$B$49,I66:I112) -> 121 | J49: ='Debt & Cash'!K60 -> 120.9 | K49: ='Debt & Cash'!L60 -> 112.5 | L49: ='Debt & Cash'!M60 -> 112.5 | M49: ='Debt & Cash'!N60 -> 112.5 | N49: ='Debt & Cash'!O60 -> 112.5
A50: x | B50: Trade Payables | D50: =SUMIF($J$66:$J$112,$B$50,D66:D112) -> 168.8 | E50: =SUMIF($J$66:$J$112,$B$50,E66:E112) -> 164 | F50: =SUMIF($J$66:$J$112,$B$50,F66:F112) -> 269 | G50: =SUMIF($J$66:$J$112,$B$50,G66:G112) -> 379 | H50: =SUMIF($J$66:$J$112,$B$50,H66:H112) -> 457 | I50: =SUMIF($J$66:$J$112,$B$50,I66:I112) -> 546 | J50: ='WC & other Assets (updated) '!M34 -> 483.28767 | K50: ='WC & other Assets (updated) '!N34 -> 498.50205 | L50: ='WC & other Assets (updated) '!O34 -> 614.02173 | M50: ='WC & other Assets (updated) '!P34 -> 710.38593 | N50: ='WC & other Assets (updated) '!Q34 -> 853.48142
B51: Current Contract Liabilities | D51: =SUMIF($J$66:$J$112,$B$51,D66:D112) -> 317.1 | E51: =SUMIF($J$66:$J$112,$B$51,E66:E112) -> 416.8 | F51: =SUMIF($J$66:$J$112,$B$51,F66:F112) -> 500 | G51: =SUMIF($J$66:$J$112,$B$51,G66:G112) -> 488 | H51: =SUMIF($J$66:$J$112,$B$51,H66:H112) -> 578 | I51: =SUMIF($J$66:$J$112,$B$51,I66:I112) -> 776 | J51: ='WC & other Assets (updated) '!M32 -> 868 | K51: ='WC & other Assets (updated) '!N32 -> 908.30124 | L51: ='WC & other Assets (updated) '!O32 -> 1135.2379 | M51: ='WC & other Assets (updated) '!P32 -> 1313.4014 | N51: ='WC & other Assets (updated) '!Q32 -> 1577.9644
B52: Current Provisions | D52: =SUMIF($J$66:$J$112,$B$52,D66:D112) -> 185.1 | E52: =SUMIF($J$66:$J$112,$B$52,E66:E112) -> 193.6 | F52: =SUMIF($J$66:$J$112,$B$52,F66:F112) -> 188 | G52: =SUMIF($J$66:$J$112,$B$52,G66:G112) -> 181 | H52: =SUMIF($J$66:$J$112,$B$52,H66:H112) -> 221 | I52: =SUMIF($J$66:$J$112,$B$52,I66:I112) -> 257 | J52: ='Debt & Cash'!K136 -> 252 | K52: ='Debt & Cash'!L136 -> 263.70036 | L52: ='Debt & Cash'!M136 -> 329.58519 | M52: ='Debt & Cash'!N136 -> 381.31009 | N52: ='Debt & Cash'!O136 -> 458.1187
B53: Other Current Liabilities | D53: =SUMIF($J$66:$J$112,$B$53,D66:D112) -> 67.1 | E53: =SUMIF($J$66:$J$112,$B$53,E66:E112) -> 86.9 | F53: =SUMIF($J$66:$J$112,$B$53,F66:F112) -> 94 | G53: =SUMIF($J$66:$J$112,$B$53,G66:G112) -> 101 | H53: =SUMIF($J$66:$J$112,$B$53,H66:H112) -> 136 | I53: =SUMIF($J$66:$J$112,$B$53,I66:I112) -> 151 | J53: ='WC & other Assets (updated) '!M77 -> 176.4 | K53: ='WC & other Assets (updated) '!N77 -> 181.95325 | L53: ='WC & other Assets (updated) '!O77 -> 224.11793 | M53: ='WC & other Assets (updated) '!P77 -> 259.29086 | N53: ='WC & other Assets (updated) '!Q77 -> 311.52072
B54: Total Current Liabilities | D54: =SUM(D49:D53) -> 782.9 | E54: =SUM(E49:E53) -> 1336.1 | F54: =SUM(F49:F53) -> 1243 | G54: =SUM(G49:G53) -> 1183 | H54: =SUM(H49:H53) -> 1442 | I54: =SUM(I49:I53) -> 1851 | J54: =SUM(J49:J53) -> 1900.5877 | K54: =SUM(K49:K53) -> 1964.9569 | ... N54: =SUM(N49:N53) -> 3313.5853
B56: Total Liabilities | D56: =SUM(D54,D46) -> 2300.8 | E56: =SUM(E54,E46) -> 2600.7 | F56: =SUM(F54,F46) -> 2538 | G56: =SUM(G54,G46) -> 2362 | H56: =SUM(H54,H46) -> 2753 | I56: =SUM(I54,I46) -> 3812 | J56: =SUM(J54,J46) -> 4043.8804 | K56: =SUM(K54,K46) -> 4202.1775 | ... N56: =SUM(N54,N46) -> 6403.8103
B58: Total Equity & Liab. | D58: =SUM(D56,D38) -> 2455.6 | E58: =SUM(E56,E38) -> 2947.5 | F58: =SUM(F56,F38) -> 2955 | G58: =SUM(G56,G38) -> 2979 | H58: =SUM(H56,H38) -> 3591 | I58: =SUM(I56,I38) -> 4695 | J58: =SUM(J56,J38) -> 5108.9332 | K58: =SUM(K56,K38) -> 5457.3085 | ... N58: =SUM(N56,N38) -> 8518.1002
B60: Sanity Check | D60: =D29-D58 -> 0.4 | E60: =E29-E58 -> 0.1 | F60: =F29-F58 -> 2 | G60: =G29-G58 -> 0 | H60: =H29-H58 -> -12 | I60: =I29-I58 -> 0 | J60: =J29-J58 -> 56.182221 | K60: =K29-K58 -> 58.400959 | ... N60: =N29-N58 -> 80.013322
B62: Reported balance Sheet
D63: 2019 | E63: 2020 | F63: 2021 | G63: 2022 | H63: 2023 | I63: 2024
B64: Assets
B65: Non-current Assets | D65: 1392.6 | E65: 1313.4 | F65: 1326 | G65: 1335 | H65: 1424 | I65: 2289
B66: Goodwill | D66: 637.2 | E66: 637.2 | F66: 658 | G66: 658 | H66: 658 | I66: 1115 | J66: Goodwill & Intangibles
B67: Intangible assets | D67: 403.3 | E67: 386.2 | F67: 385 | G67: 384 | H67: 399 | I67: 667 | J67: Goodwill & Intangibles
B68: PPE | D68: 92.9 | E68: 103.1 | F68: 108 | G68: 121 | H68: 140 | I68: 202 | J68: Property, Plant & Equipment (incl. RoU)
B69: Right of Use assets | D69: 154.9 | E69: 143.5 | F69: 141 | G69: 140 | H69: 189 | I69: 249 | J69: Property, Plant & Equipment (incl. RoU)
B70: Investments accounted for using equity method | D70: 1.2 | E70: 0 | F70: 0 | G70: 1 | H70: 0 | I70: 4 | J70: Investments & Other Fin Assets (NC)
B71: Other investments and non-current other financial investments | D71: 14.7 | E71: 11.3 | F71: 21 | G71: 22 | H71: 25 | I71: 24 | J71: Investments & Other Fin Assets (NC)
B72: Non-current other financial assets | D72: 53.2 | E72: 1 | F72: 1 | G72: 1 | H72: 1 | I72: 7 | J72: Investments & Other Fin Assets (NC)
B73: Non-current other assets | D73: 4.9 | E73: 4.8 | F73: 3 | G73: 2 | H73: 3 | I73: 20 | J73: Other Non-Current Assets
B74: Deferred tax assets | D74: 30.4 | E74: 26.3 | F74: 11 | G74: 6 | H74: 9 | I74: 1 | J74: Deferred Tax Assets
B75: Current assets | D75: 1063.1 | E75: 1634.2 | F75: 1629 | G75: 1644 | H75: 2155 | I75: 2407 | J75: Total Non-Current Assets
B76: Non-current other financial investments | D76: 3 | E76: 11.2 | F76: 1 | G76: 0 | H76: 0 | I76: 0 | J76: Other Current Assets
B77: inventories | D77: 411.1 | E77: 403.7 | F77: 444 | G77: 516 | H77: 625 | I77: 719 | J77: Inventories
... B84: Total Assets | D84: 2455.7 | E84: 2947.6 | F84: 2956 | G84: 2979 | H84: 3579 | I84: 4696 | J84: Total Assets
B86: Equities and Liabilities
B87: Share Capital | D87: 10 | E87: 105 | F87: 105 | G87: 105 | H87: 116 | I87: 116 | J87: Share Capital
B88: Capital reserve | D88: 396.7 | E88: 596.8 | F88: 537 | G88: 472 | H88: 613 | I88: 474 | J88: Other Reserves (incl. Capital Reserve)
B89: other reserve | D89: -49.8 | E89: -86.3 | F89: -65 | G89: 82 | H89: 32 | I89: 37 | J89: Other Reserves (incl. Capital Reserve)
B90: retained earnings | D90: -215.8 | E90: -281.6 | F90: -171 | G90: -55 | H90: 62 | I90: 245 | J90: Retained Earnings
B91: Equity held by shareholders of Hensoldt AG | D91: 141.2 | E91: 333.9 | F91: 406 | G91: 604 | H91: 822 | I91: 873 | J91: Equity Attributable to Shareholders
B92: Non-Controlling interests | D92: 13.6 | E92: 12.9 | F92: 11 | G92: 13 | H92: 16 | I92: 14 | J92: Non-Controlling Interests
B93: Equity | D93: 154.8 | E93: 346.8 | F93: 417 | G93: 616 | H93: 838 | I93: 886 | J93: Total Equity
B94: Non-current liabilities | D94: 1517.9 | E94: 1257.1 | F94: 1284 | G94: 1160 | H94: 1271 | I94: 1927
B95: non-current provisions | D95: 413.6 | E95: 482.6 | F95: 497 | G95: 282 | H95: 357 | I95: 418 | J95: Non-Current Provisions
B96: non-current financing liabilities | D96: 887.7 | E96: 601.3 | F96: 622 | G96: 619 | H96: 621 | I96: 1072 | J96: Non-Current Debt (Financing & Lease)
B97: non-current contract liabilities | D97: 16.3 | E97: 16 | F97: 12 | G97: 11 | H97: 0 | I97: 4 | J97: Other Non-Current Liabilities
B98: non-current lease liabilities | D98: 147.5 | E98: 140.3 | F98: 139 | G98: 140 | H98: 191 | I98: 256 | J98: Non-Current Debt (Financing & Lease)
B99: non-current other financial liabilities | D99: 0.2 | E99: 0.2 | F99: 0 | G99: 3 | H99: 10 | I99: 13 | J99: Other Non-Current Liabilities
B100: non-current other liabilities | D100: 7.7 | E100: 8.9 | F100: 10 | G100: 11 | H100: 14 | I100: 15 | J100: Other Non-Current Liabilities
B101: deffered income | D101: 0 | E101: 0 | F101: 0 | G101: 0 | H101: 0 | I101: 27 | J101: Other Non-Current Liabilities
B102: deferred tax liabilities | D102: 44.8 | E102: 7.7 | F102: 4 | G102: 94 | H102: 79 | I102: 123 | J102: Deferred Tax Liabilities
B103: Current liabilities | D103: 783 | E103: 1343.7 | F103: 1255 | G103: 1203 | H103: 1470 | I103: 1883 | J103: Total Non-Current Liabilities
B104: current provisions | D104: 185.1 | E104: 193.6 | F104: 188 | G104: 181 | H104: 221 | I104: 257 | J104: Current Provisions
B105: current financing liabilities | D105: 11.3 | E105: 363.3 | F105: 166 | G105: 12 | H105: 23 | I105: 22 | J105: Current Debt (Financing & Lease)
B106: current contract liabilities | D106: 317.1 | E106: 416.8 | F106: 500 | G106: 488 | H106: 578 | I106: 776 | J106: Current Contract Liabilities
... B112: Total equity and liabilities | D112: 2455.7 | E112: 2947.6 | F112: 2956 | G112: 2979 | H112: 3579 | I112: 4696 | J112: Total Equity & Liab.

Sheet CF Neu 
A1: =_xlfn.CONCAT(Inputs!C7, " - ", "Cash Flow", " - ", "in ", Inputs!C9, " ", Inputs!C10) -> HAG - Cash Flow - in Euro millions
B4: Financial year end | G4: =EDATE(Inputs!$C$8, G5*12) -> 43830 | H4: =EDATE(Inputs!$C$8, H5*12) -> 44196 | I4: =EDATE(Inputs!$C$8, I5*12) -> 44561 | J4: =EDATE(Inputs!$C$8, J5*12) -> 44926 | K4: =EDATE(Inputs!$C$8, K5*12) -> 45291 | L4: =EDATE(Inputs!$C$8, L5*12) -> 45657 | M4: =EDATE(Inputs!$C$8, M5*12) -> 46022 | N4: =EDATE(Inputs!$C$8, N5*12) -> 46387 | ... Q4: =EDATE(Inputs!$C$8, Q5*12) -> 47483
B5: Time-line counter | G5: -5 | H5: -4 | I5: -3 | J5: -2 | K5: -1 | L5: 0 | M5: 1 | N5: 2 | O5: 3 | P5: 4 | Q5: 5
B6: Currency and units | G6: =_xlfn.CONCAT(Inputs!$C$9, " ", Inputs!$C$10) -> Euro millions | H6: =_xlfn.CONCAT(Inputs!$C$9, " ", Inputs!$C$10) -> Euro millions | I6: =_xlfn.CONCAT(Inputs!$C$9, " ", Inputs!$C$10) -> Euro millions | J6: =_xlfn.CONCAT(Inputs!$C$9, " ", Inputs!$C$10) -> Euro millions | K6: =_xlfn.CONCAT(Inputs!$C$9, " ", Inputs!$C$10) -> Euro millions | L6: =_xlfn.CONCAT(Inputs!$C$9, " ", Inputs!$C$10) -> Euro millions | M6: =_xlfn.CONCAT(Inputs!$C$9, " ", Inputs!$C$10) -> Euro millions | N6: =_xlfn.CONCAT(Inputs!$C$9, " ", Inputs!$C$10) -> Euro millions | ... Q6: =_xlfn.CONCAT(Inputs!$C$9, " ", Inputs!$C$10) -> Euro millions
B7: Time-Stamp | G7: =IF(G5<=0, "Historical", "Forecasted") -> Historical | H7: =IF(H5<=0, "Historical", "Forecasted") -> Historical | I7: =IF(I5<=0, "Historical", "Forecasted") -> Historical | J7: =IF(J5<=0, "Historical", "Forecasted") -> Historical | K7: =IF(K5<=0, "Historical", "Forecasted") -> Historical | L7: =IF(L5<=0, "Historical", "Forecasted") -> Historical | M7: =IF(M5<=0, "Historical", "Forecasted") -> Forecasted | N7: =IF(N5<=0, "Historical", "Forecasted") -> Forecasted | ... Q7: =IF(Q5<=0, "Historical", "Forecasted") -> Forecasted
B10: Standardised Cash Flow Statement
B14: Operating Activities
B15: Group Profit / Loss (or Net Income) | G15: =G52 -> 8.2 | H15: =H52 -> -64.5 | I15: =I52 -> 63 | J15: =J52 -> 80 | K15: =K52 -> 58 | L15: =L52 -> 106 | M15: ='IS Neu'!J24 -> 319.39086 | N15: ='IS Neu'!K24 -> 345.59666 | O15: ='IS Neu'!L24 -> 464.84432 | P15: ='IS Neu'!M24 -> 556.05881 | Q15: ='IS Neu'!N24 -> 671.83982
B16: Adjustments for Non-Cash Items | G16: =SUMIF($M$53:$M$90, $B$16, G53:G90) -> 143.2 | H16: =SUMIF($M$53:$M$90, $B$16, H53:H90) -> 118.4 | I16: =SUMIF($M$53:$M$90, $B$16, I53:I90) -> 128 | J16: =SUMIF($M$53:$M$90, $B$16, J53:J90) -> 105 | K16: =SUMIF($M$53:$M$90, $B$16, K53:K90) -> 133 | L16: =SUMIF($M$53:$M$90, $B$16, L53:L90) -> 180 | M16: ='FA-Forecast (updated)'!M84 -> 263.0373 | N16: ='FA-Forecast (updated)'!N84 -> 270.98997 | O16: ='FA-Forecast (updated)'!O84 -> 279.6455 | P16: ='FA-Forecast (updated)'!P84 -> 296.85834 | Q16: ='FA-Forecast (updated)'!Q84 -> 319.58634
B17: Change in Working Capital | G17: =SUMIF($M$53:$M$90, $B$17, G53:G90) -> -60 | H17: =SUMIF($M$53:$M$90, $B$17, H53:H90) -> 92 | I17: =SUMIF($M$53:$M$90, $B$17, I53:I90) -> 100 | J17: =SUMIF($M$53:$M$90, $B$17, J53:J90) -> 17 | K17: =SUMIF($M$53:$M$90, $B$17, K53:K90) -> 46 | L17: =SUMIF($M$53:$M$90, $B$17, L53:L90) -> 28 | M17: ='WC & other Assets (updated) '!M135 -> -44.391834 | N17: ='WC & other Assets (updated) '!N135 -> 28.520058 | O17: ='WC & other Assets (updated) '!O135 -> 154.90912 | P17: ='WC & other Assets (updated) '!P135 -> 120.53532 | Q17: ='WC & other Assets (updated) '!Q135 -> 178.98826
B18: Interest Paid (Net of Received) | G18: =SUMIF($M$53:$M$90, $B$18, G53:G90) -> -45.1 | H18: =SUMIF($M$53:$M$90, $B$18, H53:H90) -> -58.5 | I18: =SUMIF($M$53:$M$90, $B$18, I53:I90) -> -36 | J18: =SUMIF($M$53:$M$90, $B$18, J53:J90) -> -24 | K18: =SUMIF($M$53:$M$90, $B$18, K53:K90) -> -35 | L18: =SUMIF($M$53:$M$90, $B$18, L53:L90) -> -45 | M18: ='Debt & Cash'!K55 -> -30.54552 | N18: ='Debt & Cash'!L55 -> -45.397016 | O18: ='Debt & Cash'!M55 -> -47.472527 | P18: ='Debt & Cash'!N55 -> -29.452679 | Q18: ='Debt & Cash'!O55 -> -30.124391
B19: Taxes Paid (Net of Refunds) | G19: =SUMIF($M$53:$M$90, $B$19, G53:G90) -> 16.5 | H19: =SUMIF($M$53:$M$90, $B$19, H53:H90) -> -16.2 | I19: =SUMIF($M$53:$M$90, $B$19, I53:I90) -> 13 | J19: =SUMIF($M$53:$M$90, $B$19, J53:J90) -> 38 | K19: =SUMIF($M$53:$M$90, $B$19, K53:K90) -> 9 | L19: =SUMIF($M$53:$M$90, $B$19, L53:L90) -> -6 | M19: ='WC & other Assets (updated) '!M124 -> 64.393476 | N19: ='WC & other Assets (updated) '!N124 -> 7.9963319 | O19: ='WC & other Assets (updated) '!O124 -> 20.235392 | P19: ='WC & other Assets (updated) '!P124 -> 21.867847 | Q19: ='WC & other Assets (updated) '!Q124 -> 28.469928
B20: Net Cash from Operating Activities | G20: =SUM(G15:G19) -> 62.8 | H20: =SUM(H15:H19) -> 71.2 | I20: =SUM(I15:I19) -> 268 | J20: =SUM(J15:J19) -> 216 | K20: =SUM(K15:K19) -> 211 | L20: =SUM(L15:L19) -> 263 | M20: =SUM(M15:M19) -> 571.88429 | N20: =SUM(N15:N19) -> 607.706 | ... Q20: =SUM(Q15:Q19) -> 1168.76
B22: Investing Activities
B23: Capital Expenditures (Net) | G23: =SUMIF($M$53:$M$90, $B$23, G53:G90) -> -80 | H23: =SUMIF($M$53:$M$90, $B$23, H53:H90) -> -97.2 | I23: =SUMIF($M$53:$M$90, $B$23, I53:I90) -> -99 | J23: =SUMIF($M$53:$M$90, $B$23, J53:J90) -> -95 | K23: =SUMIF($M$53:$M$90, $B$23, K53:K90) -> -114 | L23: =SUMIF($M$53:$M$90, $B$23, L53:L90) -> -197 | M23: ='FA-Forecast (updated)'!M65*-1 -> -336 | N23: ='FA-Forecast (updated)'!N65*-1 -> -351.60048 | O23: ='FA-Forecast (updated)'!O65*-1 -> -439.44692 | P23: ='FA-Forecast (updated)'!P65*-1 -> -508.41346 | Q23: ='FA-Forecast (updated)'!Q65*-1 -> -610.82494
B24: Acquisitions & Investments (Net) | G24: =SUMIF($M$53:$M$90, $B$24, G53:G90) -> -85.6 | H24: =SUMIF($M$53:$M$90, $B$24, H53:H90) -> 2.1 | I24: =SUMIF($M$53:$M$90, $B$24, I53:I90) -> -19 | J24: =SUMIF($M$53:$M$90, $B$24, J53:J90) -> -6 | K24: =SUMIF($M$53:$M$90, $B$24, K53:K90) -> -9 | L24: =SUMIF($M$53:$M$90, $B$24, L53:L90) -> -547 | M24: 0 | N24: 0 | O24: 0 | P24: 0 | Q24: 0
B25: Other Investing Activities | G25: =SUMIF($M$53:$M$90, $B$25, G53:G90) -> 20.4 | H25: =SUMIF($M$53:$M$90, $B$25, H53:H90) -> 125.9 | I25: =SUMIF($M$53:$M$90, $B$25, I53:I90) -> 32 | J25: =SUMIF($M$53:$M$90, $B$25, J53:J90) -> 28 | K25: =SUMIF($M$53:$M$90, $B$25, K53:K90) -> 55 | L25: =SUMIF($M$53:$M$90, $B$25, L53:L90) -> 49 | M25: 50 | N25: 50 | O25: 50 | P25: 50 | Q25: 50 | R25: (since there is no clear indication of this changing dramatically)
B26: Net Cash from Investing Activities | G26: =SUM(G23:G25) -> -145.2 | H26: =SUM(H23:H25) -> 30.8 | I26: =SUM(I23:I25) -> -86 | J26: =SUM(J23:J25) -> -73 | K26: =SUM(K23:K25) -> -68 | L26: =SUM(L23:L25) -> -695 | M26: =SUM(M23:M25) -> -286 | N26: =SUM(N23:N25) -> -301.60048 | ... Q26: =SUM(Q23:Q25) -> -560.82494
B28: Financing Activities
B29: Net Change in Debt / Financing | G29: =SUMIF($M$53:$M$90, $B$29, G53:G90) -> 2.4 | H29: =SUMIF($M$53:$M$90, $B$29, H53:H90) -> 127.1 | I29: =SUMIF($M$53:$M$90, $B$29, I53:I90) -> -264 | J29: =SUMIF($M$53:$M$90, $B$29, J53:J90) -> -169 | K29: =SUMIF($M$53:$M$90, $B$29, K53:K90) -> 10 | L29: =SUMIF($M$53:$M$90, $B$29, L53:L90) -> 442 | M29: ='Debt & Cash'!K63 -> 54.671794 | N29: ='Debt & Cash'!L63 -> 49.770364 | O29: ='Debt & Cash'!M63 -> 85.255476 | P29: ='Debt & Cash'!N63 -> 104.22761 | Q29: ='Debt & Cash'!O63 -> 133.02323
B30: Net Change related to Equity | G30: =SUMIF($M$53:$M$90, $B$30, G53:G90) -> 0 | H30: =SUMIF($M$53:$M$90, $B$30, H53:H90) -> 298.4 | I30: =SUMIF($M$53:$M$90, $B$30, I53:I90) -> -3 | J30: =SUMIF($M$53:$M$90, $B$30, J53:J90) -> 0 | K30: =SUMIF($M$53:$M$90, $B$30, K53:K90) -> 238 | L30: =SUMIF($M$53:$M$90, $B$30, L53:L90) -> -1 | M30: 0 | N30: 0 | O30: 0 | P30: 0 | Q30: 0 | R30: (Share amount is kept constant)
B31: Payment of Lease Liabilities | G31: =SUMIF($M$53:$M$90, $B$31, G53:G90) -> -11.3 | H31: =SUMIF($M$53:$M$90, $B$31, H53:H90) -> -14.3 | I31: =SUMIF($M$53:$M$90, $B$31, I53:I90) -> -16 | J31: =SUMIF($M$53:$M$90, $B$31, J53:J90) -> -19 | K31: =SUMIF($M$53:$M$90, $B$31, K53:K90) -> -19 | L31: =SUMIF($M$53:$M$90, $B$31, L53:L90) -> -27 | M31: 0 | N31: 0 | O31: 0 | P31: 0 | Q31: 0 | R31: (Already Included in Change in Debt/Financing)
B32: Dividends Paid | G32: =SUMIF($M$53:$M$90, $B$32, G53:G90) -> -0.2 | H32: =SUMIF($M$53:$M$90, $B$32, H53:H90) -> 0 | I32: =SUMIF($M$53:$M$90, $B$32, I53:I90) -> -14 | J32: =SUMIF($M$53:$M$90, $B$32, J53:J90) -> -26 | K32: =SUMIF($M$53:$M$90, $B$32, K53:K90) -> -32 | L32: =SUMIF($M$53:$M$90, $B$32, L53:L90) -> -46 | M32: ='Debt & Cash'!K25*-1 -> -137.33807 | N32: ='Debt & Cash'!L25*-1 -> -155.5185 | O32: ='Debt & Cash'!M25*-1 -> -218.47683 | P32: ='Debt & Cash'!N25*-1 -> -272.46882 | Q32: ='Debt & Cash'!O25*-1 -> -342.63831
B33: Other Financing Activities | G33: =SUMIF($M$53:$M$90, $B$33, G53:G90) -> 0 | H33: =SUMIF($M$53:$M$90, $B$33, H53:H90) -> 0 | I33: =SUMIF($M$53:$M$90, $B$33, I53:I90) -> 0 | J33: =SUMIF($M$53:$M$90, $B$33, J53:J90) -> 0 | K33: =SUMIF($M$53:$M$90, $B$33, K53:K90) -> 0 | L33: =SUMIF($M$53:$M$90, $B$33, L53:L90) -> 0 | M33: 0 | N33: 0 | O33: 0 | P33: 0 | Q33: 0
B34: Net Cash from Financing Activities | G34: =SUM(G29:G33) -> -9.1 | H34: =SUM(H29:H33) -> 411.2 | I34: =SUM(I29:I33) -> -297 | J34: =SUM(J29:J33) -> -214 | K34: =SUM(K29:K33) -> 197 | L34: =SUM(L29:L33) -> 368 | M34: =SUM(M29:M33) -> -82.666277 | N34: =SUM(N29:N33) -> -105.74813 | ... Q34: =SUM(Q29:Q33) -> -209.61507
B36: FX Effect & Net Change
B37: Effect of Exchange Rates on Cash | G37: =SUMIF($M$53:$M$90, $B$37,G53:G90) -> 1.4 | H37: =SUMIF($M$53:$M$90, $B$37,H53:H90) -> -2.3 | I37: =SUMIF($M$53:$M$90, $B$37,I53:I90) -> -1 | J37: =SUMIF($M$53:$M$90, $B$37,J53:J90) -> 2 | K37: =SUMIF($M$53:$M$90, $B$37,K53:K90) -> 0 | L37: =SUMIF($M$53:$M$90, $B$37,L53:L90) -> -3 | M37: 0 | N37: 0 | O37: 0 | P37: 0 | Q37: 0 | R37: (FX is impossible to forecast, especially with the expansion in multiple jurisdictions/currencies who will have offsetting effects, therefore kept at 0)
B38: Net Change in Cash & Equivalents | G38: =SUM(G34,G26,G20,G37) -> -90.1 | H38: =SUM(H34,H26,H20,H37) -> 510.9 | I38: =SUM(I34,I26,I20,I37) -> -116 | J38: =SUM(J34,J26,J20,J37) -> -69 | K38: =SUM(K34,K26,K20,K37) -> 340 | L38: =SUM(L34,L26,L20,L37) -> -67 | M38: =M34+M26+M20 -> 203.21801 | N38: =N34+N26+N20 -> 200.35739 | O38: =O34+O26+O20 -> 349.49352 | P38: =P34+P26+P20 -> 339.21297 | Q38: =Q34+Q26+Q20 -> 398.31994
B40: Cash Balances
B42: Cash & Equivalents (Beginning)
B43: Cash & Equivalents (End)
B50: Reported Cash Flow Statement
G51: 2019 | H51: 2020 | I51: 2021 | J51: 2022 | K51: 2023 | L51: 2024
B52: Group profit / loss | G52: 8.2 | H52: -64.5 | I52: 63 | J52: 80 | K52: 58 | L52: 106
B53: Depreciation, amortisation and impairments of non-current assets | G53: 129.6 | H53: 120.8 | I53: 126 | J53: 103 | K53: 117 | L53: 162 | M53: Adjustments for Non-Cash Items
B54: Impairments (+) / reversals of impairments (-) of inventories, trade receivables and contract assets | G54: 13.2 | H54: -2.4 | I54: 3 | J54: 2 | K54: 17 | L54: 17 | M54: Adjustments for Non-Cash Items
B55: Profit / loss from disposals of non-current assets | G55: 0.4 | H55: 0 | I55: -1 | J55: 0 | K55: -1 | L55: 1 | M55: Adjustments for Non-Cash Items
B56: Share of profits in investments accounted for using the equity method | G56: 1.2 | H56: 2.6 | I56: 2 | J56: 0 | K56: 0 | L56: -3 | M56: Other Investing Activities
B57: Financial expenses (net) | G57: 24.6 | H57: 128.3 | I57: 33 | J57: 27 | K57: 41 | L57: 56 | M57: Other Investing Activities
B58: Other non-cash expense / income | G58: -5.4 | H58: -5.1 | I58: -4 | J58: 1 | K58: 14 | L58: -4 | M58: Other Investing Activities
B59: Change in
B60: Provisions | G60: -0.4 | H60: 46.4 | I60: 31 | J60: -22 | K60: 45 | L60: -5 | M60: Change in Working Capital
B61: Inventories | G61: -17.8 | H61: 5.3 | I61: -44 | J61: -75 | K61: -128 | L61: -103 | M61: Change in Working Capital
B62: Contract balances | G62: -89.4 | H62: 61.4 | I62: 111 | J62: -25 | K62: 65 | L62: 34 | M62: Change in Working Capital
B63: Trade receivables | G63: 56.4 | H63: 5.3 | I63: -22 | J63: -13 | K63: -66 | L63: -11 | M63: Change in Working Capital
B64: Trade payables | G64: -13.4 | H64: -8.6 | I64: 107 | J64: 110 | K64: 78 | L64: 69 | M64: Change in Working Capital
B65: Other assets and liabilities | G65: 4.6 | H65: -17.8 | I65: -83 | J65: 42 | K65: 52 | L65: 44 | M65: Change in Working Capital
B66: Interest paid | G66: -45.1 | H66: =-(43.6+14.9) -> -58.5 | I66: -36 | J66: -24 | K66: -44 | L66: -66 | M66: Interest Paid (Net of Received)
B67: Interest received | G67: 0 | H67: 0 | I67: 0 | J67: 0 | K67: 9 | L67: 21 | M67: Interest Paid (Net of Received)
B68: Income tax expense (+) / income (-) | G68: 27.4 | H68: -10.7 | I68: 22 | J68: 49 | K68: 36 | L68: 12 | M68: Taxes Paid (Net of Refunds)
B69: Income tax payments (-) / refunds (+) | G69: -10.9 | H69: -5.5 | I69: -9 | J69: -11 | K69: -27 | L69: -18 | M69: Taxes Paid (Net of Refunds)
B70: Cash flows from operating activities | G70: 83.2 | H70: 196.9 | I70: 299 | J70: 244 | K70: 267 | L70: 311 | M70: Net Cash from Operating Activities
B71: Acquisition / addition of intangible assets and property, plant and equipment | G71: -80.5 | H71: -97.4 | I71: -102 | J71: -95 | K71: -115 | L71: -199 | M71: Capital Expenditures (Net)
B72: Proceeds from sale of intangible assets and property, plant and equipment | G72: 0.5 | H72: 0.2 | I72: 3 | J72: 0 | K72: 1 | L72: 2 | M72: Capital Expenditures (Net)
B73: Payments for investments in non-consolidated affiliates, joint ventures, associates, other investments and other non-current financial assets | G73: -3.9 | H73: -6.6 | I73: -7 | J73: -5 | K73: -9 | L73: -4 | M73: Acquisitions & Investments (Net)
B74: Proceeds from disposals of non-consolidated affiliates, joint ventures, associates, other investments and non-current financial assets | G74: 2.1 | H74: 2.3 | I74: 0 | J74: 0 | K74: 1 | L74: 0 | M74: Acquisitions & Investments (Net)
B75: Acquisition of subsidiaries net of cash acquired | G75: -83.8 | H75: 6.4 | I75: -12 | J75: -1 | K75: -1 | L75: -543 | M75: Acquisitions & Investments (Net)
B76: Other | G76: 0 | H76: 0.1 | I76: 1 | J76: 0 | K76: 0 | L76: 0 | M76: Other Investing Activities
B77: Cash flows from investing activities | G77: -165.6 | H77: -95 | I77: -117 | J77: -101 | K77: -122 | L77: -745 | M77: Net Cash from Investing Activities
B78: Proceeds from financing liabilities to banks | G78: 2.4 | H78: 950 | I78: -210 | J78: -150 | K78: 0 | L78: 450 | M78: Net Change in Debt / Financing
... B88: Net changes in cash and cash equivalents | G88: -90.2 | H88: 508.1 | I88: -116 | J88: -69 | K88: 342 | L88: -69 | M88: Net Change in Cash & Equivalents
B89: Cash and cash equivalents
B90: Cash and cash equivalents on 1 January | G90: 227.5 | H90: 137.4 | I90: 645 | J90: 529 | K90: 460 | L90: 802 | M90: Cash Balances
B91: Cash and cash equivalents on 31 December | G91: 137.4 | H91: 645.5 | I91: 529 | J91: 460 | K91: 802 | L91: 733
B93: Operating Cash
B94: Investing Cash

Sheet Revenue & Expenses (updated)
A1: =_xlfn.CONCAT(Inputs!C7, " - ", "Assumptions"," - ", "in ", Inputs!C9, " ", Inputs!C10) -> HAG - Assumptions - in Euro millions
B4: Financial year end | G4: =EDATE(Inputs!$C$8, G5*12) -> 43830 | H4: =EDATE(Inputs!$C$8, H5*12) -> 44196 | I4: =EDATE(Inputs!$C$8, I5*12) -> 44561 | J4: =EDATE(Inputs!$C$8, J5*12) -> 44926 | K4: =EDATE(Inputs!$C$8, K5*12) -> 45291 | L4: =EDATE(Inputs!$C$8, L5*12) -> 45657 | M4: =EDATE(Inputs!$C$8, M5*12) -> 46022 | N4: =EDATE(Inputs!$C$8, N5*12) -> 46387 | ... Q4: =EDATE(Inputs!$C$8, Q5*12) -> 47483 | S4: Revenue Conversion Rate | V4: =Inputs!N7 -> 3
B5: Time-line counter | G5: -5 | H5: -4 | I5: -3 | J5: -2 | K5: -1 | L5: 0 | M5: 1 | N5: 2 | O5: 3 | P5: 4 | Q5: 5 | S5: Revenue Growth Rate | V5: =Inputs!N8 -> 3
B6: Currency and units | G6: =_xlfn.CONCAT(Inputs!$C$9, " ", Inputs!$C$10) -> Euro millions | H6: =_xlfn.CONCAT(Inputs!$C$9, " ", Inputs!$C$10) -> Euro millions | I6: =_xlfn.CONCAT(Inputs!$C$9, " ", Inputs!$C$10) -> Euro millions | J6: =_xlfn.CONCAT(Inputs!$C$9, " ", Inputs!$C$10) -> Euro millions | K6: =_xlfn.CONCAT(Inputs!$C$9, " ", Inputs!$C$10) -> Euro millions | L6: =_xlfn.CONCAT(Inputs!$C$9, " ", Inputs!$C$10) -> Euro millions | M6: =_xlfn.CONCAT(Inputs!$C$9, " ", Inputs!$C$10) -> Euro millions | N6: =_xlfn.CONCAT(Inputs!$C$9, " ", Inputs!$C$10) -> Euro millions | ... Q6: =_xlfn.CONCAT(Inputs!$C$9, " ", Inputs!$C$10) -> Euro millions | S6: Book to Bill Ratio | V6: =Inputs!N9 -> 3
B7: Time-Stamp | G7: =IF(G5<=0, "Historical", "Forecasted") -> Historical | H7: =IF(H5<=0, "Historical", "Forecasted") -> Historical | I7: =IF(I5<=0, "Historical", "Forecasted") -> Historical | J7: =IF(J5<=0, "Historical", "Forecasted") -> Historical | K7: =IF(K5<=0, "Historical", "Forecasted") -> Historical | L7: =IF(L5<=0, "Historical", "Forecasted") -> Historical | M7: =IF(M5<=0, "Historical", "Forecasted") -> Forecasted | N7: =IF(N5<=0, "Historical", "Forecasted") -> Forecasted | ... Q7: =IF(Q5<=0, "Historical", "Forecasted") -> Forecasted | S7: Cost of Sales | V7: =Inputs!N10 -> 4
S8: SG&A | V8: =Inputs!N11 -> 3
S9: R&D | V9: =Inputs!N12 -> 3
S10: Other Income | V10: =Inputs!N13 -> 3
B11: Revenue Model | Q11: =((Q22/L22)^(1/5))-1 -> 0.17841293
B14: Actual Revenue Forecast
B15: Beginnign Backlog | H15: 2202 | I15: 3424 | J15: 5092 | K15: 5366 | L15: 5530 | M15: 6644 | N15: =M21 -> 8238.6 | O15: =N21 -> 9457.0956 | P15: =O21 -> 11273.993 | Q15: =P21 -> 13259.586 | S15: Assumptions about Scenarios
B16: Backlog Conversion rate | H16: =H17/H15 -> 0.54768392 | I16: =I17/I15 -> 0.43049065 | J16: =J17/J15 -> 0.33523174 | K16: =K17/K15 -> 0.34923593 | L16: =L17/L15 -> 0.40506329 | M16: =CHOOSE($V$4, M25, M26,M27,M28) -> 0.35 | N16: =CHOOSE($V$4, N25, N26,N27,N28) -> 0.35 | O16: =CHOOSE($V$4, O25, O26,O27,O28) -> 0.35 | P16: =CHOOSE($V$4, P25, P26,P27,P28) -> 0.35 | Q16: =CHOOSE($V$4, Q25, Q26,Q27,Q28) -> 0.35
B17: Backlog Conversion Revenue | G17: 1114 | H17: =U35 -> 1206 | I17: =V35 -> 1474 | J17: =W35 -> 1707 | K17: =X35 -> 1874 | L17: =Y35 -> 2240 | M17: =M15*M16 -> 2325.4 | N17: =N15*N16 -> 2883.51 | O17: =O15*O16 -> 3309.9835 | P17: =P15*P16 -> 3945.8975 | Q17: =Q15*Q16 -> 4640.855 | S17: Revenue:
B18: Revenue Growth Rate | H18: =(H17-G17)/G17 -> 0.082585278 | I18: =(I17-H17)/H17 -> 0.22222222 | J18: =(J17-I17)/I17 -> 0.15807327 | K18: =(K17-J17)/J17 -> 0.097832455 | L18: =(L17-K17)/K17 -> 0.19530416 | M18: =CHOOSE($V$5,M31,M32,M33,M34) -> 0.25 | N18: =CHOOSE($V$5,N31,N32,N33,N34) -> 0.26 | O18: =CHOOSE($V$5,O31,O32,O33,O34) -> 0.27 | P18: =CHOOSE($V$5,P31,P32,P33,P34) -> 0.28 | Q18: =CHOOSE($V$5,Q31,Q32,Q33,Q34) -> 0.29 | S18: While the Structural drivers (uncertain global environment, continuing increases in defense spending in HAG core business areas, fiscal expansion)
B19: Book to Bill Ratio | G19: =1040/1114 -> 0.93357271 | H19: =2541/1206 -> 2.1069652 | I19: 2.2 | J19: 1.2 | K19: 1.1 | L19: 1.3 | M19: =CHOOSE($V$6,M37,M38,M39,M40) -> 1.4 | N19: =CHOOSE($V$6,N37,N38,N39,N40) -> 1.4 | O19: =CHOOSE($V$6,O37,O38,O39,O40) -> 1.4 | P19: =CHOOSE($V$6,P37,P38,P39,P40) -> 1.4 | Q19: =CHOOSE($V$6,Q37,Q38,Q39,Q40) -> 1.4 | S19: are in tact, there are significant risks - ie if the Russia-Ukrain War stops and defense spending does not follow the forecasted path to reach 3.5% in 2035 for all Nato countries (except Spain)
B20: New Order Intake | G20: 1040 | H20: 2541 | I20: 3171 | J20: 1993 | K20: 2087 | L20: 2904 | M20: =M22*M19 -> 3920 | N20: =N22*N19 -> 4102.0056 | O20: =O22*O19 -> 5126.8808 | P20: =P22*P19 -> 5931.4904 | Q20: =Q22*Q19 -> 7126.2909 | S20: Growth therefore depends not only on governments desire to purchase but also to deliver on the backlog and expand into new markets, especially in the middle east
B21: Ending Backlog | G21: =G15+G20-G17 -> -74 | H21: =H15+H20-H17 -> 3537 | I21: =I15+I20-I17 -> 5121 | J21: =J15+J20-J17 -> 5378 | K21: =K15+K20-K17 -> 5579 | L21: =L15+L20-L17 -> 6194 | M21: =M15+M20-M17 -> 8238.6 | N21: =N15+N20-N17 -> 9457.0956 | ... Q21: =Q15+Q20-Q17 -> 15745.022
B22: Total Revenue Forecast | H22: =G17*(1+H18) -> 1206 | I22: =H17*(1+I18) -> 1474 | J22: =I17*(1+J18) -> 1707 | K22: =J17*(1+K18) -> 1874 | L22: =K17*(1+L18) -> 2240 | M22: =L17*(1+M18) -> 2800 | N22: =M17*(1+N18) -> 2930.004 | O22: =N17*(1+O18) -> 3662.0577 | ... Q22: =P17*(1+Q18) -> 5090.2078 | S22: Bookt to Bill Ratio
S23: While the current book to bill ratio of 1,2 indicates significant future backlog, HAG believes, that they can accellarate their own growth by entering new markets
B24: Backlog Conversion Rate | S24: and refocussing their offering from products to a solutions based approach. This is underlined by the aquisition of a new business (ESG) in 2024
A25: 1 | B25: Pessimistic Sceanrio | M25: 0.28 | N25: 0.28 | O25: 0.28 | P25: 0.28 | Q25: 0.28
A26: 2 | B26: Realistic Scenario | M26: 0.31 | N26: 0.31 | O26: 0.31 | P26: 0.31 | Q26: 0.31 | S26: Conversion Rate
A27: 3 | B27: Optimistic Scenario | M27: 0.35 | N27: 0.35 | O27: 0.35 | P27: 0.35 | Q27: 0.35 | S27: This essentially measures, how much of the existing backlog hensoldt is able to turn into billable revenue. Since HAG is continuously increasing capactiy
A28: 4 | B28: Company own Projection | M28: 0.3 | N28: 0.3 | O28: 0.3 | P28: 0.3 | Q28: 0.3 | S28: either in personall but also on in terms of sheet product output with a record almost 130 million in R&D Spending in 2025, it is very likely, that large parts of the backlog can be turned into actionable growth.
S29: Although comparative disadvantages exist for any industrial production in Europe, the defense sector is somewhat isolated from this due to the
B30: Revenue Growth Rate | S30: increasing willingness of all participant (planning agencies, banks, regulators, potential employees) to support it's companies.
B31: Pessimistic Sceanrio | M31: 0.2 | N31: 0.19 | O31: 0.18 | P31: 0.18 | Q31: 0.18
B32: Realistic Scenario | M32: 0.22 | N32: 0.22 | O32: 0.22 | P32: 0.22 | Q32: 0.22
B33: Optimistic Scenario | M33: 0.25 | N33: 0.26 | O33: 0.27 | P33: 0.28 | Q33: 0.29 | S33: Conversion Calculation | T33: 2019 | U33: 2020 | V33: 2021 | W33: 2022 | X33: 2023 | Y33: 2024
B34: Company own Projection | M34: 0.24 | N34: 0.25 | O34: 0.26 | P34: 0.26 | Q34: 0.26 | S34: Total Order Backlog | T34: 2202 | U34: 3424 | V34: 5092 | W34: 5366 | X34: 5530 | Y34: 6644
S35: Annual Sales | T35: 1114 | U35: 1206 | V35: 1474 | W35: 1707 | X35: 1874 | Y35: 2240
B36: Book to Bill Ratio | S36: Conversion Rate | T36: =U35/T34 -> 0.54768392 | U36: =V35/U34 -> 0.43049065 | V36: =W35/V34 -> 0.33523174 | W36: =X35/W34 -> 0.34923593 | X36: =Y35/X34 -> 0.40506329 | Y36: =Z7/Y34 -> 0
B37: Pessimistic Sceanrio | M37: 1.2 | N37: 1.2 | O37: 1.2 | P37: 1.2 | Q37: 1.2 | S37: GR Order Backlog | U37: =(U34-T34)/T34 -> 0.55495005 | V37: =(V34-U34)/U34 -> 0.48714953 | W37: =(W34-V34)/V34 -> 0.053809898 | X37: =(X34-W34)/W34 -> 0.030562803 | Y37: =(Y34-X34)/X34 -> 0.20144665
B38: Realistic Scenario | M38: 1.3 | N38: 1.3 | O38: 1.3 | P38: 1.3 | Q38: 1.3 | S38: GR Revenue | U38: =(U35-T35)/T35 -> 0.082585278 | V38: =(V35-U35)/U35 -> 0.22222222 | W38: =(W35-V35)/V35 -> 0.15807327 | X38: =(X35-W35)/W35 -> 0.097832455 | Y38: =(Y35-X35)/X35 -> 0.19530416
B39: Optimistic Scenario | M39: 1.4 | N39: 1.4 | O39: 1.4 | P39: 1.4 | Q39: 1.4
B40: Company own Projection | M40: 1.3 | N40: 1.35 | O40: 1.4 | P40: 1.5 | Q40: 1.5
S41: Margin Calculations | T41: 2019 | U41: 2020 | V41: 2021 | W41: 2022 | X41: 2023 | Y41: 2024
B42: Expense Model | S42: Revenue | T42: =IS!D10 -> 1114.2 | U42: =IS!E10 -> 1206.9 | V42: =IS!F10 -> 1474 | W42: =IS!G10 -> 1707 | X42: =IS!H10 -> 1847 | Y42: =IS!I10 -> 2240 | Z42: =M22 -> 2800 | AA42: =N22 -> 2930.004 | AB42: =O22 -> 3662.0577 | AC42: =P22 -> 4236.7788 | AD42: =Q22 -> 5090.2078
S43: Cost of Sales | T43: =IS!D11 -> -859.3 | U43: =IS!E11 -> -936.1 | V43: =IS!F11 -> -1144 | W43: =IS!G11 -> -1314 | X43: =IS!H11 -> -1427 | Y43: =IS!I11 -> -1732 | Z43: =M45*-1 -> -1960 | AA43: =N45*-1 -> -2021.7028 | AB43: =O45*-1 -> -2490.1992 | AC43: =P45*-1 -> -2881.0096 | AD43: =Q45*-1 -> -3461.3413
B44: Actual Expense Forecast | S44: Operating Margin | T44: =1-((-1)*T43/T42) -> 0.22877401 | U44: =1-((-1)*U43/U42) -> 0.2243765 | V44: =1-((-1)*V43/V42) -> 0.2238806 | W44: =1-((-1)*W43/W42) -> 0.23022847 | X44: =1-((-1)*X43/X42) -> 0.22739578 | Y44: =1-((-1)*Y43/Y42) -> 0.22678571 | Z44: =1-((-1)*Z43/Z42) -> 0.3 | AA44: =1-((-1)*AA43/AA42) -> 0.31 | ... AD44: =1-((-1)*AD43/AD42) -> 0.32
B45: Cost of Sales (€) | M45: =M22*M46 -> 1960 | N45: =N22*N46 -> 2021.7028 | O45: =O22*O46 -> 2490.1992 | P45: =P22*P46 -> 2881.0096 | Q45: =Q22*Q46 -> 3461.3413
B46: % used | M46: =CHOOSE($V$7, M57,M58,M59,M60) -> 0.7 | N46: =CHOOSE($V$7, N57,N58,N59,N60) -> 0.69 | O46: =CHOOSE($V$7, O57,O58,O59,O60) -> 0.68 | P46: =CHOOSE($V$7, P57,P58,P59,P60) -> 0.68 | Q46: =CHOOSE($V$7, Q57,Q58,Q59,Q60) -> 0.68 | S46: S&D | T46: =(-1*IS!D31/T42) -> 0.076108419 | U46: =(-1*IS!E31/U42) -> 0.074736929 | V46: =(-1*IS!F31/V42) -> 0.067164179 | W46: =(-1*IS!G31/W42) -> 0.06268307 | X46: =(-1*IS!H31/X42) -> 0.060097455 | Y46: =(-1*IS!I31/Y42) -> 0.057142857
B47: SG&A (€) | M47: =M48*M22 -> 252 | N47: =N48*N22 -> 263.70036 | O47: =O48*O22 -> 329.58519 | P47: =P48*P22 -> 381.31009 | Q47: =Q48*Q22 -> 458.1187 | S47: G&A | T47: =(IS!D32/T43) -> 0.088793204 | U47: =(IS!E32/U43) -> 0.093152441 | V47: =(IS!F32/V43) -> 0.072552448 | W47: =(IS!G32/W43) -> 0.070015221 | X47: =(IS!H32/X43) -> 0.08269096 | Y47: =(IS!I32/Y43) -> 0.093533487
B48: % used | M48: =CHOOSE($V$8,M64,M65,M66,M67) -> 0.09 | N48: =CHOOSE($V$8,N64,N65,N66,N67) -> 0.09 | O48: =CHOOSE($V$8,O64,O65,O66,O67) -> 0.09 | P48: =CHOOSE($V$8,P64,P65,P66,P67) -> 0.09 | Q48: =CHOOSE($V$8,Q64,Q65,Q66,Q67) -> 0.09 | S48: SG&A | T48: =-1*IS!D14/T42 -> 0.14458805 | U48: =-1*IS!E14/U42 -> 0.14698815 | V48: =-1*IS!F14/V42 -> 0.12347354 | W48: =-1*IS!G14/W42 -> 0.11657879 | X48: =-1*IS!H14/X42 -> 0.12398484 | Y48: =-1*IS!I14/Y42 -> 0.12946429
B49: R&D (€) | M49: =M50*M22 -> 112 | N49: =N50*N22 -> 117.20016 | O49: =O50*O22 -> 146.48231 | P49: =P50*P22 -> 169.47115 | Q49: =Q50*Q22 -> 203.60831 | S49: R&D | T49: =-1*IS!D13/T42 -> 0.027822653 | U49: =IS!E13/U42 -> -0.020797083 | V49: =IS!F13/V42 -> -0.021031208 | W49: =IS!G13/W42 -> -0.021089631 | X49: =IS!H13/X42 -> -0.016242555 | Y49: =IS!I13/Y42 -> -0.014285714
B50: % used | M50: =CHOOSE($V$9,M71,M72,M73,M74) -> 0.04 | N50: =CHOOSE($V$9,N71,N72,N73,N74) -> 0.04 | O50: =CHOOSE($V$9,O71,O72,O73,O74) -> 0.04 | P50: =CHOOSE($V$9,P71,P72,P73,P74) -> 0.04 | Q50: =CHOOSE($V$9,Q71,Q72,Q73,Q74) -> 0.04
B51: Other Operating Income/Expense | M51: =CHOOSE($V$10,M79,M80,M81,M82) -> 0 | N51: =CHOOSE($V$10,N79,N80,N81,N82) -> 0 | O51: =CHOOSE($V$10,O79,O80,O81,O82) -> 0 | P51: =CHOOSE($V$10,P79,P80,P81,P82) -> 0 | Q51: =CHOOSE($V$10,Q79,Q80,Q81,Q82) -> 0 | S51: Necessary Forecast Revenue
B52: Total Expense Forecast | M52: =SUM(M45,M47,M49) -> 2324 | N52: =SUM(N45,N47,N49) -> 2402.6033 | O52: =SUM(O45,O47,O49) -> 2966.2667 | P52: =SUM(P45,P47,P49) -> 3431.7909 | Q52: =SUM(Q45,Q47,Q49) -> 4123.0683 | S52: Backlog Conversion Rate
B53: Sanity Check | M53: =SUM(M46, M48,M50) -> 0.83 | N53: =SUM(N46, N48,N50) -> 0.82 | O53: =SUM(O46, O48,O50) -> 0.81 | P53: =SUM(P46, P48,P50) -> 0.81 | Q53: =SUM(Q46, Q48,Q50) -> 0.81 | S53: Revenue Growth Rate
S54: Book to Bill Ratio
B55: Cost of Sales
B56: as a % of Revenue | G56: =('IS Neu'!D13*-1)/'IS Neu'!D12 -> 0.77122599 | H56: =('IS Neu'!E13*-1)/'IS Neu'!E12 -> 0.7756235 | I56: =('IS Neu'!F13*-1)/'IS Neu'!F12 -> 0.7761194 | J56: =('IS Neu'!G13*-1)/'IS Neu'!G12 -> 0.76977153 | K56: =('IS Neu'!H13*-1)/'IS Neu'!H12 -> 0.77260422 | L56: =('IS Neu'!I13*-1)/'IS Neu'!I12 -> 0.77321429 | M56: =('IS Neu'!J13*-1)/'IS Neu'!J12 -> 0.7 | N56: =('IS Neu'!K13*-1)/'IS Neu'!K12 -> 0.69 | ... Q56: =('IS Neu'!N13*-1)/'IS Neu'!N12 -> 0.68 | S56: Necessary Forecasts Expenses
B57: Pessimistic Sceanrio | M57: 0.74 | N57: 0.74 | O57: 0.74 | P57: 0.74 | Q57: 0.74 | S57: Cost of Sales %
B58: Realistic Scenario | M58: 0.72 | N58: 0.72 | O58: 0.72 | P58: 0.72 | Q58: 0.72 | S58: SG&A
B59: Optimistic Scenario | M59: 0.7 | N59: 0.7 | O59: 0.7 | P59: 0.7 | Q59: 0.7 | S59: R&D
B60: Company own Projection | M60: 0.7 | N60: 0.69 | O60: 0.68 | P60: 0.68 | Q60: 0.68 | S60: Other Income is kept 0, because it is impossible to forecast with any degree of certainty/would otherwise distort the model
B62: SG&A
B63: as a % of Revenue
B64: Pessimistic Sceanrio | M64: 0.11 | N64: 0.11 | O64: 0.11 | P64: 0.11 | Q64: 0.11
B65: Realistic Scenario | M65: 0.1 | N65: 0.1 | O65: 0.1 | P65: 0.1 | Q65: 0.1
B66: Optimistic Scenario | M66: 0.09 | N66: 0.09 | O66: 0.09 | P66: 0.09 | Q66: 0.09
B67: Company own Projection | M67: 0.1 | N67: 0.095 | O67: =N67-0.5% -> 0.09 | P67: 0.09 | Q67: 0.09
B69: R&D
B70: as a % of Revenue
B71: Pessimistic Sceanrio | M71: 0.03 | N71: 0.03 | O71: 0.03 | P71: 0.03 | Q71: 0.03
B72: Realistic Scenario | M72: 0.035 | N72: 0.035 | O72: 0.035 | P72: 0.035 | Q72: 0.035
B73: Optimistic Scenario | M73: 0.04 | N73: 0.04 | O73: 0.04 | P73: 0.04 | Q73: 0.04
B74: Company own Projection | M74: 0.05 | N74: 0.05 | O74: 0.05 | P74: 0.05 | Q74: 0.05
B76: Sanity Check (Invers EBIT Margin) | M76: =SUM(M46,M48,M50) -> 0.83 | N76: =SUM(N46,N48,N50) -> 0.82 | O76: =SUM(O46,O48,O50) -> 0.81 | P76: =SUM(P46,P48,P50) -> 0.81 | Q76: =SUM(Q46,Q48,Q50) -> 0.81
B78: Other Income/Expense
B79: Pessimistic Sceanrio | G79: =IS!D18 -> -2.6 | H79: =IS!E18 -> -9.8 | I79: =IS!F18 -> 6 | J79: =IS!G18 -> 7 | K79: =IS!H18 -> -1 | L79: =IS!I18 -> -1 | M79: 0 | N79: 0 | O79: 0 | P79: 0 | Q79: 0
B80: Realistic Scenario | M80: 0 | N80: 0 | O80: 0 | P80: 0 | Q80: 0
B81: Optimistic Scenario | M81: 0 | N81: 0 | O81: 0 | P81: 0 | Q81: 0
B82: Company own Projection | M82: 0 | N82: 0 | O82: 0 | P82: 0 | Q82: 0

Sheet FA-Forecast (updated)
A1: =_xlfn.CONCAT(Inputs!C7, " - ", "Fixed Assets", " - ", "in ", Inputs!C9, " ", Inputs!C10) -> HAG - Fixed Assets - in Euro millions
V2: Version
B4: Financial year end | G4: =EDATE(Inputs!$C$8, G5*12) -> 43830 | H4: =EDATE(Inputs!$C$8, H5*12) -> 44196 | I4: =EDATE(Inputs!$C$8, I5*12) -> 44561 | J4: =EDATE(Inputs!$C$8, J5*12) -> 44926 | K4: =EDATE(Inputs!$C$8, K5*12) -> 45291 | L4: =EDATE(Inputs!$C$8, L5*12) -> 45657 | M4: =EDATE(Inputs!$C$8, M5*12) -> 46022 | N4: =EDATE(Inputs!$C$8, N5*12) -> 46387 | ... Q4: =EDATE(Inputs!$C$8, Q5*12) -> 47483 | S4: Capex | V4: =Inputs!R7 -> 3
B5: Time-line counter | G5: -5 | H5: -4 | I5: -3 | J5: -2 | K5: -1 | L5: 0 | M5: 1 | N5: 2 | O5: 3 | P5: 4 | Q5: 5 | S5: D&A | V5: =Inputs!R8 -> 3
B6: Currency and units | G6: =_xlfn.CONCAT(Inputs!$C$9, " ", Inputs!$C$10) -> Euro millions | H6: =_xlfn.CONCAT(Inputs!$C$9, " ", Inputs!$C$10) -> Euro millions | I6: =_xlfn.CONCAT(Inputs!$C$9, " ", Inputs!$C$10) -> Euro millions | J6: =_xlfn.CONCAT(Inputs!$C$9, " ", Inputs!$C$10) -> Euro millions | K6: =_xlfn.CONCAT(Inputs!$C$9, " ", Inputs!$C$10) -> Euro millions | L6: =_xlfn.CONCAT(Inputs!$C$9, " ", Inputs!$C$10) -> Euro millions | M6: =_xlfn.CONCAT(Inputs!$C$9, " ", Inputs!$C$10) -> Euro millions | N6: =_xlfn.CONCAT(Inputs!$C$9, " ", Inputs!$C$10) -> Euro millions | ... Q6: =_xlfn.CONCAT(Inputs!$C$9, " ", Inputs!$C$10) -> Euro millions | S6: Disposals | V6: =Inputs!R9 -> 3
B7: Time-Stamp | G7: =IF(G5<=0, "Historical", "Forecasted") -> Historical | H7: =IF(H5<=0, "Historical", "Forecasted") -> Historical | I7: =IF(I5<=0, "Historical", "Forecasted") -> Historical | J7: =IF(J5<=0, "Historical", "Forecasted") -> Historical | K7: =IF(K5<=0, "Historical", "Forecasted") -> Historical | L7: =IF(L5<=0, "Historical", "Forecasted") -> Historical | M7: =IF(M5<=0, "Historical", "Forecasted") -> Forecasted | N7: =IF(N5<=0, "Historical", "Forecasted") -> Forecasted | ... Q7: =IF(Q5<=0, "Historical", "Forecasted") -> Forecasted
B9: Targeted Scenario | E9: 1 | K9: Forecasted Revenue | M9: ='Revenue & Expenses (updated)'!M22 -> 2800 | N9: ='Revenue & Expenses (updated)'!N22 -> 2930.004 | O9: ='Revenue & Expenses (updated)'!O22 -> 3662.0577 | P9: ='Revenue & Expenses (updated)'!P22 -> 4236.7788 | Q9: ='Revenue & Expenses (updated)'!Q22 -> 5090.2078
S10: Basic Principle:
B11: PPE | S11: Operating Items are based on Revenue
B12: Beginning Gross PPE | G12: 126 | H12: 151 | I12: 180 | J12: 208 | K12: 282 | L12: 370 | M12: =L17 -> 448.35 | N12: =M17 -> 539.62475 | O12: =N17 -> 634.08052 | P12: =O17 -> 752.74133 | Q12: =P17 -> 889.73747 | S12: Financing&Investing on a roll forward scheduel (add to previous years amount and subtract from it)
B13: (+) CapEX | E13: =T20 -> 0.27 | G13: 21 | H13: 31 | I13: 30 | J13: 36 | K13: 46 | L13: 83 | M13: =M14*M9 -> 98 | N13: =N14*N9 -> 102.55014 | O13: =O14*O9 -> 128.17202 | P13: =P14*P9 -> 148.28726 | Q13: =Q14*Q9 -> 178.15727 | S13: Other items are idiosyncratic/forecasted by using company guidance
B14: % used | G14: =G13/G12 -> 0.16666667 | H14: =H13/H12 -> 0.20529801 | I14: =I13/I12 -> 0.16666667 | J14: =J13/J12 -> 0.17307692 | K14: =K13/K12 -> 0.16312057 | L14: 0.35 | M14: =CHOOSE($E$9,M60,M61,M62,M63)*$L$14 -> 0.035 | N14: =CHOOSE($E$9,N60,N61,N62,N63)*$L$14 -> 0.035 | O14: =CHOOSE($E$9,O60,O61,O62,O63)*$L$14 -> 0.035 | P14: =CHOOSE($E$9,P60,P61,P62,P63)*$L$14 -> 0.035 | Q14: =CHOOSE($E$9,Q60,Q61,Q62,Q63)*$L$14 -> 0.035
B15: (-) Disposals | G15: -1 | H15: -3 | I15: -4 | J15: -2 | K15: -3 | L15: -5 | M15: =(-1)*M16*M12 -> -6.72525 | N15: =(-1)*N16*N12 -> -8.0943713 | O15: =(-1)*O16*O12 -> -9.5112078 | P15: =(-1)*P16*P12 -> -11.29112 | Q15: =(-1)*Q16*Q12 -> -13.346062
B16: % used | M16: =CHOOSE($E$9,M78,M79,M80,M81) -> 0.015 | N16: =CHOOSE($E$9,N78,N79,N80,N81) -> 0.015 | O16: =CHOOSE($E$9,O78,O79,O80,O81) -> 0.015 | P16: =CHOOSE($E$9,P78,P79,P80,P81) -> 0.015 | Q16: =CHOOSE($E$9,Q78,Q79,Q80,Q81) -> 0.015
B17: Ending Gross PPE | G17: =SUM(G12:G15) -> 146.16667 | H17: =SUM(H12:H15) -> 179.2053 | I17: =SUM(I12:I15) -> 206.16667 | J17: =SUM(J12:J15) -> 242.17308 | K17: =SUM(K12:K15) -> 325.16312 | L17: =SUM(L12:L15) -> 448.35 | M17: =SUM(M12,M13,M15) -> 539.62475 | N17: =SUM(N12,N13,N15) -> 634.08052 | O17: =SUM(O12,O13,O15) -> 752.74133 | P17: =SUM(P12,P13,P15) -> 889.73747 | Q17: =SUM(Q12,Q13,Q15) -> 1054.5487
B19: Depreciation (PPE) | S19: Capex Distribution | V19: D&A Distribution
B20: Beginning Accumulating Depreciation | G20: -37 | H20: -58 | I20: -77 | J20: -100 | K20: -120 | L20: -142 | M20: =L24 -> -167 | N20: =M24 -> -219.22789 | O20: =N24 -> -273.27345 | P20: =O24 -> -330.9337 | Q20: =P24 -> -393.36683 | S20: PPE | T20: 0.27 | V20: PPE | W20: 0.21
B21: (+) D&A Expense for PPE | E21: =W20 -> 0.21 | G21: -21 | H21: -22 | I21: -23 | J21: -22 | K21: -25 | L21: -28 | M21: =CHOOSE($V$5,M69,M70,M71,M72)*M68*$E$21*-1 -> -55.227894 | N21: =CHOOSE($V$5,N69,N70,N71,N72)*N68*$E$21*-1 -> -57.045554 | O21: =CHOOSE($V$5,O69,O70,O71,O72)*O68*$E$21*-1 -> -60.660252 | P21: =CHOOSE($V$5,P69,P70,P71,P72)*P68*$E$21*-1 -> -65.433131 | Q21: =CHOOSE($V$5,Q69,Q70,Q71,Q72)*Q68*$E$21*-1 -> -72.00371 | S21: Intangibles | T21: 0.4 | V21: Intangibles | W21: 0.58
B22: % used | M22: =CHOOSE($E$9,M69,M70,M71,M72)*$E$21 -> 0.0315 | N22: =CHOOSE($E$9,N69,N70,N71,N72)*$E$21 -> 0.0315 | O22: =CHOOSE($E$9,O69,O70,O71,O72)*$E$21 -> 0.0315 | P22: =CHOOSE($E$9,P69,P70,P71,P72)*$E$21 -> 0.0315 | Q22: =CHOOSE($E$9,Q69,Q70,Q71,Q72)*$E$21 -> 0.0315 | S22: ROU | T22: 0.33 | V22: ROU | W22: 0.22
B23: (-) Accum Dep. On Disposals | G23: 1 | H23: 2 | I23: 2 | J23: 2 | K23: 2 | L23: 3 | M23: =L23 -> 3 | N23: =M23 -> 3 | O23: =N23 -> 3 | P23: =O23 -> 3 | Q23: =P23 -> 3
B24: Ending Acc. Depreciation | G24: =SUM(G20:G23) -> -57 | H24: =SUM(H20:H23) -> -78 | I24: =SUM(I20:I23) -> -98 | J24: =SUM(J20:J23) -> -120 | K24: =SUM(K20:K23) -> -143 | L24: =SUM(L20:L23) -> -167 | M24: =SUM(M20,M21,M23) -> -219.22789 | N24: =SUM(N20,N21,N23) -> -273.27345 | O24: =SUM(O20,O21,O23) -> -330.9337 | P24: =SUM(P20,P21,P23) -> -393.36683 | Q24: =SUM(Q20,Q21,Q23) -> -462.37054
B25: Net PPE | G25: =SUM(G17,G24) -> 89.166667 | H25: =SUM(H17,H24) -> 101.2053 | I25: =SUM(I17,I24) -> 108.16667 | J25: =SUM(J17,J24) -> 122.17308 | K25: =SUM(K17,K24) -> 182.16312 | L25: =SUM(L17,L24) -> 281.35 | M25: =SUM(M17,M24) -> 320.39686 | N25: =SUM(N17,N24) -> 360.80707 | ... Q25: =SUM(Q17,Q24) -> 592.17814
G26: =-G21/G25 -> 0.23551402 | H26: =-H21/H25 -> 0.21737992 | I26: =-I21/I25 -> 0.21263482 | J26: =-J21/J25 -> 0.18007241 | K26: =-K21/K25 -> 0.13723963 | L26: =-L21/L25 -> 0.099520171
B27: Intangible Assets | S27: Core Assumptions:
B28: Beginning Net intangibles | G28: 403 | H28: 386 | I28: 385 | J28: 385 | K28: 399 | L28: 667 | M28: =L34 -> 673.17091 | N28: =M34 -> 651.64928 | O28: =N34 -> 631.75529 | P28: =O34 -> 641.97967 | Q28: =P34 -> 669.80721 | S28: Disposal is fully depreciated, so held constant
B29: (+) Capex (capitalised R&D) | E29: =T21 -> 0.4 | G29: 59 | H29: 66 | I29: 66 | J29: 60 | K29: 69 | L29: 114 | M29: =$E$29*M65 -> 134.4 | N29: =$E$29*N65 -> 140.64019 | O29: =$E$29*O65 -> 175.77877 | P29: =$E$29*P65 -> 203.36538 | Q29: =$E$29*Q65 -> 244.32997 | S29: Righ of Use Assets + 50 Miscallenious assets comprise the Other non-current assets category
B30: % used | G30: =G29/G28 -> 0.14640199 | H30: =H29/H28 -> 0.17098446 | I30: =I29/I28 -> 0.17142857 | J30: =J29/J28 -> 0.15584416 | K30: =K29/K28 -> 0.17293233 | L30: =L29/L28 -> 0.17091454 | M30: =CHOOSE($E$9,M60,M61,M62,M63)*$E$29 -> 0.04 | N30: =CHOOSE($E$9,N60,N61,N62,N63)*$E$29 -> 0.04 | O30: =CHOOSE($E$9,O60,O61,O62,O63)*$E$29 -> 0.04 | P30: =CHOOSE($E$9,P60,P61,P62,P63)*$E$29 -> 0.04 | Q30: =CHOOSE($E$9,Q60,Q61,Q62,Q63)*$E$29 -> 0.04
B31: (-) Amortisation Expenses | E31: =W21 -> 0.58 | G31: -78 | H31: -80 | I31: -82 | J31: -59 | K31: -61 | L31: -91 | M31: =$E$31*M74 -> 147.92163 | N31: =$E$31*N74 -> 152.53418 | O31: =$E$31*O74 -> 157.55439 | P31: =$E$31*P74 -> 167.53784 | Q31: =$E$31*Q74 -> 180.72008 | S31: PPE
B32: % used | M32: =CHOOSE($V$6,M78,M79,M80,M81)*$E$31 -> 0.0029 | N32: =CHOOSE($V$6,N78,N79,N80,N81)*$E$31 -> 0.0029 | O32: =CHOOSE($V$6,O78,O79,O80,O81)*$E$31 -> 0.0029 | P32: =CHOOSE($V$6,P78,P79,P80,P81)*$E$31 -> 0.0029 | Q32: =CHOOSE($V$6,Q78,Q79,Q80,Q81)*$E$31 -> 0.0029 | S32: Capxe is taken as a share of Revenue and then devided by the diffrent investment categories (PPE, Intangibles, Right of Use).
B33: (-) Disposals/Impairments | G33: 0 | H33: -13 | I33: 0 | J33: -1 | K33: -8 | L33: -17 | M33: -8 | N33: -8 | O33: -8 | P33: -8 | Q33: -8 | S33: Although it is not actually capex but expansion/new lease agreements
B34: Ending Net Intangibles | G34: =SUM(G28:G33) -> 384.1464 | H34: =SUM(H28:H33) -> 359.17098 | I34: =SUM(I28:I33) -> 369.17143 | J34: =SUM(J28:J33) -> 385.15584 | K34: =SUM(K28:K33) -> 399.17293 | L34: =SUM(L28:L33) -> 673.17091 | M34: =SUM(M28, M29, -M31, M33) -> 651.64928 | N34: =SUM(N28, N29, -N31, N33) -> 631.75529 | O34: =SUM(O28, O29, -O31, O33) -> 641.97967 | P34: =SUM(P28, P29, -P31, P33) -> 669.80721 | Q34: =SUM(Q28, Q29, -Q31, Q33) -> 725.41711 | S34: this serves as a usefull ploy in order to estimate, how much production items are needed to scale with the revenue growth expected.
B36: Purchase of Intangibls | M36: =M29 -> 134.4 | N36: =N29 -> 140.64019 | O36: =O29 -> 175.77877 | P36: =P29 -> 203.36538 | Q36: =Q29 -> 244.32997 | S36: Disposals are reductions of PPE assets other than depreciation, which is the orderly book value reduction of assets
B37: Capex PPE + CAPEX ROU | M37: =M13+M45 -> 208.88 | N37: =N13+N45 -> 218.5783 | O37: =O13+O45 -> 273.1895 | P37: =P13+P45 -> 316.0637 | Q37: =Q13+Q45 -> 379.7295 | S37: therefore, they can be taken as a share of gross assets, since they will also scale with the amount of assets aquired.
S39: Depreciation
B40: Goodwill | G40: 647 | H40: 627 | I40: 651 | J40: 658 | K40: 658 | L40: 1115 | M40: =L40 -> 1115 | N40: =M40 -> 1115 | O40: =N40 -> 1115 | P40: =O40 -> 1115 | Q40: =P40 -> 1115 | S40: This is linked to the total gross assets, since those are the assets actually depreciationg.
B41: Intangibles + Goodwill | G41: =G34+G40 -> 1031.1464 | H41: =H34+H40 -> 986.17098 | I41: =I34+I40 -> 1020.1714 | J41: =J34+J40 -> 1043.1558 | K41: =K34+K40 -> 1057.1729 | L41: =L34+L40 -> 1788.1709 | M41: =SUM(M34,M40) -> 1766.6493 | N41: =SUM(N34,N40) -> 1746.7553 | O41: =SUM(O34,O40) -> 1756.9797 | P41: =SUM(P34,P40) -> 1784.8072 | Q41: =SUM(Q34,Q40) -> 1840.4171 | S41: Again, this is forecast as a share of beginning gross assets and then split among the three categories, although they are called Amortisation
S42: for intangible assets.
B43: Right-of-Use Assets | S43: The net effect of Capex and D&A for each item is then the actual change (+/- misscallenious items) that happens to the balance sheet position.
B44: Beginning Net ROU Assets | G44: 147 | H44: 155 | I44: 144 | J44: 141 | K44: 189 | L44: 249 | M44: =L49 -> 249 | N44: =M49 -> 303.77179 | O44: =N49 -> 361.94216 | P44: =O49 -> 447.19763 | Q44: =P49 -> 551.42524
B45: (+) Addition (new Leases) | E45: =T22 -> 0.33 | G45: 21 | H45: 10 | I45: 16 | J45: 73 | K45: 95 | L45: 22 | M45: =$E$45*M65 -> 110.88 | N45: =$E$45*N65 -> 116.02816 | O45: =$E$45*O65 -> 145.01748 | P45: =$E$45*P65 -> 167.77644 | Q45: =$E$45*Q65 -> 201.57223
B46: % used | M46: =CHOOSE($E$9,M69,M70,M71,M72)*$E$45 -> 0.0495 | N46: =CHOOSE($E$9,N69,N70,N71,N72)*$E$45 -> 0.0495 | O46: =CHOOSE($E$9,O69,O70,O71,O72)*$E$45 -> 0.0495 | P46: =CHOOSE($E$9,P69,P70,P71,P72)*$E$45 -> 0.0495 | Q46: =CHOOSE($E$9,Q69,Q70,Q71,Q72)*$E$45 -> 0.0495 | S46: Capex
B47: (-) D&A Expenses (ROU) | E47: =W22 -> 0.22 | G47: -17 | H47: -19 | I47: -21 | J47: -23 | K47: -33 | L47: -22 | M47: =$E$47*M74 -> 56.108206 | N47: =$E$47*N74 -> 57.857794 | O47: =$E$47*O74 -> 59.762009 | P47: =$E$47*P74 -> 63.548835 | Q47: =$E$47*Q74 -> 68.548995 | S47: The assumption for capex is derived from a) historical figures through baysian thinking as a baseline. But b) then the companies own forecast as well as industry
B48: % used | M48: =CHOOSE($E$9,M69,M70,M71,M72)*$E$47 -> 0.033 | N48: =CHOOSE($E$9,N69,N70,N71,N72)*$E$47 -> 0.033 | O48: =CHOOSE($E$9,O69,O70,O71,O72)*$E$47 -> 0.033 | P48: =CHOOSE($E$9,P69,P70,P71,P72)*$E$47 -> 0.033 | Q48: =CHOOSE($E$9,Q69,Q70,Q71,Q72)*$E$47 -> 0.033 | S48: growth data and the disproportionat growth rates for military budgets especially in germany are factored in. This is needed, because Revenue expansion and the conversion rate of Backlog
B49: Ending Net ROU Assets | D49: (+50 other noncurrent) | G49: =SUM(G44:G47) -> 151 | H49: =SUM(H44:H47) -> 146 | I49: =SUM(I44:I47) -> 139 | J49: =SUM(J44:J47) -> 191 | K49: =SUM(K44:K47) -> 251 | L49: =SUM(L44:L47) -> 249 | M49: =SUM(M44,M45,-M47)+$F$49 -> 303.77179 | N49: =SUM(N44,N45,-N47)+$F$49 -> 361.94216 | O49: =SUM(O44,O45,-O47)+$F$49 -> 447.19763 | P49: =SUM(P44,P45,-P47)+$F$49 -> 551.42524 | Q49: =SUM(Q44,Q45,-Q47)+$F$49 -> 684.44847 | S49: require large upfront investments in machienery and other assets (such as software) to deliver on the deals signed.
B51: Total PPE + ROU | M51: =SUM(M49,M25) -> 624.16865 | N51: =SUM(N49,N25) -> 722.74923 | O51: =SUM(O49,O25) -> 869.00526 | P51: =SUM(P49,P25) -> 1047.7959 | Q51: =SUM(Q49,Q25) -> 1276.6266 | S51: Tax Liabilities are calculated as diffrent tax regiemes for writing down assets. This is done a s simple increase to the depreciation book assumption, in line with industry standards.
B53: Total Net fixed Assets | G53: =SUM(G49,G34,G40,G25) -> 1271.3131 | H53: =SUM(H49,H34,H40,H25) -> 1233.3763 | I53: =SUM(I49,I34,I40,I25) -> 1267.3381 | J53: =SUM(J49,J34,J40,J25) -> 1356.3289 | K53: =SUM(K49,K34,K40,K25) -> 1490.3361 | L53: =SUM(L49,L34,L40,L25) -> 2318.5209 | M53: =SUM(M49,M34,M40,M25) -> 2390.8179 | N53: =SUM(N49,N34,N40,N25) -> 2469.5045 | ... Q53: =SUM(Q49,Q34,Q40,Q25) -> 3117.0437
B55: Sanity Check CAPEX | E55: =SUM(E45,E29,E13) -> 1
B56: Sanity Check D&A | E56: =SUM(E47,E31,E21) -> 1.01
B58: CAPEX | G58: =G45+G29+G13 -> 101 | H58: =H45+H29+H13 -> 107 | I58: =I45+I29+I13 -> 112 | J58: =J45+J29+J13 -> 169 | K58: =K45+K29+K13 -> 210 | L58: =L45+L29+L13 -> 219
B59: % of Revenue | G59: ='IS Neu'!D12 -> 1114.2 | H59: ='IS Neu'!E12 -> 1206.9 | I59: ='IS Neu'!F12 -> 1474 | J59: ='IS Neu'!G12 -> 1707 | K59: ='IS Neu'!H12 -> 1847 | L59: ='IS Neu'!I12 -> 2240
B60: Pessimistic Sceanrio | G60: =G58/G59 -> 0.090647999 | H60: =H58/H59 -> 0.08865689 | I60: =I58/I59 -> 0.075983718 | J60: =J58/J59 -> 0.099004101 | K60: =K58/K59 -> 0.11369789 | L60: =L58/L59 -> 0.097767857 | M60: 0.1 | N60: 0.1 | O60: 0.1 | P60: 0.1 | Q60: 0.1
B61: Realistic Scenario | M61: 0.11 | N61: 0.11 | O61: 0.11 | P61: 0.11 | Q61: 0.11
B62: Optimistic Scenario | M62: 0.12 | N62: 0.12 | O62: 0.12 | P62: 0.12 | Q62: 0.12
B63: Company own Projection | M63: 0.15 | N63: 0.15 | O63: 0.15 | P63: 0.15 | Q63: 0.15
B64: Percentage Used | M64: =CHOOSE($V$4, M60,M61,M62,M63) -> 0.12 | N64: =CHOOSE($V$4, N60,N61,N62,N63) -> 0.12 | O64: =CHOOSE($V$4, O60,O61,O62,O63) -> 0.12 | P64: =CHOOSE($V$4, P60,P61,P62,P63) -> 0.12 | Q64: =CHOOSE($V$4, Q60,Q61,Q62,Q63) -> 0.12
B65: Value | M65: =M64*M9 -> 336 | N65: =N64*N9 -> 351.60048 | O65: =O64*O9 -> 439.44692 | P65: =P64*P9 -> 508.41346 | Q65: =Q64*Q9 -> 610.82494
B67: D&A | J67: (HERE IS THE CRUX if a Value ERROR exists again. Since D&A is dependant on total assets, this will make a diffrence)
B68: as a % of Assets | G68: =G53 -> 1271.3131 | H68: =H53 -> 1233.3763 | I68: =I53 -> 1267.3381 | J68: =J53 -> 1356.3289 | K68: =K53 -> 1490.3361 | L68: =L53 -> 2318.5209 | M68: =M53 -> 2390.8179 | N68: =N53 -> 2469.5045 | ... Q68: =Q53 -> 3117.0437
B69: Pessimistic Sceanrio | G69: =G47+G31+G21 -> -116 | H69: =H47+H31+H21 -> -121 | I69: =I47+I31+I21 -> -126 | J69: =J47+J31+J21 -> -104 | K69: =K47+K31+K21 -> -119 | L69: =L47+L31+L21 -> -141 | M69: 0.15 | N69: 0.15 | O69: 0.15 | P69: 0.15 | Q69: 0.15
B70: Realistic Scenario | G70: =-G69/G68 -> 0.091244244 | H70: =-H69/H68 -> 0.098104692 | I70: =-I69/I68 -> 0.099420984 | J70: =-J69/J68 -> 0.076677566 | K70: =-K69/K68 -> 0.079847763 | L70: =-L69/L68 -> 0.060814634 | M70: 0.14 | N70: 0.14 | O70: 0.14 | P70: 0.14 | Q70: 0.14
B71: Optimistic Scenario | M71: 0.11 | N71: 0.11 | O71: 0.11 | P71: 0.11 | Q71: 0.11
B72: Company own Projection | M72: 0.1 | N72: 0.1 | O72: 0.1 | P72: 0.1 | Q72: 0.1
B73: Percentage used | M73: =CHOOSE($V$5,M69,M70,M71,M72) -> 0.11 | N73: =CHOOSE($V$5,N69,N70,N71,N72) -> 0.11 | O73: =CHOOSE($V$5,O69,O70,O71,O72) -> 0.11 | P73: =CHOOSE($V$5,P69,P70,P71,P72) -> 0.11 | Q73: =CHOOSE($V$5,Q69,Q70,Q71,Q72) -> 0.11
B74: Value | M74: =M73*L68 -> 255.0373 | N74: =N73*M68 -> 262.98997 | O74: =O73*N68 -> 271.6455 | P74: =P73*O68 -> 288.85834 | Q74: =Q73*P68 -> 311.58634
B76: Disposals
B77: as a % of Beginning Gross Assets
B78: Pessimistic Sceanrio | M78: 0.015 | N78: 0.015 | O78: 0.015 | P78: 0.015 | Q78: 0.015
B79: Realistic Scenario | M79: 0.0075 | N79: 0.0075 | O79: 0.0075 | P79: 0.0075 | Q79: 0.0075
B80: Optimistic Scenario | M80: 0.005 | N80: 0.005 | O80: 0.005 | P80: 0.005 | Q80: 0.005
B81: Company own Projection | M81: 0.01 | N81: 0.01 | O81: 0.01 | P81: 0.01 | Q81: 0.01
B84: D&A Total | M84: =SUM(M74)-M33 -> 263.0373 | N84: =SUM(N74)-N33 -> 270.98997 | O84: =SUM(O74)-O33 -> 279.6455 | P84: =SUM(P74)-P33 -> 296.85834 | Q84: =SUM(Q74)-Q33 -> 319.58634
B86: Tax PP&E Scheduel
B87: Beginning Book PPE | G87: =F25 -> 0 | H87: =G25 -> 89.166667 | I87: =H25 -> 101.2053 | J87: =I25 -> 108.16667 | K87: =J25 -> 122.17308 | L87: =K25 -> 182.16312 | M87: =L25 -> 281.35 | N87: =M25 -> 320.39686 | ... Q87: =P25 -> 496.37064
B88: (+) CAPEX | G88: =G13 -> 21 | H88: =H13 -> 31 | I88: =I13 -> 30 | J88: =J13 -> 36 | K88: =K13 -> 46 | L88: =L13 -> 83 | M88: =M13 -> 98 | N88: =N13 -> 102.55014 | ... Q88: =Q13 -> 178.15727
B89: (-) Tax D&A | D89: (+15% above Book D&A) | F89: 0.15 | G89: =(G70+$F$89)*G87 -> 0 | H89: =(H70+$F$89)*H87 -> 22.122668 | I89: =(I70+$F$89)*I87 -> 25.242725 | J89: =(J70+$F$89)*J87 -> 24.518957 | K89: =(K70+$F$89)*K87 -> 28.081208 | L89: =(L70+$F$89)*L87 -> 38.402652 | M89: =(M73+$F$89)*M87 -> 73.151 | N89: =(N73+$F$89)*N87 -> 83.303183 | O89: =(O73+$F$89)*O87 -> 93.809838 | P89: =(P73+$F$89)*P87 -> 109.66998 | Q89: =(Q73+$F$89)*Q87 -> 129.05637
B90: Ending Tax PP&E | G90: =G87+G88-G89 -> 21 | H90: =H87+H88-H89 -> 98.043998 | I90: =I87+I88-I89 -> 105.96257 | J90: =J87+J88-J89 -> 119.64771 | K90: =K87+K88-K89 -> 140.09187 | L90: =L87+L88-L89 -> 226.76047 | M90: =M87+M88-M89 -> 306.199 | N90: =N87+N88-N89 -> 339.64381 | ... Q90: =Q87+Q88-Q89 -> 545.47154
B91: Ending Book PPE | M91: =M25 -> 320.39686 | N91: =N25 -> 360.80707 | O91: =O25 -> 421.80763 | P91: =P25 -> 496.37064 | Q91: =Q25 -> 592.17814
B92: Cumulative Timing Diffrence | M92: =M91-M90 -> 14.197856 | N92: =N91-N90 -> 21.163257 | O92: =O91-O90 -> 26.638379 | P92: =P91-P90 -> 35.945732 | Q92: =Q91-Q90 -> 46.706594
B94: Ending Deferred Tax Liabilitiy | F94: 0.283 | M94: =M92*$F$94 -> 4.0179932 | N94: =N92*$F$94 -> 5.9892017 | O94: =O92*$F$94 -> 7.5386611 | P94: =P92*$F$94 -> 10.172642 | Q94: =Q92*$F$94 -> 13.217966
B97: Share of CAPEX | D97: 2019 | E97: 2020 | F97: 2021 | G97: 2022 | H97: 2023 | I97: 2024
B99: Total | D99: =G45+G29+G13 -> 101 | E99: =H45+H29+H13 -> 107 | F99: =I45+I29+I13 -> 112 | G99: =J45+J29+J13 -> 169 | H99: =K45+K29+K13 -> 210 | I99: =L45+L29+L13 -> 219 | J99: Average
B100: PPE | D100: =G13/D99 -> 0.20792079 | E100: =H13/E99 -> 0.28971963 | F100: =I13/F99 -> 0.26785714 | G100: =J13/G99 -> 0.21301775 | H100: =K13/H99 -> 0.21904762 | I100: =L13/I99 -> 0.37899543 | J100: =AVERAGE(G100:I100) -> 0.2703536
B101: Intangible | D101: =G29/D99 -> 0.58415842 | E101: =H29/E99 -> 0.61682243 | F101: =I29/F99 -> 0.58928571 | G101: =J29/G99 -> 0.35502959 | H101: =K29/H99 -> 0.32857143 | I101: =L29/I99 -> 0.52054795 | J101: =AVERAGE(G101:I101) -> 0.40138299
B102: ROU | D102: =G45/D99 -> 0.20792079 | E102: =H45/E99 -> 0.093457944 | F102: =I45/F99 -> 0.14285714 | G102: =J45/G99 -> 0.43195266 | H102: =K45/H99 -> 0.45238095 | I102: =L45/I99 -> 0.10045662 | J102: =AVERAGE(G102:I102) -> 0.32826341
B105: Share of D&A | D105: 2019 | E105: 2020 | F105: 2021 | G105: 2022 | H105: 2023 | I105: 2024
B106: Total | D106: =G47+G31+G21 -> -116 | E106: =H47+H31+H21 -> -121 | F106: =I47+I31+I21 -> -126 | G106: =J47+J31+J21 -> -104 | H106: =K47+K31+K21 -> -119 | I106: =L47+L31+L21 -> -141
B107: PPE | D107: =G21/D106 -> 0.18103448 | E107: =H21/E106 -> 0.18181818 | F107: =I21/F106 -> 0.18253968 | G107: =J21/G106 -> 0.21153846 | H107: =K21/H106 -> 0.21008403 | I107: =L21/I106 -> 0.19858156 | J107: =AVERAGE(G107:I107) -> 0.20673469
B108: Intangible | D108: =G31/D106 -> 0.67241379 | E108: =H31/E106 -> 0.66115702 | F108: =I31/F106 -> 0.65079365 | G108: =J31/G106 -> 0.56730769 | H108: =K31/H106 -> 0.51260504 | I108: =L31/I106 -> 0.64539007 | J108: =AVERAGE(G108:I108) -> 0.57510094
B109: ROU | D109: =G47/D106 -> 0.14655172 | E109: =H47/E106 -> 0.15702479 | F109: =I47/F106 -> 0.16666667 | G109: =J47/G106 -> 0.22115385 | H109: =K47/H106 -> 0.27731092 | I109: =L47/I106 -> 0.15602837 | J109: =AVERAGE(G109:I109) -> 0.21816438
B114: (Because Timing Diffrence * Tax Rate -> Tax Liability)

Sheet WC & other Assets (updated) 
A1: =_xlfn.CONCAT(Inputs!C7, " - ", "Cash Flow", " - ", "in ", Inputs!C9, " ", Inputs!C10) -> HAG - Cash Flow - in Euro millions
V2: Versions
B4: Financial year end | G4: =EDATE(Inputs!$C$8, G5*12) -> 43830 | H4: =EDATE(Inputs!$C$8, H5*12) -> 44196 | I4: =EDATE(Inputs!$C$8, I5*12) -> 44561 | J4: =EDATE(Inputs!$C$8, J5*12) -> 44926 | K4: =EDATE(Inputs!$C$8, K5*12) -> 45291 | L4: =EDATE(Inputs!$C$8, L5*12) -> 45657 | M4: =EDATE(Inputs!$C$8, M5*12) -> 46022 | N4: =EDATE(Inputs!$C$8, N5*12) -> 46387 | ... Q4: =EDATE(Inputs!$C$8, Q5*12) -> 47483 | S4: Inventories | V4: =Inputs!W7 -> 3
B5: Time-line counter | G5: -5 | H5: -4 | I5: -3 | J5: -2 | K5: -1 | L5: 0 | M5: 1 | N5: 2 | O5: 3 | P5: 4 | Q5: 5
B6: Currency and units | G6: =_xlfn.CONCAT(Inputs!$C$9, " ", Inputs!$C$10) -> Euro millions | H6: =_xlfn.CONCAT(Inputs!$C$9, " ", Inputs!$C$10) -> Euro millions | I6: =_xlfn.CONCAT(Inputs!$C$9, " ", Inputs!$C$10) -> Euro millions | J6: =_xlfn.CONCAT(Inputs!$C$9, " ", Inputs!$C$10) -> Euro millions | K6: =_xlfn.CONCAT(Inputs!$C$9, " ", Inputs!$C$10) -> Euro millions | L6: =_xlfn.CONCAT(Inputs!$C$9, " ", Inputs!$C$10) -> Euro millions | M6: =_xlfn.CONCAT(Inputs!$C$9, " ", Inputs!$C$10) -> Euro millions | N6: =_xlfn.CONCAT(Inputs!$C$9, " ", Inputs!$C$10) -> Euro millions | ... Q6: =_xlfn.CONCAT(Inputs!$C$9, " ", Inputs!$C$10) -> Euro millions | S6: Trade Recievables | V6: =Inputs!W9 -> 3
B7: Time-Stamp | G7: =IF(G5<=0, "Historical", "Forecasted") -> Historical | H7: =IF(H5<=0, "Historical", "Forecasted") -> Historical | I7: =IF(I5<=0, "Historical", "Forecasted") -> Historical | J7: =IF(J5<=0, "Historical", "Forecasted") -> Historical | K7: =IF(K5<=0, "Historical", "Forecasted") -> Historical | L7: =IF(L5<=0, "Historical", "Forecasted") -> Historical | M7: =IF(M5<=0, "Historical", "Forecasted") -> Forecasted | N7: =IF(N5<=0, "Historical", "Forecasted") -> Forecasted | ... Q7: =IF(Q5<=0, "Historical", "Forecasted") -> Forecasted | S7: Contract Assets | V7: =Inputs!W10 -> 3
S8: Trade Payable | V8: =Inputs!W11 -> 3
B9: Scenario | E9: 4 | S9: Contract Liabilites | V9: =Inputs!W12 -> 3
B11: Revenue | G11: =G20 -> 1114.2 | H11: =H20 -> 1206.9 | I11: =I20 -> 1474 | J11: =J20 -> 1707 | K11: =K20 -> 1847 | L11: =L20 -> 2240 | M11: =M20 -> 2800 | N11: =N20 -> 2930.004 | ... Q11: =Q20 -> 5090.2078 | S11: Other current assets | V11: =Inputs!W14 -> 3
B12: Operating Cost | G12: =G15 -> 859.3 | H12: =H15 -> 936.1 | I12: =I15 -> 1144 | J12: =J15 -> 1314 | K12: =K15 -> 1427 | L12: =L15 -> 1732 | M12: =M15 -> 1960 | N12: =N15 -> 2021.7028 | ... Q12: =Q15 -> 3461.3413 | S12: Other Current Liabilities | V12: =Inputs!W15 -> 3
S13: Other Non-current Liabiltiy | V13: =Inputs!W16 -> 2
B14: Inventories
B15: Operating Costs | G15: ='IS Neu'!D13*-1 -> 859.3 | H15: ='IS Neu'!E13*-1 -> 936.1 | I15: ='IS Neu'!F13*-1 -> 1144 | J15: ='IS Neu'!G13*-1 -> 1314 | K15: ='IS Neu'!H13*-1 -> 1427 | L15: ='IS Neu'!I13*-1 -> 1732 | M15: ='Revenue & Expenses (updated)'!M45 -> 1960 | N15: ='Revenue & Expenses (updated)'!N45 -> 2021.7028 | O15: ='Revenue & Expenses (updated)'!O45 -> 2490.1992 | P15: ='Revenue & Expenses (updated)'!P45 -> 2881.0096 | Q15: ='Revenue & Expenses (updated)'!Q45 -> 3461.3413
B16: Inventory Levels | G16: ='BS Neu'!D22 -> 411.1 | H16: ='BS Neu'!E22 -> 403.7 | I16: ='BS Neu'!F22 -> 444 | J16: ='BS Neu'!G22 -> 516 | K16: ='BS Neu'!H22 -> 625 | L16: ='BS Neu'!I22 -> 719 | M16: =M17/365*M15 -> 751.78082 | N16: =N17/365*N15 -> 775.44763 | O16: =O17/365*O15 -> 955.14491 | P16: =P17/365*P15 -> 1105.0448 | Q16: =Q17/365*Q15 -> 1327.6378 | S16: Important Assumptions
B17: Inventory Days outstanding | G17: =(G16/G15)*365 -> 174.62062 | H17: =(H16/H15)*365 -> 157.40893 | I17: =(I16/I15)*365 -> 141.66084 | J17: =(J16/J15)*365 -> 143.33333 | K17: =(K16/K15)*365 -> 159.86335 | L17: =(L16/L15)*365 -> 151.52136 | M17: =CHOOSE($V$4,M40,M41,M42,M43) -> 140 | N17: =CHOOSE($V$4,N40,N41,N42,N43) -> 140 | O17: =CHOOSE($V$4,O40,O41,O42,O43) -> 140 | P17: =CHOOSE($V$4,P40,P41,P42,P43) -> 140 | Q17: =CHOOSE($V$4,Q40,Q41,Q42,Q43) -> 140 | S17: Contract Assets (as unbilled revenue) are NOT part of trade recievables, but separatly forecasted
S18: Contract liabilities (as revenue for unfinished services) is NOT part of trade payables, but separatly forecasted
B19: Recievables (withour contract assets in the forecast) | S19: These are essentially liabilites (cash we have recieved) for services/products we still have to deliver.
B20: Revenue | G20: ='IS Neu'!D12 -> 1114.2 | H20: ='IS Neu'!E12 -> 1206.9 | I20: ='IS Neu'!F12 -> 1474 | J20: ='IS Neu'!G12 -> 1707 | K20: ='IS Neu'!H12 -> 1847 | L20: ='IS Neu'!I12 -> 2240 | M20: ='IS Neu'!J12 -> 2800 | N20: ='IS Neu'!K12 -> 2930.004 | ... Q20: ='IS Neu'!N12 -> 5090.2078
B21: Account Recievables | G21: ='BS Neu'!D23 -> 290.8 | H21: ='BS Neu'!E23 -> 282 | I21: ='BS Neu'!F23 -> 309 | J21: ='BS Neu'!G23 -> 323 | K21: ='BS Neu'!H23 -> 382 | L21: ='BS Neu'!I23 -> 426
B22: Days Sales Ountstanding | G22: =G21/G20*365 -> 95.262969 | H22: =H21/H20*365 -> 85.284613 | I22: =I21/I20*365 -> 76.516282 | J22: =J21/J20*365 -> 69.065612 | K22: =K21/K20*365 -> 75.489984 | L22: =L21/L20*365 -> 69.415179 | S22: Other current liabilities:
B23: Contract Assets | M23: =M20*M24 -> 308 | N23: =N20*N24 -> 322.30044 | O23: =O20*O24 -> 402.82635 | P23: =P20*P24 -> 466.04567 | Q23: =Q20*Q24 -> 559.92286 | S23: Include Liabilities for tax (Including income tax), social security/towards personell
B24: % of Revenue | M24: =CHOOSE($V$7, M58,M59,M60,M61) -> 0.11 | N24: =CHOOSE($V$7, N58,N59,N60,N61) -> 0.11 | O24: =CHOOSE($V$7, O58,O59,O60,O61) -> 0.11 | P24: =CHOOSE($V$7, P58,P59,P60,P61) -> 0.11 | Q24: =CHOOSE($V$7, Q58,Q59,Q60,Q61) -> 0.11 | S24: V1: Growing liabilities share (increased personell cost as forecast by management of 5% DE, 2,5% FR, 4% UK -> Average 3,8% increase
B25: Actual accounts recievable | M25: =(M26/365)*M20 -> 421.91781 | N25: =(N26/365)*N20 -> 441.50745 | O25: =(O26/365)*O20 -> 551.81691 | P25: =(P26/365)*P20 -> 638.41873 | Q25: =(Q26/365)*Q20 -> 767.01761 | S25: V2: reduced liablities (Synergies due to the ESG Aquisition) | X25: (2,5% increased efficiency annually)
B26: DSO | M26: =CHOOSE($V$6,M46,M47,M48,M49) -> 55 | N26: =CHOOSE($V$6,N46,N47,N48,N49) -> 55 | O26: =CHOOSE($V$6,O46,O47,O48,O49) -> 55 | P26: =CHOOSE($V$6,P46,P47,P48,P49) -> 55 | Q26: =CHOOSE($V$6,Q46,Q47,Q48,Q49) -> 55 | S26: V3: Constant Liabilities share (growing with overall business)
B28: Payables | S28: Other non-current liabilities:
B29: Operating Costs | G29: =G15 -> 859.3 | H29: =H15 -> 936.1 | I29: =I15 -> 1144 | J29: =J15 -> 1314 | K29: =K15 -> 1427 | L29: =L15 -> 1732 | M29: =M15 -> 1960 | N29: =N15 -> 2021.7028 | ... Q29: =Q15 -> 3461.3413 | S29: V1: Use last historical value as a constant due to new structure of Hensoldt after the ESG Aquisition
B30: Accounts Payable | G30: ='BS Neu'!D50 -> 168.8 | H30: ='BS Neu'!E50 -> 164 | I30: ='BS Neu'!F50 -> 269 | J30: ='BS Neu'!G50 -> 379 | K30: ='BS Neu'!H50 -> 457 | L30: ='BS Neu'!I50 -> 546 | S30: V2: Average of last 3 Years
B31: Days Payables Outstanding | G31: =G30/G29*365 -> 71.700221 | H31: =H30/H29*365 -> 63.94616 | I31: =I30/I29*365 -> 85.826049 | J31: =J30/J29*365 -> 105.27778 | K31: =K30/K29*365 -> 116.89208 | L31: =L30/L29*365 -> 115.06351
B32: Contract liabilities | G32: =G63 -> 317.1 | H32: =H63 -> 416.8 | I32: =I63 -> 500 | J32: =J63 -> 488 | K32: =K63 -> 578 | L32: =L63 -> 776 | M32: =M33*M11 -> 868 | N32: =N33*N11 -> 908.30124 | O32: =O33*O11 -> 1135.2379 | P32: =P33*P11 -> 1313.4014 | Q32: =Q33*Q11 -> 1577.9644
B33: % of revenue | G33: =G32/G11 -> 0.28459882 | H33: =H32/H11 -> 0.34534758 | I33: =I32/I11 -> 0.33921303 | J33: =J32/J11 -> 0.28588166 | K33: =K32/K11 -> 0.3129399 | L33: =L32/L11 -> 0.34642857 | M33: =CHOOSE($V$9,M64,M65,M66,M67) -> 0.31 | N33: =CHOOSE($V$9,N64,N65,N66,N67) -> 0.31 | O33: =CHOOSE($V$9,O64,O65,O66,O67) -> 0.31 | P33: =CHOOSE($V$9,P64,P65,P66,P67) -> 0.31 | Q33: =CHOOSE($V$9,Q64,Q65,Q66,Q67) -> 0.31
B34: Actual trade payables | M34: =M35/365*M12 -> 483.28767 | N34: =N35/365*N12 -> 498.50205 | O34: =O35/365*O12 -> 614.02173 | P34: =P35/365*P12 -> 710.38593 | Q34: =Q35/365*Q12 -> 853.48142
B35: DPO | M35: =CHOOSE($V$8,M52,M53,M54,M55) -> 90 | N35: =CHOOSE($V$8,N52,N53,N54,N55) -> 90 | O35: =CHOOSE($V$8,O52,O53,O54,O55) -> 90 | P35: =CHOOSE($V$8,P52,P53,P54,P55) -> 90 | Q35: =CHOOSE($V$8,Q52,Q53,Q54,Q55) -> 90
B37: Chash Conversion Cycle | G37: =G17+G22-G31 -> 198.18337 | H37: =H17+H22-H31 -> 178.74738 | I37: =I17+I22-I31 -> 132.35107 | J37: =J17+J22-J31 -> 107.12117 | K37: =K17+K22-K31 -> 118.46125 | L37: =L17+L22-L31 -> 105.87303 | M37: =M17+M26-M35 -> 105 | N37: =N17+N26-N35 -> 105 | O37: =O17+O26-O35 -> 105 | P37: =P17+P26-P35 -> 105 | Q37: =Q17+Q26-Q35 -> 105
B39: Inventories (DOI)
B40: Pessimistic Sceanrio | M40: 160 | N40: 162 | O40: 164 | P40: 166 | Q40: 168 | S40: DOI
B41: Realistic Scenario | M41: 150 | N41: 150 | O41: 150 | P41: 150 | Q41: 150 | S41: Informed by historical values, needs to scale with revenue in order to fullfill the backlog
B42: Optimistic Scenario | M42: 140 | N42: 140 | O42: 140 | P42: 140 | Q42: 140
B43: Company own Projection | M43: 145 | N43: 140 | O43: 135 | P43: 135 | Q43: 135 | S43: DSO
S44: In line with historical trends, but contract assets are separated and forecast as a share from revenue. So not directly lined to historical values
B45: Recievables (DSO)
B46: Pessimistic Sceanrio | M46: 70 | N46: 70 | O46: 70 | P46: 70 | Q46: 70 | S46: DPO
B47: Realistic Scenario | M47: 65 | N47: 65 | O47: 65 | P47: 65 | Q47: 65 | S47: Same story as DSO, but here Contract liabilities are separated
B48: Optimistic Scenario | M48: 55 | N48: 55 | O48: 55 | P48: 55 | Q48: 55
B49: Company own Projection | M49: 50 | N49: 50 | O49: 50 | P49: 50 | Q49: 50 | S49: Other current assets
S50: Miscallanious items, that can only be forecast in bulk
B51: Payables (DPO)
B52: Pessimistic Sceanrio | M52: 110 | N52: 110 | O52: 110 | P52: 110 | Q52: 110
B53: Realistic Scenario | M53: 100 | N53: 100 | O53: 100 | P53: 100 | Q53: 100
B54: Optimistic Scenario | M54: 90 | N54: 90 | O54: 90 | P54: 90 | Q54: 90
B55: Company own Projection | M55: 80 | N55: 80 | O55: 80 | P55: 80 | Q55: 80
B57: Contract Assets % of Revenue
B58: Pessimistic Sceanrio | M58: 0.13 | N58: 0.13 | O58: 0.13 | P58: 0.13 | Q58: 0.13
B59: Realistic Scenario | M59: 0.12 | N59: 0.12 | O59: 0.12 | P59: 0.12 | Q59: 0.12
B60: Optimistic Scenario | M60: 0.11 | N60: 0.11 | O60: 0.11 | P60: 0.11 | Q60: 0.11
B61: Company own Projection | M61: 0.1 | N61: 0.1 | O61: 0.1 | P61: 0.1 | Q61: 0.1
B63: Contract liabilites as % of Revenue | G63: ='BS Neu'!D51 -> 317.1 | H63: ='BS Neu'!E51 -> 416.8 | I63: ='BS Neu'!F51 -> 500 | J63: ='BS Neu'!G51 -> 488 | K63: ='BS Neu'!H51 -> 578 | L63: ='BS Neu'!I51 -> 776
B64: Pessimistic Sceanrio | G64: =G63/G11 -> 0.28459882 | H64: =H63/H11 -> 0.34534758 | I64: =I63/I11 -> 0.33921303 | J64: =J63/J11 -> 0.28588166 | K64: =K63/K11 -> 0.3129399 | L64: =L63/L11 -> 0.34642857 | M64: 0.35 | N64: 0.35 | O64: 0.35 | P64: 0.35 | Q64: 0.35
B65: Realistic Scenario | M65: 0.33 | N65: 0.33 | O65: 0.33 | P65: 0.33 | Q65: 0.33
B66: Optimistic Scenario | M66: 0.31 | N66: 0.31 | O66: 0.31 | P66: 0.31 | Q66: 0.31
B67: Company own Projection | M67: 0.3 | N67: 0.3 | O67: 0.3 | P67: 0.3 | Q67: 0.3
B69: Other Current assets | G69: =G11 -> 1114.2 | H69: =H11 -> 1206.9 | I69: =I11 -> 1474 | J69: =J11 -> 1707 | K69: =K11 -> 1847 | L69: =L11 -> 2240 | M69: =M11 -> 2800 | N69: =N11 -> 2930.004 | ... Q69: =Q11 -> 5090.2078
B70: % of Revenue | G70: ='BS Neu'!D25 -> 58.1 | H70: ='BS Neu'!E25 -> 98.6 | I70: ='BS Neu'!F25 -> 177 | J70: ='BS Neu'!G25 -> 163 | K70: ='BS Neu'!H25 -> 150 | L70: ='BS Neu'!I25 -> 143 | M70: =CHOOSE($V$11, M71,M72,M73)*M69 -> 280 | N70: =CHOOSE($V$11, N71,N72,N73)*N69 -> 293.0004 | O70: =CHOOSE($V$11, O71,O72,O73)*O69 -> 366.20577 | P70: =CHOOSE($V$11, P71,P72,P73)*P69 -> 423.67788 | Q70: =CHOOSE($V$11, Q71,Q72,Q73)*Q69 -> 509.02078
B71: V1 | G71: =G70/G69 -> 0.052145037 | H71: =H70/H69 -> 0.081696909 | I71: =I70/I69 -> 0.12008141 | J71: =J70/J69 -> 0.095489162 | K71: =K70/K69 -> 0.081212777 | L71: =L70/L69 -> 0.063839286 | M71: 0.06 | N71: 0.06 | O71: 0.06 | P71: 0.06 | Q71: 0.06
B72: V2 | M72: 0.08 | N72: 0.08 | O72: 0.08 | P72: 0.08 | Q72: 0.08
B73: V3 | M73: 0.1 | N73: 0.1 | O73: 0.1 | P73: 0.1 | Q73: 0.1
B75: Contract balane | G75: ='BS Neu'!D24-'BS Neu'!D51 -> -151.2 | H75: ='BS Neu'!E24-'BS Neu'!E51 -> -212.4 | I75: ='BS Neu'!F24-'BS Neu'!F51 -> -330 | J75: ='BS Neu'!G24-'BS Neu'!G51 -> -306 | K75: ='BS Neu'!H24-'BS Neu'!H51 -> -382 | L75: ='BS Neu'!I24-'BS Neu'!I51 -> -391 | M75: =M23-M32 -> -560 | N75: =N23-N32 -> -586.0008 | O75: =O23-O32 -> -732.41154 | P75: =P23-P32 -> -847.35577 | Q75: =Q23-Q32 -> -1018.0416
B77: Other Current liabilities | G77: ='BS Neu'!D53 -> 67.1 | H77: ='BS Neu'!E53 -> 86.9 | I77: ='BS Neu'!F53 -> 94 | J77: ='BS Neu'!G53 -> 101 | K77: ='BS Neu'!H53 -> 136 | L77: ='BS Neu'!I53 -> 151 | M77: =M78*M12 -> 176.4 | N77: =N78*N12 -> 181.95325 | O77: =O78*O12 -> 224.11793 | P77: =P78*P12 -> 259.29086 | Q77: =Q78*Q12 -> 311.52072
B78: Share of OpEX in % | G78: =G77/G12 -> 0.078086815 | H78: =H77/H12 -> 0.092831962 | I78: =I77/I12 -> 0.082167832 | J78: =J77/J12 -> 0.076864536 | K78: =K77/K12 -> 0.095304835 | L78: =L77/L12 -> 0.087182448 | M78: =CHOOSE($V$12,M79,M80,M81) -> 0.09 | N78: =CHOOSE($V$12,N79,N80,N81) -> 0.09 | O78: =CHOOSE($V$12,O79,O80,O81) -> 0.09 | P78: =CHOOSE($V$12,P79,P80,P81) -> 0.09 | Q78: =CHOOSE($V$12,Q79,Q80,Q81) -> 0.09
B79: V1: | M79: =L78*(1.038) -> 0.090495381 | N79: =M79*(1.038) -> 0.093934206 | O79: =N79*(1.038) -> 0.097503705 | P79: =O79*(1.038) -> 0.10120885 | Q79: =P79*(1.038) -> 0.10505478
B80: V2: | M80: =L78*(0.975) -> 0.085002887 | N80: =M80*0.975 -> 0.082877815 | O80: =N80*0.975 -> 0.080805869 | P80: =O80*0.975 -> 0.078785723 | Q80: =P80*0.975 -> 0.07681608
B81: V3 | M81: 0.09 | N81: 0.09 | O81: 0.09 | P81: 0.09 | Q81: 0.09
B83: Other non-current liabilities | G83: ='BS Neu'!D44 -> 24.2 | H83: ='BS Neu'!E44 -> 25.1 | I83: ='BS Neu'!F44 -> 22 | J83: ='BS Neu'!G44 -> 25 | K83: ='BS Neu'!H44 -> 24 | L83: ='BS Neu'!I44 -> 59 | M83: =M84*M12 -> 45.673907 | N83: =N84*N12 -> 49.994134 | O83: =O84*O12 -> 68.145468 | P83: =P84*P12 -> 72.406694 | Q83: =Q84*Q12 -> 89.102537
B84: Share of OpEX in % | G84: =G83/G12 -> 0.028162458 | H84: =H83/H12 -> 0.026813375 | I84: =I83/I12 -> 0.019230769 | J84: =J83/J12 -> 0.019025875 | K84: =K83/K12 -> 0.0168185 | L84: =L83/L12 -> 0.034064665 | M84: =CHOOSE($V$13, M85,M86) -> 0.023303014 | N84: =CHOOSE($V$13, N85,N86) -> 0.024728726 | O84: =CHOOSE($V$13, O85,O86) -> 0.027365468 | P84: =CHOOSE($V$13, P85,P86) -> 0.025132403 | Q84: =CHOOSE($V$13, Q85,Q86) -> 0.025742199
B85: V1: | M85: 0.03 | N85: 0.03 | O85: 0.03 | P85: 0.03 | Q85: 0.03
B86: V2: | M86: =AVERAGE(J84:L84) -> 0.023303014 | N86: =AVERAGE(K84:L84,M86) -> 0.024728726 | O86: =AVERAGE(L84,M86:N86) -> 0.027365468 | P86: =AVERAGE(M86:O86) -> 0.025132403 | Q86: =AVERAGE(N86:P86) -> 0.025742199
B91: Change in Working Capital
B92: Provisions | G92: ='CF Neu '!G60 -> -0.4 | H92: ='CF Neu '!H60 -> 46.4 | I92: ='CF Neu '!I60 -> 31 | J92: ='CF Neu '!J60 -> -22 | K92: ='CF Neu '!K60 -> 45 | L92: ='CF Neu '!L60 -> -5 | M92: ='Debt & Cash'!K145 -> 165 | N92: ='Debt & Cash'!L145 -> 39.0012 | O92: ='Debt & Cash'!M145 -> 219.61611 | P92: ='Debt & Cash'!N145 -> 172.41634 | Q92: ='Debt & Cash'!O145 -> 256.02869
B93: Inventories | G93: {='CF Neu '!G61:L61} -> -17.8 | H93: 5.3 | I93: -44 | J93: -75 | K93: -128 | L93: -103 | M93: =L16-M16 -> -32.780822 | N93: =M16-N16 -> -23.666812 | O93: =N16-O16 -> -179.69728 | P93: =O16-P16 -> -149.89987 | Q93: =P16-Q16 -> -222.59298
B94: Contract balances | G94: {='CF Neu '!G62:L62} -> -89.4 | H94: 61.4 | I94: 111 | J94: -25 | K94: 65 | L94: 34 | M94: =L75-M75 -> 169 | N94: =M75-N75 -> 26.0008 | O94: =N75-O75 -> 146.41074 | P94: =O75-P75 -> 114.94423 | Q94: =P75-Q75 -> 170.68579
B95: Trade receivables | G95: {='CF Neu '!G63:L63} -> 56.4 | H95: 5.3 | I95: -22 | J95: -13 | K95: -66 | L95: -11 | M95: =L21-M25 -> 4.0821918 | N95: =M25-N25 -> -19.589644 | O95: =N25-O25 -> -110.30946 | P95: =O25-P25 -> -86.601814 | Q95: =P25-Q25 -> -128.59889
B96: Trade payables | G96: {='CF Neu '!G64:L64} -> -13.4 | H96: -8.6 | I96: 107 | J96: 110 | K96: 78 | L96: 69 | M96: =M34-L30 -> -62.712329 | N96: =N34-M34 -> 15.214379 | O96: =O34-N34 -> 115.51968 | P96: =P34-O34 -> 96.3642 | Q96: =Q34-P34 -> 143.09549
B97: Other assets and liabilities | G97: {='CF Neu '!G65:L65} -> 4.6 | H97: -17.8 | I97: -83 | J97: 42 | K97: 52 | L97: 44 | M97: =M105 -> -146.30697 | N97: =N105 -> -4.1196379 | O97: =O105 -> -18.479335 | P97: =P105 -> -22.42654 | Q97: =Q105 -> -22.934007
M98: =SUM(M92:M97) -> 96.282073 | N98: =SUM(N92:N97) -> 32.840285 | O98: =SUM(O92:O97) -> 173.06045 | P98: =SUM(P92:P97) -> 124.79654 | Q98: =SUM(Q92:Q97) -> 195.6841
B100: Other Non-Current Assets | G100: ='BS Neu'!D17 -> 4.9 | H100: ='BS Neu'!E17 -> 4.8 | I100: ='BS Neu'!F17 -> 3 | J100: ='BS Neu'!G17 -> 2 | K100: ='BS Neu'!H17 -> 3 | L100: ='BS Neu'!I17 -> 20 | M100: ='BS Neu'!J17 -> 20 | N100: ='BS Neu'!K17 -> 20 | ... Q100: ='BS Neu'!N17 -> 20
B101: Other Non-Current Liabilities | G101: ='BS Neu'!D44 -> 24.2 | H101: ='BS Neu'!E44 -> 25.1 | I101: ='BS Neu'!F44 -> 22 | J101: ='BS Neu'!G44 -> 25 | K101: ='BS Neu'!H44 -> 24 | L101: ='BS Neu'!I44 -> 59 | M101: ='BS Neu'!J44 -> 45.673907 | N101: ='BS Neu'!K44 -> 49.994134 | ... Q101: ='BS Neu'!N44 -> 89.102537
B102: Other Current Assets | G102: ='BS Neu'!D25 -> 58.1 | H102: ='BS Neu'!E25 -> 98.6 | I102: ='BS Neu'!F25 -> 177 | J102: ='BS Neu'!G25 -> 163 | K102: ='BS Neu'!H25 -> 150 | L102: ='BS Neu'!I25 -> 143 | M102: ='BS Neu'!J25 -> 301.38087 | N102: ='BS Neu'!K25 -> 315.37399 | ... Q102: ='BS Neu'!N25 -> 547.88974
B103: Other current liabilities | G103: ='BS Neu'!D53 -> 67.1 | H103: ='BS Neu'!E53 -> 86.9 | I103: ='BS Neu'!F53 -> 94 | J103: ='BS Neu'!G53 -> 101 | K103: ='BS Neu'!H53 -> 136 | L103: ='BS Neu'!I53 -> 151 | M103: ='BS Neu'!J53 -> 176.4 | N103: ='BS Neu'!K53 -> 181.95325 | ... Q103: ='BS Neu'!N53 -> 311.52072
B104: Total | G104: =G100+G102-G101-G103 -> -28.3 | H104: =H100+H102-H101-H103 -> -8.6 | I104: =I100+I102-I101-I103 -> 64 | J104: =J100+J102-J101-J103 -> 39 | K104: =K100+K102-K101-K103 -> -7 | L104: =L100+L102-L101-L103 -> -47 | M104: =M100+M102-M101-M103 -> 99.306968 | N104: =N100+N102-N101-N103 -> 103.42661 | ... Q104: =Q100+Q102-Q101-Q103 -> 167.26649
B105: Change | H105: =G104-H104 -> -19.7 | I105: =H104-I104 -> -72.6 | J105: =I104-J104 -> 25 | K105: =J104-K104 -> 46 | L105: =K104-L104 -> 40 | M105: =L104-M104 -> -146.30697 | N105: =M104-N104 -> -4.1196379 | O105: =N104-O104 -> -18.479335 | ... Q105: =P104-Q104 -> -22.934007
B108: Stock | L108: L | M108: M
B109: Current Provisions: | G109: ='BS Neu'!D52 -> 185.1 | H109: ='BS Neu'!E52 -> 193.6 | I109: ='BS Neu'!F52 -> 188 | J109: ='BS Neu'!G52 -> 181 | K109: ='BS Neu'!H52 -> 221 | L109: ='BS Neu'!I52 -> 257 | M109: ='BS Neu'!J52 -> 252 | N109: ='BS Neu'!K52 -> 263.70036 | ... Q109: ='BS Neu'!N52 -> 458.1187
B110: Non-current Provisions | G110: ='BS Neu'!D43 -> 413.6 | H110: ='BS Neu'!E43 -> 482.6 | I110: ='BS Neu'!F43 -> 497 | J110: ='BS Neu'!G43 -> 282 | K110: ='BS Neu'!H43 -> 357 | L110: ='BS Neu'!I43 -> 418 | M110: ='BS Neu'!J43 -> 588 | N110: ='BS Neu'!K43 -> 615.30084 | ... Q110: ='BS Neu'!N43 -> 1068.9436
B111: Provisions | G111: ='BS Neu'!D43+'BS Neu'!D52 -> 598.7 | H111: ='BS Neu'!E43+'BS Neu'!E52 -> 676.2 | I111: ='BS Neu'!F43+'BS Neu'!F52 -> 685 | J111: ='BS Neu'!G43+'BS Neu'!G52 -> 463 | K111: ='BS Neu'!H43+'BS Neu'!H52 -> 578 | L111: ='BS Neu'!I43+'BS Neu'!I52 -> 675 | M111: ='BS Neu'!J43+'BS Neu'!J52 -> 840 | N111: ='BS Neu'!K43+'BS Neu'!K52 -> 879.0012 | ... Q111: ='BS Neu'!N43+'BS Neu'!N52 -> 1527.0623 | R111: (+)
B112: Inventories | G112: ='BS Neu'!D22 -> 411.1 | H112: ='BS Neu'!E22 -> 403.7 | I112: ='BS Neu'!F22 -> 444 | J112: ='BS Neu'!G22 -> 516 | K112: ='BS Neu'!H22 -> 625 | L112: ='BS Neu'!I22 -> 719 | M112: ='BS Neu'!J22 -> 751.78082 | N112: ='BS Neu'!K22 -> 775.44763 | ... Q112: ='BS Neu'!N22 -> 1327.6378 | R112: (-)
B113: Contract Assets | G113: ='BS Neu'!D24 -> 165.9 | H113: ='BS Neu'!E24 -> 204.4 | I113: ='BS Neu'!F24 -> 170 | J113: ='BS Neu'!G24 -> 182 | K113: ='BS Neu'!H24 -> 196 | L113: ='BS Neu'!I24 -> 385 | M113: ='BS Neu'!J24 -> 308 | N113: ='BS Neu'!K24 -> 322.30044 | ... Q113: ='BS Neu'!N24 -> 559.92286 | R113: (-)
B114: Contract Liabilities | G114: ='BS Neu'!D51 -> 317.1 | H114: ='BS Neu'!E51 -> 416.8 | I114: ='BS Neu'!F51 -> 500 | J114: ='BS Neu'!G51 -> 488 | K114: ='BS Neu'!H51 -> 578 | L114: ='BS Neu'!I51 -> 776 | M114: ='BS Neu'!J51 -> 868 | N114: ='BS Neu'!K51 -> 908.30124 | ... Q114: ='BS Neu'!N51 -> 1577.9644 | R114: (+)
B115: Trade receivables | G115: ='BS Neu'!D23 -> 290.8 | H115: ='BS Neu'!E23 -> 282 | I115: ='BS Neu'!F23 -> 309 | J115: ='BS Neu'!G23 -> 323 | K115: ='BS Neu'!H23 -> 382 | L115: ='BS Neu'!I23 -> 426 | M115: ='BS Neu'!J23 -> 421.91781 | N115: ='BS Neu'!K23 -> 441.50745 | ... Q115: ='BS Neu'!N23 -> 767.01761 | R115: (-)
B116: Trade payables | G116: ='BS Neu'!D50 -> 168.8 | H116: ='BS Neu'!E50 -> 164 | I116: ='BS Neu'!F50 -> 269 | J116: ='BS Neu'!G50 -> 379 | K116: ='BS Neu'!H50 -> 457 | L116: ='BS Neu'!I50 -> 546 | M116: ='BS Neu'!J50 -> 483.28767 | N116: ='BS Neu'!K50 -> 498.50205 | ... Q116: ='BS Neu'!N50 -> 853.48142 | R116: (+)
B117: Other Current Assets | G117: ='BS Neu'!D25 -> 58.1 | H117: ='BS Neu'!E25 -> 98.6 | I117: ='BS Neu'!F25 -> 177 | J117: ='BS Neu'!G25 -> 163 | K117: ='BS Neu'!H25 -> 150 | L117: ='BS Neu'!I25 -> 143 | M117: ='BS Neu'!J25 -> 301.38087 | N117: ='BS Neu'!K25 -> 315.37399 | ... Q117: ='BS Neu'!N25 -> 547.88974 | R117: (-)
B118: Other Current Liabilties | G118: ='BS Neu'!D53 -> 67.1 | H118: ='BS Neu'!E53 -> 86.9 | I118: ='BS Neu'!F53 -> 94 | J118: ='BS Neu'!G53 -> 101 | K118: ='BS Neu'!H53 -> 136 | L118: ='BS Neu'!I53 -> 151 | M118: ='BS Neu'!J53 -> 176.4 | N118: ='BS Neu'!K53 -> 181.95325 | ... Q118: ='BS Neu'!N53 -> 311.52072 | R118: (+)
...

Sheet Debt & Cash
A1: =_xlfn.CONCAT(Inputs!C7, " - ", "Debt & Cash", " - ", "in ", Inputs!C9, " ", Inputs!C10) -> HAG - Debt & Cash - in Euro millions
S2: Version | U2: Scenario
Q3: Debt Policy | S3: 1
B4: Financial year end | E4: =EDATE(Inputs!$C$8, E5*12) -> 43830 | F4: =EDATE(Inputs!$C$8, F5*12) -> 44196 | G4: =EDATE(Inputs!$C$8, G5*12) -> 44561 | H4: =EDATE(Inputs!$C$8, H5*12) -> 44926 | I4: =EDATE(Inputs!$C$8, I5*12) -> 45291 | J4: =EDATE(Inputs!$C$8, J5*12) -> 45657 | K4: =EDATE(Inputs!$C$8, K5*12) -> 46022 | L4: =EDATE(Inputs!$C$8, L5*12) -> 46387 | ... O4: =EDATE(Inputs!$C$8, O5*12) -> 47483 | Q4: Dividend Policy | S4: =Inputs!AA8 -> 1 | U4: =Inputs!AC8 -> 2
B5: Time-line counter | E5: -5 | F5: -4 | G5: -3 | H5: -2 | I5: -1 | J5: 0 | K5: 1 | L5: 2 | M5: 3 | N5: 4 | O5: 5 | Q5: Intrest Income Scenario | S5: =Inputs!AA9 -> 2
B6: Currency and units | E6: =_xlfn.CONCAT(Inputs!$C$9, " ", Inputs!$C$10) -> Euro millions | F6: =_xlfn.CONCAT(Inputs!$C$9, " ", Inputs!$C$10) -> Euro millions | G6: =_xlfn.CONCAT(Inputs!$C$9, " ", Inputs!$C$10) -> Euro millions | H6: =_xlfn.CONCAT(Inputs!$C$9, " ", Inputs!$C$10) -> Euro millions | I6: =_xlfn.CONCAT(Inputs!$C$9, " ", Inputs!$C$10) -> Euro millions | J6: =_xlfn.CONCAT(Inputs!$C$9, " ", Inputs!$C$10) -> Euro millions | K6: =_xlfn.CONCAT(Inputs!$C$9, " ", Inputs!$C$10) -> Euro millions | L6: =_xlfn.CONCAT(Inputs!$C$9, " ", Inputs!$C$10) -> Euro millions | ... O6: =_xlfn.CONCAT(Inputs!$C$9, " ", Inputs!$C$10) -> Euro millions | Q6: Intrest Expense Scenario | S6: =Inputs!AA10 -> 2
B7: Time-Stamp | E7: =IF(E5<=0, "Historical", "Forecasted") -> Historical | F7: =IF(F5<=0, "Historical", "Forecasted") -> Historical | G7: =IF(G5<=0, "Historical", "Forecasted") -> Historical | H7: =IF(H5<=0, "Historical", "Forecasted") -> Historical | I7: =IF(I5<=0, "Historical", "Forecasted") -> Historical | J7: =IF(J5<=0, "Historical", "Forecasted") -> Historical | K7: =IF(K5<=0, "Historical", "Forecasted") -> Forecasted | L7: =IF(L5<=0, "Historical", "Forecasted") -> Forecasted | ... O7: =IF(O5<=0, "Historical", "Forecasted") -> Forecasted | Q7: Main Intrest Rate | S7: =Inputs!AA11 -> 4
B9: Net Income | E9: ='IS Neu'!D24 -> 8.2 | F9: ='IS Neu'!E24 -> -64.5 | G9: ='IS Neu'!F24 -> 63 | H9: ='IS Neu'!G24 -> 81 | I9: ='IS Neu'!H24 -> 60 | J9: ='IS Neu'!I24 -> 104 | K9: ='IS Neu'!J24 -> 319.39086 | L9: ='IS Neu'!K24 -> 345.59666 | ... O9: ='IS Neu'!N24 -> 671.83982 | Q9: Target Levrage ratio | S9: =Inputs!AA13 -> 2
Q10: Deffered Tax Liabilities | S10: =Inputs!AA14 -> 1
B11: Debt | Q11: Provisions % of Revenue | S11: =Inputs!AA15 -> 0.3
B12: Beginning Debt (includes financing and leases) | F12: ='BS Neu'!E42+'BS Neu'!E49 -> 1216.4 | G12: ='BS Neu'!F42+'BS Neu'!F49 -> 953 | H12: ='BS Neu'!G42+'BS Neu'!G49 -> 793 | I12: ='BS Neu'!H42+'BS Neu'!H49 -> 862 | J12: ='BS Neu'!I42+'BS Neu'!I49 -> 1449 | K12: =J17 -> 1449 | L12: =K17 -> 1503.6718 | M12: =L17 -> 1553.4422 | N12: =M17 -> 1638.6976 | O12: =N17 -> 1742.9252
B13: (+) New Financing | F13: 97 | G13: 0 | H13: 0 | I13: 13 | K13: =CHOOSE($S$3, K85,K157) -> 0 | L13: =CHOOSE($S$3, L85,L157) -> 0 | M13: =CHOOSE($S$3, M85,M157) -> 990 | N13: =CHOOSE($S$3, N85,N157) -> 0 | O13: =CHOOSE($S$3, O85,O157) -> 0 | Q13: Interest Expense
B14: (+) New Leases | K14: =K87 -> 110.88 | L14: =L87 -> 116.02816 | M14: =M87 -> 145.01748 | N14: =N87 -> 167.77644 | O14: =O87 -> 201.57223 | Q14: This is forecasted by taking the actual loans HAG has and assuming interest payment until principal is repayed.
B15: (-) Finance Repayments | K15: =-K83 -> -0.1 | L15: =-L83 -> -8.4 | M15: =-M83 -> -990 | N15: =-N83 -> 0 | O15: =-O83 -> 0 | Q15: It also assumes that newly issued debt will have similar conditions to the current loans, meaning Euribor + 1,75%
B16: (-) lease Repayments | K16: =K88*-1 -> -56.108206 | L16: =L88*-1 -> -57.857794 | M16: =M88*-1 -> -59.762009 | N16: =N88*-1 -> -63.548835 | O16: =O88*-1 -> -68.548995
B17: Ending debt balance | F17: =SUM(F12:F16) -> 1313.4 | G17: =SUM(G12:G16) -> 953 | H17: =SUM(H12:H16) -> 793 | I17: =SUM(I12:I16) -> 875 | J17: =SUM(J12:J16) -> 1449 | K17: =SUM(K12:K16) -> 1503.6718 | L17: =SUM(L12:L16) -> 1553.4422 | M17: =SUM(M12:M16) -> 1638.6976 | ... O17: =SUM(O12:O16) -> 1875.9485 | Q17: Current Rating B2 | S17: Hensold Corporate Spead | V17: 0.028
Q18: (Premium over risk free bonds, in this case German BUNDS) | V18: As of October 2025
B19: Dividends | C19: No. of Shares | D19: 115
B20: Net Income (attrib. to shareholder) | F20: ='IS Neu'!E24 -> -64.5 | G20: ='IS Neu'!F24 -> 63 | H20: ='IS Neu'!G24 -> 81 | I20: ='IS Neu'!H24 -> 60 | J20: ='IS Neu'!I24 -> 104 | K20: ='IS Neu'!J24 -> 319.39086 | L20: ='IS Neu'!K24 -> 345.59666 | M20: ='IS Neu'!L24 -> 464.84432 | ... O20: ='IS Neu'!N24 -> 671.83982
B21: Dividend per Share | F21: 0 | G21: 0.13 | H21: 0.25 | I21: 0.3 | J21: 0.4 | K21: =K25/$D$19 -> 1.1942441 | L21: =L25/$D$19 -> 1.3523347 | M21: =M25/$D$19 -> 1.8997985 | N21: =N25/$D$19 -> 2.3692941 | O21: =O25/$D$19 -> 2.9794636
B22: Payout Ratio | F22: =F25/F20 -> 0 | G22: =G25/G20 -> 0.22222222 | H22: =H25/H20 -> 0.32098765 | I22: =I25/I20 -> 0.53333333 | J22: =J25/J20 -> 0.44230769 | K22: =K91 -> 0.43 | L22: =L91 -> 0.45 | M22: =M91 -> 0.47 | N22: =N91 -> 0.49 | O22: =O91 -> 0.51
B23: EPS Dividend | K23: =K96*115 -> 48.3 | L23: =L96*115 -> 50.715 | M23: =M96*115 -> 53.25075 | N23: =N96*115 -> 55.913288 | O23: =O96*115 -> 58.708952
B24: Payout Ratio Dividend | K24: =K22*K20 -> 137.33807 | L24: =L22*L20 -> 155.5185 | M24: =M22*M20 -> 218.47683 | N24: =N22*N20 -> 272.46882 | O24: =O22*O20 -> 342.63831 | Q24: Lease payments
B25: Total Dividend payed | F25: 0 | G25: 14 | H25: 26 | I25: 32 | J25: 46 | K25: =IF($S$4=1, K24, K23) -> 137.33807 | L25: =IF($S$4=1, L24, L23) -> 155.5185 | M25: =IF($S$4=1, M24, M23) -> 218.47683 | N25: =IF($S$4=1, N24, N23) -> 272.46882 | O25: =IF($S$4=1, O24, O23) -> 342.63831 | Q25: Repayments of lease principal roughly equal depreciation of ROU assets
Q26: Lease Intrest rate hovered in the past around 5%, therefore for forcasting this rate, Hensoldt Corporate Spread + Main Intrest rate scenario has been used
B27: Intrest Expense | D27: (detailled forecast with actual loans) | Q27: Lease Amount has been set to Right of Use Net assets, since it corresponds to the additions/detractions directly
B28: Debt | K28: =SUM(K29:K35) -> 60.20552 | L28: =SUM(L29:L35) -> 60.20388 | M28: =SUM(M29:M35) -> 60.1575 | N28: =SUM(N29:N35) -> 42.867 | O28: =SUM(O29:O35) -> 42.867
B29: Term-Loan (620) | J29: 620 | K29: =$J$29*0.0566 -> 35.092 | L29: =$J$29*0.0566 -> 35.092 | M29: =$J$29*0.0566 -> 35.092 | N29: 0 | O29: 0
B30: Term-Facility(450) | J30: 450 | K30: =$J$30*0.0545 -> 24.525 | L30: =$J$30*0.0545 -> 24.525 | M30: =$J$30*0.0545 -> 24.525 | N30: 0 | O30: 0 | Q30: Interest Income
B31: South Africa Loan (4.6) | J31: 4.6 | K31: =$J$31*0.1175 -> 0.5405 | L31: =$J$31*0.1175 -> 0.5405 | M31: =$J$31*0.1175 -> 0.5405 | N31: 0 | O31: 0 | Q31: This assumes (as reported) that Interest Income is derived from 3 pillars. Interest on Cash, Interest on Plan Assets (Pensions, in this case that are overfunded) and
B32: French (0,1) | J32: 0.1 | K32: =J32*0.0164 -> 0.00164 | L32: 0 | M32: 0 | N32: 0 | O32: 0 | Q32: Interest rate Swaps (which are there to hedge the floating rate debt into a fixed debt)
B33: Fench (1) | J33: 1 | K33: =$J$33*0.0209 -> 0.0209 | L33: =$J$33*0.0209 -> 0.0209 | M33: 0 | N33: 0 | O33: 0 | Q33: The main interest rate used for a cash forecast in this case is the same as otherwise (Euribor or the other chosen scenario)
B34: French (2.8) | J34: 2.8 | K34: =$J$34*0.0091 -> 0.02548 | L34: =$J$34*0.0091 -> 0.02548 | M34: 0 | N34: 0 | O34: 0 | Q34: Plan Assets are forecast as constant, since the pension obligations don't necessariyl increase disproportionatly to the provisions that are made
B35: New Debt (990) | J35: 990 | N35: =$J$35*N43 -> 42.867 | O35: =$J$35*O43 -> 42.867
B36: Intrest rate used | D36: =Inputs!AA17 -> 0.0175 | K36: =K70+$D$36 -> 0.0375 | L36: =L70+$D$36 -> 0.035 | M36: =M70+$D$36 -> 0.0325 | N36: =N70+$D$36 -> 0.0325 | O36: =O70+$D$36 -> 0.0325
B37: Lease | E37: =SUM(E38:E39) -> 160.5 | F37: =SUM(F38:F39) -> 154 | G37: =SUM(G38:G39) -> 155 | H37: =SUM(H38:H39) -> 158 | I37: =SUM(I38:I39) -> 211 | J37: =SUM(J38:J39) -> 281 | L37: ='FA-Forecast (updated)'!N49 -> 361.94216 | M37: ='FA-Forecast (updated)'!O49 -> 447.19763 | N37: ='FA-Forecast (updated)'!P49 -> 551.42524 | O37: ='FA-Forecast (updated)'!Q49 -> 684.44847 | Q37: Dividends:
B38: Current Lease | E38: ='BS Neu'!D107 -> 13 | F38: ='BS Neu'!E107 -> 13.7 | G38: ='BS Neu'!F107 -> 16 | H38: ='BS Neu'!G107 -> 18 | I38: ='BS Neu'!H107 -> 20 | J38: ='BS Neu'!I107 -> 25 | Q38: Amount of Shares is kept constant | U38: Company Dividend Policy: payout ratio between 30-40% of Net Income
B39: Non-Current Lease | E39: ='BS Neu'!D98 -> 147.5 | F39: ='BS Neu'!E98 -> 140.3 | G39: ='BS Neu'!F98 -> 139 | H39: ='BS Neu'!G98 -> 140 | I39: ='BS Neu'!H98 -> 191 | J39: ='BS Neu'!I98 -> 256 | Q39: V1: constant payout ratio of Net Income
B40: Payment for lease Liabilities | E40: 10 | F40: 10 | G40: 10 | H40: 9 | I40: 11 | J40: 14 | Q40: Scenarios model diffrent payout ratios | T40: (1: Constant, 2: Growing, 3: decreasing Ratio)
B41: % (assumed Intrest rate) | E41: =E40/E37 -> 0.062305296 | F41: =F40/F37 -> 0.064935065 | G41: =G40/G37 -> 0.064516129 | H41: =H40/H37 -> 0.056962025 | I41: =I40/I37 -> 0.052132701 | J41: =J40/J37 -> 0.049822064
B42: Lease Expense | K42: =K37*K43 -> 0 | L42: =L37*L43 -> 16.576951 | M42: =M37*M43 -> 19.363658 | N42: =N37*N43 -> 23.876713 | O42: =O37*O43 -> 29.636619 | Q42: V2: Constant Dividend Growth | T42: Scenarios model a cent per share growth pathway
B43: Intrest rate used for lease intrest | D43: =Inputs!AA16 -> 0.0283 | K43: =K70+$D$43 -> 0.0483 | L43: =L70+$D$43 -> 0.0458 | M43: =M70+$D$43 -> 0.0433 | N43: =N70+$D$43 -> 0.0433 | O43: =O70+$D$43 -> 0.0433
B44: Total Expense | K44: =(K42+K28)*-1 -> -60.20552 | L44: =(L42+L28)*-1 -> -76.780831 | M44: =(M42+M28)*-1 -> -79.521158 | N44: =(N42+N28)*-1 -> -66.743713 | O44: =(O42+O28)*-1 -> -72.503619 | Q44: Debt New:
Q45: Repayments are made based on the due dates of credit as per annual report
B46: Intrest Income | Q46: If cash-flow is not enough to cover the repayment, then new issuance is assumed (otherwise the company would be debt free anyway)
B47: Interest Income from Cash | K47: =J53*K50 -> 14.66 | L47: =K53*L50 -> 16.383815 | M47: =L53*M50 -> 17.048631 | N47: =M53*N50 -> 22.291034 | O47: =N53*O50 -> 27.379228 | Q47: So repayments can be modeled as: all the existing debt with due dates (but only the principal, intrest is calculated seperatly)
B48: Interest Income from Plan Assets | K48: 10 | L48: 10 | M48: 10 | N48: 10 | O48: 10 | Q48: (+) any additional debt that must be issued, regarding their assumed due date (for this, historical debt conditions can be an indicator)
B49: Interest Income from Currency Swaps | K49: =IF($S$7=1,4,IF($S$7=2,3,IF($S$7=3,4,IF($S$7=4,5)))) -> 5 | L49: =IF($S$7=1,4,IF($S$7=2,3,IF($S$7=3,4,IF($S$7=4,5)))) -> 5 | M49: =IF($S$7=1,4,IF($S$7=2,3,IF($S$7=3,4,IF($S$7=4,5)))) -> 5 | N49: =IF($S$7=1,4,IF($S$7=2,3,IF($S$7=3,4,IF($S$7=4,5)))) -> 5 | O49: =IF($S$7=1,4,IF($S$7=2,3,IF($S$7=3,4,IF($S$7=4,5)))) -> 5 | Q49: Repayments, that can be made through cash-flow (smaller debt items) will be made this way, because they also usually have higher intrest rates and
B50: Main Interest Rate Used | K50: =K70 -> 0.02 | L50: =L70 -> 0.0175 | M50: =M70 -> 0.015 | N50: =N70 -> 0.015 | O50: =O70 -> 0.015 | Q50: are therefore a priority to be repaied
B51: Total | K51: =SUM(K47:K49) -> 29.66 | L51: =SUM(L47:L49) -> 31.383815 | M51: =SUM(M47:M49) -> 32.048631 | N51: =SUM(N47:N49) -> 37.291034 | O51: =SUM(O47:O49) -> 42.379228
Q52: Debt Issuance:
B53: Cash | E53: ='BS Neu'!D26 -> 137.4 | F53: ='BS Neu'!E26 -> 645.5 | G53: ='BS Neu'!F26 -> 529 | H53: ='BS Neu'!G26 -> 460 | I53: ='BS Neu'!H26 -> 802 | J53: ='BS Neu'!I26 -> 733 | K53: ='BS Neu'!J26 -> 936.21801 | L53: ='BS Neu'!K26 -> 1136.5754 | ... O53: ='BS Neu'!N26 -> 2223.6018 | Q53: In 2027, there is a maturity wall with almost 1 bn of debt needing to be refinanced
Q54: since cash-flow can not cover this, a new issuance in the exact amount is assumed with the following conditions
B55: Net Intrest Income/Expense | K55: =K44+K51 -> -30.54552 | L55: =L44+L51 -> -45.397016 | M55: =M44+M51 -> -47.472527 | N55: =N44+N51 -> -29.452679 | O55: =O44+O51 -> -30.124391 | Q55: Cupon: 3M Euroibor +1,75% Intrest rate, Due date: 2032 (5 year loan agreement).
Q56: Since this loan is cheaper than the revolving credit facility, it is assumed the facility will be unused just as the previous one and only exists as a safety provision.
Q57: Cash management (and cash accrural allow for equity financing in a sufficient manner)
B58: Ending Current Debt Financing | K58: =K13+K15 -> -0.1 | L58: =L13+L15 -> -8.4 | M58: =M13+M15 -> 0 | N58: =N13+N15 -> 0 | O58: =O13+O15 -> 0 | Q58: Version 1: Just the refinancing of the two large loans under then present conditions
B59: Ending Current Debt Lease | K59: =K16 -> -56.108206 | L59: =L16 -> -57.857794 | M59: =M16 -> -59.762009 | N59: =N16 -> -63.548835 | O59: =O16 -> -68.548995
B60: Ending Current Debt | K60: =SUM(K58)+'BS Neu'!I49 -> 120.9 | L60: =SUM(L58)+'BS Neu'!J49 -> 112.5 | M60: =SUM(M58)+'BS Neu'!K49 -> 112.5 | N60: =SUM(N58)+'BS Neu'!L49 -> 112.5 | O60: =SUM(O58)+'BS Neu'!M49 -> 112.5
B61: Ending Non-Current Debt | K61: =K17-K60+K59 -> 1326.6636 | L61: =L17-L60+L59 -> 1383.0844 | M61: =M17-M60+M59 -> 1466.4356 | N61: =N17-N60+N59 -> 1566.8764 | O61: =O17-O60+O59 -> 1694.8995
B63: Net Change in debt | E63: =F13+F15 -> 97 | F63: =G13+G15 -> 0 | G63: =H13+H15 -> 0 | H63: =I13+I15 -> 13 | I63: =J13+J15 -> 0 | J63: =K13+K15 -> -0.1 | K63: =SUM(K13:K16) -> 54.671794 | L63: =SUM(L13:L16) -> 49.770364 | M63: =SUM(M13:M16) -> 85.255476 | N63: =SUM(N13:N16) -> 104.22761 | O63: =SUM(O13:O16) -> 133.02323
B65: Scenarios | C65: Intrest rates development
B66: Yield Curve (Euribor) | K66: 0.0191 | L66: 0.02042 | M66: 0.02162 | N66: 0.02315 | O66: 0.02475
B67: Pessimistic | K67: 0.0225 | L67: 0.025 | M67: 0.0275 | N67: 0.03 | O67: 0.03
B68: Neutral | K68: 0.02 | L68: 0.02 | M68: 0.02 | N68: 0.02 | O68: 0.02
B69: Optimistic | K69: 0.02 | L69: 0.0175 | M69: 0.015 | N69: 0.015 | O69: 0.015
B70: Maint intrest rate | K70: =CHOOSE($S$7,K66,K67,K68,K69) -> 0.02 | L70: =CHOOSE($S$7,L66,L67,L68,L69) -> 0.0175 | M70: =CHOOSE($S$7,M66,M67,M68,M69) -> 0.015 | N70: =CHOOSE($S$7,N66,N67,N68,N69) -> 0.015 | O70: =CHOOSE($S$7,O66,O67,O68,O69) -> 0.015
B72: Debt Scheduel | D72: (separated for Leases and Long term debt)
B74: Long term | C74: Mandatory repayments
B75: Hensoldt AG | K75: 0 | L75: 0 | M75: 990 | N75: 0 | O75: 0
B76: Hensoldt France | K76: 0.1 | L76: 3.8 | M76: 0 | N76: 0 | O76: 0
B77: Hensoldt South Africa | K77: 0 | L77: 4.6 | M77: 0 | N77: 0 | O77: 0
B78: Total | K78: =SUM(K75:K77) -> 0.1 | L78: =SUM(L75:L77) -> 8.4 | M78: =SUM(M75:M77) -> 990 | N78: =SUM(N75:N77) -> 0 | O78: =SUM(O75:O77) -> 0
B79: Long term | C79: Cash Accrural | D79: (Optional Repayments/early repayments)
B83: Total Repayments | K83: =K78 -> 0.1 | L83: =L78 -> 8.4 | M83: =M78 -> 990 | N83: =N78 -> 0 | O83: =O78 -> 0
B84: Long term | C84: New debt Issuance
B85: Hensoldt AG | K85: 0 | L85: 0 | M85: 990 | N85: 0 | O85: 0
B86: Leases | C86: Mandatory Repayments
B87: Additions (Capex related from FA-Scheduel) | K87: ='FA-Forecast (updated)'!M45 -> 110.88 | L87: ='FA-Forecast (updated)'!N45 -> 116.02816 | M87: ='FA-Forecast (updated)'!O45 -> 145.01748 | N87: ='FA-Forecast (updated)'!P45 -> 167.77644 | O87: ='FA-Forecast (updated)'!Q45 -> 201.57223
B88: Repayments (set as Depreciation for leases) | K88: ='FA-Forecast (updated)'!M47 -> 56.108206 | L88: ='FA-Forecast (updated)'!N47 -> 57.857794 | M88: ='FA-Forecast (updated)'!O47 -> 59.762009 | N88: ='FA-Forecast (updated)'!P47 -> 63.548835 | O88: ='FA-Forecast (updated)'!Q47 -> 68.548995
B90: Dividend
B91: Version 1: Payout Dividend Forecast | K91: =CHOOSE($U$4,K92, K93, K94) -> 0.43 | L91: =CHOOSE($U$4,L92, L93, L94) -> 0.45 | M91: =CHOOSE($U$4,M92, M93, M94) -> 0.47 | N91: =CHOOSE($U$4,N92, N93, N94) -> 0.49 | O91: =CHOOSE($U$4,O92, O93, O94) -> 0.51
B92: Constant Ratio | K92: 0.4 | L92: 0.4 | M92: 0.4 | N92: 0.4 | O92: 0.4
B93: Growing Ratio | K93: 0.43 | L93: 0.45 | M93: 0.47 | N93: 0.49 | O93: 0.51
B94: Reduction up to a minimum level | K94: 0.4 | L94: 0.38 | M94: 0.36 | N94: 0.34 | O94: 0.32
B96: Version 2: | K96: =CHOOSE($U$4,K97,K98,K99) -> 0.42 | L96: =CHOOSE($U$4,L97,L98,L99) -> 0.441 | M96: =CHOOSE($U$4,M97,M98,M99) -> 0.46305 | N96: =CHOOSE($U$4,N97,N98,N99) -> 0.4862025 | O96: =CHOOSE($U$4,O97,O98,O99) -> 0.51051263 | Q96: Tax Considerations
B97: Constant | K97: 0.45 | L97: 0.45 | M97: 0.45 | N97: 0.45 | O97: 0.45 | Q97: Since there is no clear guidance by the company itesl on how deferred taxes are going to develop other than that they will grow in clockstep with future taxable income
B98: Slow Growth | D98: 0.05 | K98: =J21*1.05 -> 0.42 | L98: =K98*1.05 -> 0.441 | M98: =L98*1.05 -> 0.46305 | N98: =M98*1.05 -> 0.4862025 | O98: =N98*1.05 -> 0.51051263 | Q98: ie. EBT, this means that Tax liablities (at leas current ones) are difficult to foercast.
B99: High Growth | D99: 0.1 | K99: =J21*1.1 -> 0.44 | L99: =K99*1.1 -> 0.484 | M99: =L99*1.1 -> 0.5324 | N99: =M99*1.1 -> 0.58564 | O99: =N99*1.1 -> 0.644204 | Q99: It is therefore assumed, that current deffered taxliabilities are comprised of 30% of the Income tax that is expected to be payed in that year
B101: Deferred Taxes (Current) | Q101: There is no clear indication for weather deferred current tax liabilities follow a specific trend
Q102: Therefore, an industry average of 30% of the income tax burden is taken as a proxy
B103: Deferred Tax liabilities | E103: ='BS Neu'!D111 -> 0.1 | F103: ='BS Neu'!E111 -> 7.6 | G103: ='BS Neu'!F111 -> 11 | H103: ='BS Neu'!G111 -> 19 | I103: ='BS Neu'!H111 -> 39 | J103: ='BS Neu'!I111 -> 33 | K103: =K104*$D$105*-1 -> 37.819085 | L103: =L104*$D$105*-1 -> 40.922114 | M103: =M104*$D$105*-1 -> 55.042235 | N103: =N104*$D$105*-1 -> 65.842947 | O103: =O104*$D$105*-1 -> 79.552581 | Q103: Since it would create a circular refrence, making income tax revievables a share of current assets, revenue is substitutet (although a more blunt tool)
B104: Income tax | E104: ='IS Neu'!D23 -> -27.4 | F104: ='IS Neu'!E23 -> 10.7 | G104: ='IS Neu'!F23 -> -22 | H104: ='IS Neu'!G23 -> -49 | I104: ='IS Neu'!H23 -> -36 | J104: ='IS Neu'!I23 -> -12 | K104: ='IS Neu'!J23 -> -126.06362 | L104: ='IS Neu'!K23 -> -136.40705 | ... O104: ='IS Neu'!N23 -> -265.17527
B105: as a Share of Income tax | D105: 0.3 | E105: =E103/E104 -> -0.003649635 | F105: =F103/F104 -> 0.71028037 | G105: =G103/G104 -> -0.5 | H105: =H103/H104 -> -0.3877551 | I105: =I103/I104 -> -1.0833333 | J105: =J103/J104 -> -2.75 | Q105: For Non-Current tax liabilities, it is advisable to use the share of net tax liabilities (meaning deffered liabilities - deferred assets) of total non-current assets
B106: Revenue | E106: ='IS Neu'!D12 -> 1114.2 | F106: ='IS Neu'!E12 -> 1206.9 | G106: ='IS Neu'!F12 -> 1474 | H106: ='IS Neu'!G12 -> 1707 | I106: ='IS Neu'!H12 -> 1847 | J106: ='IS Neu'!I12 -> 2240 | K106: ='IS Neu'!J12 -> 2800 | L106: ='IS Neu'!K12 -> 2930.004 | ... O106: ='IS Neu'!N12 -> 5090.2078 | Q106: this is a solid indication of how large the estimated future tax burden will be and avoids circular refrences
B107: Income Tax Recievables (Current Tax Assets) | E107: ='BS Neu'!D82 -> 3.2 | F107: ='BS Neu'!E82 -> 1.6 | G107: ='BS Neu'!F82 -> 2 | H107: ='BS Neu'!G82 -> 10 | I107: ='BS Neu'!H82 -> 15 | J107: ='BS Neu'!I82 -> 20 | K107: =K106*K108 -> 21.380875 | L107: =L106*L108 -> 22.373589 | M107: =M106*M108 -> 27.96357 | N107: =N106*N108 -> 32.352156 | O107: =O106*O108 -> 38.868963
E108: =E107/E106 -> 0.0028720158 | F108: =F107/F106 -> 0.0013257105 | G108: =G107/G106 -> 0.0013568521 | H108: =H107/H106 -> 0.0058582308 | I108: =I107/I106 -> 0.0081212777 | J108: =J107/J106 -> 0.0089285714 | K108: =AVERAGE(H108:J108) -> 0.0076360267 | L108: =K108 -> 0.0076360267 | M108: =L108 -> 0.0076360267 | N108: =M108 -> 0.0076360267 | O108: =N108 -> 0.0076360267 | Q108: Deferred Tax Liabilities
Q109: This will be forecast in the net change in deferred tax as most of it arises due to the PPE-Capex.
B110: Deferred Taxes (Non-Current) | Q110: Important for the DCF is also the assumption that in the long run (terminal value), Capex = Depreciation,
B111: Total non-Current assets | E111: ='BS Neu'!D19 -> 1392.7 | F111: ='BS Neu'!E19 -> 1313.4 | G111: ='BS Neu'!F19 -> 1328 | H111: ='BS Neu'!G19 -> 1335 | I111: ='BS Neu'!H19 -> 1424 | J111: ='BS Neu'!I19 -> 2289 | K111: ='BS Neu'!J19 -> 2445.8179 | L111: ='BS Neu'!K19 -> 2524.5045 | ... O111: ='BS Neu'!N19 -> 3172.0437 | Q111: so it will trend towards 0 in all scenarios
...

Sheet DCF Valuation 
A1: =_xlfn.CONCAT(Inputs!C7, " - ", "DCF Model", " - ", "in ", Inputs!C9, " ", Inputs!C10) -> HAG - DCF Model - in Euro millions
B4: Financial year end | G4: =EDATE(Inputs!$C$8, G5*12) -> 43830 | H4: =EDATE(Inputs!$C$8, H5*12) -> 44196 | I4: =EDATE(Inputs!$C$8, I5*12) -> 44561 | J4: =EDATE(Inputs!$C$8, J5*12) -> 44926 | K4: =EDATE(Inputs!$C$8, K5*12) -> 45291 | L4: =EDATE(Inputs!$C$8, L5*12) -> 45657 | M4: =EDATE(Inputs!$C$8, M5*12) -> 46022 | N4: =EDATE(Inputs!$C$8, N5*12) -> 46387 | ... Q4: =EDATE(Inputs!$C$8, Q5*12) -> 47483 | R4: Final Year
B5: Time-line counter | G5: -5 | H5: -4 | I5: -3 | J5: -2 | K5: -1 | L5: 0 | M5: 1 | N5: 2 | O5: 3 | P5: 4 | Q5: 5
B6: Currency and units | G6: =_xlfn.CONCAT(Inputs!$C$9, " ", Inputs!$C$10) -> Euro millions | H6: =_xlfn.CONCAT(Inputs!$C$9, " ", Inputs!$C$10) -> Euro millions | I6: =_xlfn.CONCAT(Inputs!$C$9, " ", Inputs!$C$10) -> Euro millions | J6: =_xlfn.CONCAT(Inputs!$C$9, " ", Inputs!$C$10) -> Euro millions | K6: =_xlfn.CONCAT(Inputs!$C$9, " ", Inputs!$C$10) -> Euro millions | L6: =_xlfn.CONCAT(Inputs!$C$9, " ", Inputs!$C$10) -> Euro millions | M6: =_xlfn.CONCAT(Inputs!$C$9, " ", Inputs!$C$10) -> Euro millions | N6: =_xlfn.CONCAT(Inputs!$C$9, " ", Inputs!$C$10) -> Euro millions | ... Q6: =_xlfn.CONCAT(Inputs!$C$9, " ", Inputs!$C$10) -> Euro millions | T6: Assumptions:
B7: Time-Stamp | G7: =IF(G5<=0, "Historical", "Forecasted") -> Historical | H7: =IF(H5<=0, "Historical", "Forecasted") -> Historical | I7: =IF(I5<=0, "Historical", "Forecasted") -> Historical | J7: =IF(J5<=0, "Historical", "Forecasted") -> Historical | K7: =IF(K5<=0, "Historical", "Forecasted") -> Historical | L7: =IF(L5<=0, "Historical", "Forecasted") -> Historical | M7: =IF(M5<=0, "Historical", "Forecasted") -> Forecasted | N7: =IF(N5<=0, "Historical", "Forecasted") -> Forecasted | ... Q7: =IF(Q5<=0, "Historical", "Forecasted") -> Forecasted | T7: Company uses Terminal Growth rate of 1% in their own DCF Model
T8: Utilised Tax Rate is the same as the assumed (for Income tax purposes) 28,3%
B9: Exit Multiple | E9: 2
T10: Average Cost of debt is: Actual cost of debt + cost of lease / average debt balance (which includes leases)
B11: EBIT | G11: ='IS Neu'!D18 -> 62.1 | H11: ='IS Neu'!E18 -> 68.5 | I11: ='IS Neu'!F18 -> 126 | J11: ='IS Neu'!G18 -> 166 | K11: ='IS Neu'!H18 -> 167 | L11: ='IS Neu'!I18 -> 184 | M11: ='IS Neu'!J18 -> 476 | N11: ='IS Neu'!K18 -> 527.40072 | ... Q11: ='IS Neu'!N18 -> 967.13948
B12: (-) Effective Tax Rate | E12: 0.283 | G12: =('IS Neu'!D23*-1)/G11 -> 0.44122383 | H12: =('IS Neu'!E23*-1)/H11 -> -0.15620438 | I12: =('IS Neu'!F23*-1)/I11 -> 0.17460317 | J12: =('IS Neu'!G23*-1)/J11 -> 0.29518072 | K12: =('IS Neu'!H23*-1)/K11 -> 0.21556886 | L12: =('IS Neu'!I23*-1)/L11 -> 0.065217391 | M12: =$E$12 -> 0.283 | N12: =$E$12 -> 0.283 | O12: =$E$12 -> 0.283 | P12: =$E$12 -> 0.283 | Q12: =$E$12 -> 0.283 | T12: ß is derived from | V12: https://www.alphaspread.com/security/xetra/hag/discount-rate
B13: =NOPAT | M13: =M11*(1-$E$12) -> 341.292 | N13: =N11*(1-$E$12) -> 378.14632 | O13: =O11*(1-$E$12) -> 498.88212 | P13: =P11*(1-$E$12) -> 577.17638 | Q13: =Q11*(1-$E$12) -> 693.43901
B14: (+) Depreciation & Amortisation | M14: ='FA-Forecast (updated)'!M84 -> 263.0373 | N14: ='FA-Forecast (updated)'!N84 -> 270.98997 | O14: ='FA-Forecast (updated)'!O84 -> 279.6455 | P14: ='FA-Forecast (updated)'!P84 -> 296.85834 | Q14: ='FA-Forecast (updated)'!Q84 -> 319.58634 | T14: Risk Free Rate is current (29.10.2025) 10y Bunds rate at 2,628%
B15: (-) Change in Net Working Capital | M15: ='CF Neu '!M17 -> -44.391834 | N15: ='CF Neu '!N17 -> 28.520058 | O15: ='CF Neu '!O17 -> 154.90912 | P15: ='CF Neu '!P17 -> 120.53532 | Q15: ='CF Neu '!Q17 -> 178.98826
B16: (-) Capital Expenditure | M16: ='FA-Forecast (updated)'!M65*-1 -> -336 | N16: ='FA-Forecast (updated)'!N65*-1 -> -351.60048 | O16: ='FA-Forecast (updated)'!O65*-1 -> -439.44692 | P16: ='FA-Forecast (updated)'!P65*-1 -> -508.41346 | Q16: ='FA-Forecast (updated)'!Q65*-1 -> -610.82494
B17: Unlevered Free Cashflow | M17: =SUM(M13:M16) -> 223.93747 | N17: =SUM(N13:N16) -> 326.05587 | O17: =SUM(O13:O16) -> 493.98981 | P17: =SUM(P13:P16) -> 486.15658 | Q17: =SUM(Q13:Q16) -> 581.18867
L19: Delta | M19: =M17 -> 223.93747 | N19: =N17-M17 -> 102.1184 | O19: =O17-N17 -> 167.93395 | P19: =P17-O17 -> -7.8332324 | Q19: =Q17-P17 -> 95.032088 | R19: =SUM(M19:Q19) -> 581.18867
B21: WACC | E21: =(E22/(E23+E22))*E30+(E23/(E23+E22))*(1-E27)*E28 -> 0.061673299
B22: Equity Value | D22: E | E22: 10560 | F22: (use the market cap, since this is the equity value * multiple it is assigned)
B23: Debt | D23: D | E23: ='BS Neu'!I46+'BS Neu'!I54 -> 3812 | F23: (all liabilities)
B24: Risk Free Rate | D24: R(f) | E24: 0.02628
B25: Equity Risk HAG | D25: R(m) | E25: 0.0703
B26: beta | D26: ß | E26: 1.07
B27: Tax Rate | D27: T | E27: =E12 -> 0.283 | I27: Cash (currently) | K27: ='BS Neu'!I26 -> 733
B28: Cost of Debt | D28: R(d) | E28: =('Debt & Cash'!K28+'Debt & Cash'!K42)/(('Debt & Cash'!K17+'Debt & Cash'!K12)/2) -> 0.040780367 | I28: Total Debt | K28: ='BS Neu'!I56 -> 3812
B29: Caulculation | D29: E/(E+D)*R( e) +D/(D+E)*(1-T)*R(d)
B30: Cost of Equity | D30: R (e ) | E30: =E24+E26*(E25-E24) -> 0.0733814 | I30: Exit Multiple (EV/EBITDA) | K30: =CHOOSE(E9, K32,K33)*K31 -> 9415.2564
I31: EBITDA | K31: =Q17 -> 581.18867
I32: Median Multiple | K32: ='Competitors KPI''s'!F18 -> 11.9
I33: Market Cap weighted Mean | K33: ='Competitors KPI''s'!F17 -> 16.2
B34: Terminal Value | E34: =(Q17*(1+E35))/(E21-E35) -> 11359.843
B35: Terminal Growth rate | E35: 0.01 | I35: Exit Multiple | K35: =K30 -> 9415.2564
B36: Net Present Value FCF | E36: =NPV(E21, M17,N17,O17,P17,Q17) -> 1726.5545 | I36: NPV Exit Multiple | K36: =K35/((1+E21)^5) -> 6980.3577
B37: Terminal Value | E37: =E34/(1+E21)^5 -> 8422.0507 | I37: NPV FCF | K37: =E36 -> 1726.5545
B38: Enterprise Value 1 | E38: =E37+E36 -> 10148.605 | I38: Enterprise Value 2 | K38: =K36+K37 -> 8706.9123
B39: (-) Net Debt | E39: =(K28-K27)*-1 -> -3079 | I39: (-) Net Debt | K39: =E39 -> -3079
B40: Equity Value | E40: =SUM(E38:E39) -> 7069.6053 | I40: Equity Value | K40: =SUM(K38:K39) -> 5627.9123
B42: Number of Shares | E42: 115.5
B44: Implied Share price 1 | E44: =E40/E42 -> 61.208704 | F44: € per Share | I44: Implied Share price 2 | K44: =K40/E42 -> 48.726513 | L44: € per Share
B47: Exit Multiple: | E47: =E38/Q17 -> 17.461809

Sheet Competitors KPI's
A1: =_xlfn.CONCAT(Inputs!C7, " - ", "Competitors", " - ", "in ", Inputs!C9, " ", Inputs!C10) -> HAG - Competitors - in Euro millions
D4: EV/Sales | F4: EV/EBITDA | H4: P/E
B5: Peer Group | D5: 2025 | E5: 2026E | F5: 2025 | G5: 2026E | H5: 2025 | I5: 2026E
B6: BAE Systems | D6: 1.5 | E6: 1.4 | F6: 11.6 | G6: 10.7 | H6: 17.6 | I6: 16
B7: Chemring Group PLC | D7: 1.9 | E7: 1.7 | F7: 11.2 | G7: 9.8 | H7: 17.7 | I7: 15.3
B8: Elbit Systems | D8: 1.9 | E8: 1.7 | F8: 17.6 | G8: 15.1 | H8: 30.8 | I8: 25.1
B9: General Dynamics | D9: 1.5 | E9: 1.4 | F9: 12.1 | G9: 11.1 | H9: 16.2 | I9: 14.1
B10: Indra Sistemas S.A. | D10: 0.6 | E10: 0.5 | F10: 5.1 | G10: 4.3 | H10: 10.1 | I10: 9.2
B11: Kongsberg Gruppen | D11: 3.7 | E11: 3.1 | F11: 22 | G11: 18.4 | H11: 34.1 | I11: 28.2
B12: Leonardo | D12: 1.2 | E12: 1.1 | F12: 10.1 | G12: 8.9 | H12: 20 | I12: 16.8
B13: Lockheer Martin | D13: 1.6 | E13: 1.6 | F13: 11.5 | G13: 11.1 | H13: 15.5 | I13: 14.2
B14: MTU Aero Engines | D14: 2.3 | E14: 2.1 | F14: 13.2 | G14: 11.9 | H14: 21.4 | I14: 19.2
B15: Rheinmetall | D15: 3.4 | E15: 2.6 | F15: 17.4 | G15: 12.8 | H15: 31 | I15: 22.2
B16: Thales | D16: 1.9 | E16: 1.7 | F16: 11.7 | G16: 10.6 | H16: 19.1 | I16: 17
B17: Defence (Mkt cap weighted mean) | D17: 2.5 | E17: 2.2 | F17: 16.2 | G17: 14 | H17: 25.1 | I17: 21.1
A18: x | B18: Defence (Median) | D18: 1.9 | E18: 1.7 | F18: 11.9 | G18: 10.9 | H18: 19.5 | I18: 16.9
B22: Company | C22: Revenue (Sales) | D22: Order Backlog (Book) | E22: Backlog-to-Sales Ratio | F22: Adj. EBITDA/EBIT Margin | G22: R&D as % of Revenue | H22: 1€ = 1,15 $
B23: Thales (Group) | C23: €20.6 Billion | D23: €50.6 Billion | E23: 2.46x | F23: 11.8% (Adj. EBIT Margin) | G23: 6.2% (Self-funded R&D: €1.274bn / €20.6bn) | H23: 1€ = 11 SEK
B24: Elbit Systems | C24: $6.8 Billion | D24: $22.6 Billion | E24: 3.31x | F24: 8.1% (Non-GAAP Operating Margin) | G24: 6.8% ($466.4m / $6.8bn) | H24: 1€ = 0,88 Pound
B25: L3Harris | C25: $21.3 Billion | D25: $34.0 Billion | E25: 1.60x | F25: 15.4% (Adj. Segment Operating Margin) | G25: ~2.0% (Capital Expenditures as % of sales) (1)
B26: BAE Systems (Group) | C26: £28.3 Billion | D26: £77.8 Billion | E26: 2.75x | F26: 10.7% (Underlying EBIT Margin: £3.015bn / £28.3bn) | G26: Significant (2)
B27: Leonardo (Group) | C27: €17.8 Billion | D27: €44.0 Billion | E27: 2.47x | F27: 8.6% (EBITA Margin: €1.525bn / €17.8bn) | G27: ~14.0% (€2.490bn / €17.8bn)
B28: SAAB | C28: SEK 63.8 Billion | D28: SEK 187 Billion | E28: 2.93x | F28: 13.1% (EBITDA Margin) | G28: Significant (4)
C30: Revenue | D30: Order Backlog | E30: Backlog-to-Sales Ratio | F30: Adj EBITDA/Ebit Margin | G30: R&D as % of Revenue
B31: Thales | C31: =D31/E31 -> 20.569106 | D31: 50.6 | E31: 2.46 | F31: 0.118 | G31: 0.062
B32: Elbit | C32: =D32/E32 -> 5.9372127 | D32: =22.6/1.15 -> 19.652174 | E32: 3.31 | F32: 0.081 | G32: 0.068
B33: L3Harris | C33: =D33/E33 -> 18.478261 | D33: =34/1.15 -> 29.565217 | E33: 1.6 | F33: 0.154 | G33: 0.02
B34: BAE Systems (Electronics) | C34: =D34/E34 -> 5.2479339 | D34: =12.7/0.88 -> 14.431818 | E34: 2.75 | F34: 0.107 | G34: =357/5200 -> 0.068653846
B35: Leonardo | C35: 3.7 | D35: 18.7 | E35: =D35/C35 -> 5.0540541 | F35: 0.086 | G35: 0.14
B36: SAAB | C36: =D36/E36 -> 5.8020478 | D36: =187/11 -> 17 | E36: 2.93 | F36: 0.131 | G36: =2809/63751 -> 0.044062054
B37: Hensoldt | C37: =D37/E37 -> 2.2222222 | D37: 6.6 | E37: 2.97 | F37: 0.194 | G37: 0.014
B39: Min | C39: =MIN(C31:C37) -> 2.2222222 | D39: =MIN(D31:D37) -> 6.6 | E39: =MIN(E31:E37) -> 1.6 | F39: =MIN(F31:F37) -> 0.081 | G39: =MIN(G31:G37) -> 0.014
B40: Max | C40: =MAX(C31:C37) -> 20.569106 | D40: =MAX(D31:D37) -> 50.6 | E40: =MAX(E31:E37) -> 5.0540541 | F40: =MAX(F31:F37) -> 0.194 | G40: =MAX(G31:G37) -> 0.14
C42: Revenue | D42: Order Backlog | E42: Backlog-to-Sales Ratio | F42: Adj EBITDA/Ebit Margin | G42: R&D as % of Revenue | H42: Competitive Ranking | I42: Rank
B43: Normalising the Data
B44: Thales | C44: =(C31-$C$39)/($C$40-$C$39) -> 1 | D44: =(D31-$D$39)/($D$40-$D$39) -> 1 | E44: =(E31-$E$39)/($E$40-$E$39) -> 0.24898279 | F44: =(F31-$F$39)/($F$40-$F$39) -> 0.32743363 | G44: =(G31-$G$39)/($G$40-$G$39) -> 0.38095238 | H44: =SUMPRODUCT(C44:G44) -> 2.9573688 | I44: =_xlfn.RANK.EQ(H44, $H$44:$H$50,0) -> 1
B45: Elbit | C45: =(C32-$C$39)/($C$40-$C$39) -> 0.20248619 | D45: =(D32-$D$39)/($D$40-$D$39) -> 0.29664032 | E45: =(E32-$E$39)/($E$40-$E$39) -> 0.49507042 | F45: =(F32-$F$39)/($F$40-$F$39) -> 0 | G45: =(G32-$G$39)/($G$40-$G$39) -> 0.42857143 | H45: =SUMPRODUCT(C45:G45) -> 1.4227684 | I45: =_xlfn.RANK.EQ(H45, $H$44:$H$50,0) -> 5
B46: L3Harris | C46: =(C33-$C$39)/($C$40-$C$39) -> 0.88603815 | D46: =(D33-$D$39)/($D$40-$D$39) -> 0.52193676 | E46: =(E33-$E$39)/($E$40-$E$39) -> 0 | F46: =(F33-$F$39)/($F$40-$F$39) -> 0.6460177 | G46: =(G33-$G$39)/($G$40-$G$39) -> 0.047619048 | H46: =SUMPRODUCT(C46:G46) -> 2.1016117 | I46: =_xlfn.RANK.EQ(H46, $H$44:$H$50,0) -> 3
B47: BAE Systems (Electronics) | C47: =(C34-$C$39)/($C$40-$C$39) -> 0.16491693 | D47: =(D34-$D$39)/($D$40-$D$39) -> 0.17799587 | E47: =(E34-$E$39)/($E$40-$E$39) -> 0.3329421 | F47: =(F34-$F$39)/($F$40-$F$39) -> 0.2300885 | G47: =(G34-$G$39)/($G$40-$G$39) -> 0.43376068 | H47: =SUMPRODUCT(C47:G47) -> 1.3397041 | I47: =_xlfn.RANK.EQ(H47, $H$44:$H$50,0) -> 7
B48: Leonardo | C48: =(C35-$C$39)/($C$40-$C$39) -> 0.080546529 | D48: =(D35-$D$39)/($D$40-$D$39) -> 0.275 | E48: =(E35-$E$39)/($E$40-$E$39) -> 1 | F48: =(F35-$F$39)/($F$40-$F$39) -> 0.044247788 | G48: =(G35-$G$39)/($G$40-$G$39) -> 1 | H48: =SUMPRODUCT(C48:G48) -> 2.3997943 | I48: =_xlfn.RANK.EQ(H48, $H$44:$H$50,0) -> 2
B49: SAAB | C49: =(C36-$C$39)/($C$40-$C$39) -> 0.195119 | D49: =(D36-$D$39)/($D$40-$D$39) -> 0.23636364 | E49: =(E36-$E$39)/($E$40-$E$39) -> 0.38505477 | F49: =(F36-$F$39)/($F$40-$F$39) -> 0.44247788 | G49: =(G36-$G$39)/($G$40-$G$39) -> 0.23858773 | H49: =SUMPRODUCT(C49:G49) -> 1.497603 | I49: =_xlfn.RANK.EQ(H49, $H$44:$H$50,0) -> 4
B50: Hensoldt | C50: =(C37-$C$39)/($C$40-$C$39) -> 0 | D50: =(D37-$D$39)/($D$40-$D$39) -> 0 | E50: =(E37-$E$39)/($E$40-$E$39) -> 0.39663537 | F50: =(F37-$F$39)/($F$40-$F$39) -> 1 | G50: =(G37-$G$39)/($G$40-$G$39) -> 0 | H50: =SUMPRODUCT(C50:G50) -> 1.3966354 | I50: =_xlfn.RANK.EQ(H50, $H$44:$H$50,0) -> 6
C56: Operating Segments
B57: Sensors | C57: 1910
B58: Optronics | C58: 334
C62: Geographic Locations
B63: Germany | C63: 1280
B64: Europe (excluding Germany) | C64: 684
B65: Middle East | C65: 83
B66: APAC | C66: 78
B67: North & South America | C67: 65
B68: Africa | C68: 48

Sheet IS
A1: =_xlfn.CONCAT(Inputs!C7, " - ", "Income Statement", " - ", "in ", Inputs!C9, " ", Inputs!C10) -> HAG - Income Statement - in Euro millions
B4: Financial year end | D4: =EDATE(Inputs!$C$8, D5*12) -> 43830 | E4: =EDATE(Inputs!$C$8, E5*12) -> 44196 | F4: =EDATE(Inputs!$C$8, F5*12) -> 44561 | G4: =EDATE(Inputs!$C$8, G5*12) -> 44926 | H4: =EDATE(Inputs!$C$8, H5*12) -> 45291 | I4: =EDATE(Inputs!$C$8, I5*12) -> 45657 | J4: =EDATE(Inputs!$C$8, J5*12) -> 46022 | K4: =EDATE(Inputs!$C$8, K5*12) -> 46387 | ... N4: =EDATE(Inputs!$C$8, N5*12) -> 47483
B5: Time-line counter | D5: -5 | E5: -4 | F5: -3 | G5: -2 | H5: -1 | I5: 0 | J5: 1 | K5: 2 | L5: 3 | M5: 4 | N5: 5
B6: Currency and units | D6: =_xlfn.CONCAT(Inputs!$C$9, " ", Inputs!$C$10) -> Euro millions | E6: =_xlfn.CONCAT(Inputs!$C$9, " ", Inputs!$C$10) -> Euro millions | F6: =_xlfn.CONCAT(Inputs!$C$9, " ", Inputs!$C$10) -> Euro millions | G6: =_xlfn.CONCAT(Inputs!$C$9, " ", Inputs!$C$10) -> Euro millions | H6: =_xlfn.CONCAT(Inputs!$C$9, " ", Inputs!$C$10) -> Euro millions | I6: =_xlfn.CONCAT(Inputs!$C$9, " ", Inputs!$C$10) -> Euro millions | J6: =_xlfn.CONCAT(Inputs!$C$9, " ", Inputs!$C$10) -> Euro millions | K6: =_xlfn.CONCAT(Inputs!$C$9, " ", Inputs!$C$10) -> Euro millions | ... N6: =_xlfn.CONCAT(Inputs!$C$9, " ", Inputs!$C$10) -> Euro millions
B7: Time-Stamp | D7: =IF(D5<=0, "Historical", "Forecasted") -> Historical | E7: =IF(E5<=0, "Historical", "Forecasted") -> Historical | F7: =IF(F5<=0, "Historical", "Forecasted") -> Historical | G7: =IF(G5<=0, "Historical", "Forecasted") -> Historical | H7: =IF(H5<=0, "Historical", "Forecasted") -> Historical | I7: =IF(I5<=0, "Historical", "Forecasted") -> Historical | J7: =IF(J5<=0, "Historical", "Forecasted") -> Forecasted | K7: =IF(K5<=0, "Historical", "Forecasted") -> Forecasted | ... N7: =IF(N5<=0, "Historical", "Forecasted") -> Forecasted
B9: Standardised Income Statement
B10: Revenue | D10: =D28 -> 1114.2 | E10: =E28 -> 1206.9 | F10: =F28 -> 1474 | G10: =G28 -> 1707 | H10: =H28 -> 1847 | I10: =I28 -> 2240 | J10: ='Revenue & Expenses (updated)'!M22 -> 2800 | K10: ='Revenue & Expenses (updated)'!N22 -> 2930.004 | L10: ='Revenue & Expenses (updated)'!O22 -> 3662.0577 | M10: ='Revenue & Expenses (updated)'!P22 -> 4236.7788 | N10: ='Revenue & Expenses (updated)'!Q22 -> 5090.2078 | P10: Assumptions & Relevant Data Points
B11: Cost of Sales | D11: =D29 -> -859.3 | E11: =E29 -> -936.1 | F11: =F29 -> -1144 | G11: =G29 -> -1314 | H11: =H29 -> -1427 | I11: =I29 -> -1732 | J11: ='Revenue & Expenses (updated)'!M45*-1 -> -1960 | K11: ='Revenue & Expenses (updated)'!N45*-1 -> -2021.7028 | L11: ='Revenue & Expenses (updated)'!O45*-1 -> -2490.1992 | M11: ='Revenue & Expenses (updated)'!P45*-1 -> -2881.0096 | N11: ='Revenue & Expenses (updated)'!Q45*-1 -> -3461.3413
B12: Gross Profit | D12: =SUM(D10:D11) -> 254.9 | E12: =SUM(E10:E11) -> 270.8 | F12: =SUM(F10:F11) -> 330 | G12: =SUM(G10:G11) -> 393 | H12: =SUM(H10:H11) -> 420 | I12: =SUM(I10:I11) -> 508 | J12: =SUM(J10:J11) -> 840 | K12: =SUM(K10:K11) -> 908.30124 | ... N12: =SUM(N10:N11) -> 1628.8665 | P12: Tax Rate as shown in Annual report is on average 28,3% in Germany,
B13: Operating R&D | D13: =SUMIF($J$28:$J$49, $B$13, $D$28:$D$49) -> -31 | E13: =SUMIF($J$28:$J$49, $B13, $E$28:$E$49) -> -25.1 | F13: =SUMIF($J$28:$J$49, $B13, $F$28:$F$49) -> -31 | G13: =SUMIF($J$28:$J$49, $B13, $G$28:$G$49) -> -36 | H13: =SUMIF($J$28:$J$49, $B13, $H$28:$H$49) -> -30 | I13: =SUMIF($J$28:$J$49, $B13, $I$28:$I$49) -> -32 | J13: ='Revenue & Expenses (updated)'!M49*-1 -> -112 | K13: ='Revenue & Expenses (updated)'!N49*-1 -> -117.20016 | L13: ='Revenue & Expenses (updated)'!O49*-1 -> -146.48231 | M13: ='Revenue & Expenses (updated)'!P49*-1 -> -169.47115 | N13: ='Revenue & Expenses (updated)'!Q49*-1 -> -203.60831 | P13: used here to forecast the income tax burden with deferred taxed being used in 2024 to reduce the tax burden
B14: Selling, General & Admin | D14: =SUMIF($J$28:$J$49, $B$14, $D$28:$D$49) -> -161.1 | E14: =SUMIF($J$28:$J$49, $B14, $E$28:$E$49) -> -177.4 | F14: =SUMIF($J$28:$J$49, $B14, $F$28:$F$49) -> -182 | G14: =SUMIF($J$28:$J$49, $B14, $G$28:$G$49) -> -199 | H14: =SUMIF($J$28:$J$49, $B14, $H$28:$H$49) -> -229 | I14: =SUMIF($J$28:$J$49, $B14, $I$28:$I$49) -> -290 | J14: ='Revenue & Expenses (updated)'!M47*-1 -> -252 | K14: ='Revenue & Expenses (updated)'!N47*-1 -> -263.70036 | L14: ='Revenue & Expenses (updated)'!O47*-1 -> -329.58519 | M14: ='Revenue & Expenses (updated)'!P47*-1 -> -381.31009 | N14: ='Revenue & Expenses (updated)'!Q47*-1 -> -458.1187
B15: EBITDA | D15: =D17+D16 -> #REF! | E15: =E17+E16 -> #REF! | F15: =F17+F16 -> #REF! | G15: =G17+G16 -> #REF! | H15: =H17+H16 -> #REF! | I15: =I17+I16 -> #REF! | J15: =SUM(J12:J14) -> 476 | K15: =SUM(K12:K14) -> 527.40072 | L15: =SUM(L12:L14) -> 695.79096 | M15: =SUM(M12:M14) -> 804.98798 | N15: =SUM(N12:N14) -> 967.13948 | P15: Other Non-Operating Income kept at 0 due to small impact/discretionary nature
B16: Depreciation & Amortisation | D16: =#REF! -> #REF! | E16: =#REF! -> #REF! | F16: =#REF! -> #REF! | G16: =#REF! -> #REF! | H16: =#REF! -> #REF! | I16: =#REF! -> #REF! | J16: ='FA-Forecast (updated)'!M74 -> 255.0373 | K16: ='FA-Forecast (updated)'!N74 -> 262.98997 | L16: ='FA-Forecast (updated)'!O74 -> 271.6455 | M16: ='FA-Forecast (updated)'!P74 -> 288.85834 | N16: ='FA-Forecast (updated)'!Q74 -> 311.58634
B17: EBIT | D17: =SUM(D12,D13:D14) -> 62.8 | E17: =SUM(E12,E13:E14) -> 68.3 | F17: =SUM(F12,F13:F14) -> 117 | G17: =SUM(G12,G13:G14) -> 158 | H17: =SUM(H12,H13:H14) -> 161 | I17: =SUM(I12,I13:I14) -> 186 | J17: =J15-J16 -> 220.9627 | K17: =K15-K16 -> 264.41075 | L17: =L15-L16 -> 424.14547 | M17: =M15-M16 -> 516.12963 | N17: =N15-N16 -> 655.55314
B18: Other Non Operating Income/Expense (net) | D18: =SUMIF($J$28:$J$49, $B$18, $D$28:$D$49) -> -2.6 | E18: =SUMIF($J$28:$J$49, $B$18, $E$28:$E$49) -> -9.8 | F18: =SUMIF($J$28:$J$49, $B18, $F$28:$F$49) -> 6 | G18: =SUMIF($J$28:$J$49, $B18, $G$28:$G$49) -> 7 | H18: =SUMIF($J$28:$J$49, $B18, $H$28:$H$49) -> -1 | I18: =SUMIF($J$28:$J$49, $B18, $I$28:$I$49) -> -1 | J18: ='Revenue & Expenses (updated)'!M79 -> 0 | K18: ='Revenue & Expenses (updated)'!N79 -> 0 | L18: ='Revenue & Expenses (updated)'!O79 -> 0 | M18: ='Revenue & Expenses (updated)'!P79 -> 0 | N18: ='Revenue & Expenses (updated)'!Q79 -> 0
B19: Net intrest income/loss | D19: =SUMIF($J$28:$J$49, $B$19, $D$28:$D$49) -> -24.6 | E19: =SUMIF($J$28:$J$49, $B$19, $E$28:$E$49) -> -133.7 | F19: =SUMIF($J$28:$J$49, $B19, $F$28:$F$49) -> -38 | G19: =SUMIF($J$28:$J$49, $B19, $G$28:$G$49) -> -35 | H19: =SUMIF($J$28:$J$49, $B19, $H$28:$H$49) -> -64 | I19: =SUMIF($J$28:$J$49, $B19, $I$28:$I$49) -> -69 | J19: ='Debt & Cash'!K55 -> -30.54552 | K19: ='Debt & Cash'!L55 -> -45.397016 | L19: ='Debt & Cash'!M55 -> -47.472527 | M19: ='Debt & Cash'!N55 -> -29.452679 | N19: ='Debt & Cash'!O55 -> -30.124391
B20: EBT | D20: =D17+SUM(D18:D19) -> 35.6 | E20: =E17+SUM(E18:E19) -> -75.2 | F20: =F17+SUM(F18:F19) -> 85 | G20: =G17+SUM(G18:G19) -> 130 | H20: =H17+SUM(H18:H19) -> 96 | I20: =I17+SUM(I18:I19) -> 116 | J20: =SUM(J17:J19) -> 190.41718 | K20: =SUM(K17:K19) -> 219.01373 | L20: =SUM(L17:L19) -> 376.67294 | M20: =SUM(M17:M19) -> 486.67696 | N20: =SUM(N17:N19) -> 625.42875
B21: Income Taxes | D21: =SUMIF($J$28:$J$49, $B$21, $D$28:$D$49) -> -27.4 | E21: =SUMIF($J$28:$J$49, $B$21, $E$28:$E$49) -> 10.7 | F21: =SUMIF($J$28:$J$49, $B21, $F$28:$F$49) -> -22 | G21: =SUMIF($J$28:$J$49, $B21, $G$28:$G$49) -> -49 | H21: =SUMIF($J$28:$J$49, $B21, $H$28:$H$49) -> -36 | I21: =SUMIF($J$28:$J$49, $B21, $I$28:$I$49) -> -12 | J21: =IF(J20>0, J20*$C$23*-1, 0) -> -53.888062 | K21: =IF(K20>0, K20*$C$23*-1, 0) -> -61.980886 | L21: =IF(L20>0, L20*$C$23*-1, 0) -> -106.59844 | M21: =IF(M20>0, M20*$C$23*-1, 0) -> -137.72958 | N21: =IF(N20>0, N20*$C$23*-1, 0) -> -176.99634
B22: Net Income | D22: =SUM(D20:D21) -> 8.2 | E22: =SUM(E20:E21) -> -64.5 | F22: =SUM(F20:F21) -> 63 | G22: =SUM(G20:G21) -> 81 | H22: =SUM(H20:H21) -> 60 | I22: =SUM(I20:I21) -> 104 | J22: =SUM(J20:J21) -> 136.52912 | K22: =SUM(K20:K21) -> 157.03285 | ... N22: =SUM(N20:N21) -> 448.43242
B23: Income Tax Rate | C23: 0.283 | D23: =D21/D20 -> -0.76966292 | E23: =E21/E20 -> -0.14228723 | F23: =F21/F20 -> -0.25882353 | G23: =G21/G20 -> -0.37692308 | H23: =H21/H20 -> -0.375 | I23: =I21/I20 -> -0.10344828 | J23: =J21/J20 -> -0.283 | K23: =K21/K20 -> -0.283 | ... N23: =N21/N20 -> -0.283
B25: Reported Income Statement
B27: 2024-2019 | D27: 2019 | E27: 2020 | F27: 2021 | G27: 2022 | H27: 2023 | I27: 2024
B28: Revenue | D28: 1114.2 | E28: 1206.9 | F28: 1474 | G28: 1707 | H28: 1847 | I28: 2240 | J28: Revenue
B29: Cost of sales | D29: -859.3 | E29: -936.1 | F29: -1144 | G29: -1314 | H29: -1427 | I29: -1732 | J29: Cost of Sales
B30: Gross profit | D30: 254.9 | E30: 270.8 | F30: 330 | G30: 393 | H30: 420 | I30: 508 | J30: Gross Profit
B31: Selling and distribution expenses | D31: -84.8 | E31: -90.2 | F31: -99 | G31: -107 | H31: -111 | I31: -128 | J31: Selling, General & Admin
B32: General administrative expenses | D32: -76.3 | E32: -87.2 | F32: -83 | G32: -92 | H32: -118 | I32: -162 | J32: Selling, General & Admin
B33: Research and development costs | D33: -31 | E33: -25.1 | F33: -31 | G33: -36 | H33: -30 | I33: -32 | J33: Operating R&D
B34: Other operating income | D34: 25.3 | E34: 18.9 | F34: 29 | G34: 21 | H34: 22 | I34: 22 | J34: Other Non Operating Income/Expense (net)
B35: Other operating expenses | D35: -24.8 | E35: -16.1 | F35: -18 | G35: -21 | H35: -21 | I35: -24 | J35: Other Non Operating Income/Expense (net)
B36: Share of profit / loss from investments accounted for using the equity method | D36: -1.2 | E36: -2.6 | F36: -2 | G36: 0 | H36: 0 | I36: 3 | J36: Other Non Operating Income/Expense (net)
B37: Other income / expense from investments | D37: 0 | E37: 0 | F37: 0 | G37: 8 | H37: 5 | I37: -3 | J37: Other Non Operating Income/Expense (net)
B38: Earnings before financial result and income taxes (EBIT) | D38: 62.1 | E38: 68.5 | F38: 126 | G38: 166 | H38: 166 | I38: 185
B39: Interest income | D39: 58.9 | E39: 4 | F39: 4 | G39: 9 | H39: 18 | I39: 31 | J39: Net intrest income/loss
B40: Interest expense | D40: -83.5 | E40: -137.7 | F40: -42 | G40: -44 | H40: -82 | I40: -100 | J40: Net intrest income/loss
B41: Other finance income / cost | D41: -1.9 | E41: -10 | F41: -3 | G41: -1 | H41: -7 | I41: 1 | J41: Other Non Operating Income/Expense (net)
B42: Finance result | D42: -26.5 | E42: -143.7 | F42: -41 | G42: -37 | H42: -72 | I42: -68
B43: Earnings before income taxes (EBT) | D43: 35.6 | E43: -75.2 | F43: 85 | G43: 130 | H43: 94 | I43: 117
B44: Income taxes | D44: -27.4 | E44: 10.7 | F44: -22 | G44: -49 | H44: -36 | I44: -12 | J44: Income Taxes
B45: Group profit / loss | D45: 8.2 | E45: -64.5 | F45: 63 | G45: 80 | H45: 58 | I45: 106
B46: thereof attributable to the owners of HENSOLDT AG | D46: 5.9 | E46: -65.2 | F46: 63 | G46: 78 | H46: 56 | I46: 108
B47: thereof attributable to non-controlling interests | D47: 2.3 | E47: 0.7 | F47: 0 | G47: 2 | H47: 2 | I47: -2
B48: Earnings per share
B49: Basic and diluted earnings per share (EUR) | D49: 0.07 | E49: -0.75 | F49: 0.6 | G49: 0.75 | H49: 0.53 | I49: 0.93
